{"distrito":{"id":"julio_de_castilhos_soja","nome":"JULIO DE CASTILHOS-SOJA","regional":"RS SOJA","codigo_regional":"RSSO","uf":"RS","ufs":["RS"],"cultura_principal":"soja"},"gerado_em":"2026-07-22T05:27:13+00:00","municipios":[{"id":"augusto_pestana","nome":"AUGUSTO PESTANA","ibge":4301503,"uf":"RS","lat":-28.5172,"lon":-53.9883,"area_soja_ha":20120,"clima":{"ibge":4301503,"nome":"AUGUSTO PESTANA","uf":"RS","lat":-28.5172,"lon":-53.9883,"atual":{"tmax":18.1,"tmin":13.4,"precip_mm":0.7,"prob_chuva":41,"weathercode":51,"tempo":"garoa"},"previsao_7d":[{"data":"2026-07-22","tmax":18.1,"tmin":13.4,"precip_mm":0.7,"prob_chuva":41,"weathercode":51,"tempo":"garoa","vento_kmh":19.8,"rajada_kmh":36.4,"vento_dir_graus":190,"et0_mm":0.79},{"data":"2026-07-23","tmax":18.2,"tmin":12.5,"precip_mm":0.0,"prob_chuva":2,"weathercode":3,"tempo":"nuvem","vento_kmh":23.2,"rajada_kmh":43.6,"vento_dir_graus":123,"et0_mm":2.08},{"data":"2026-07-24","tmax":21.7,"tmin":11.1,"precip_mm":1.2,"prob_chuva":31,"weathercode":51,"tempo":"garoa","vento_kmh":17.2,"rajada_kmh":30.6,"vento_dir_graus":114,"et0_mm":1.99},{"data":"2026-07-25","tmax":22.1,"tmin":11.4,"precip_mm":0.0,"prob_chuva":6,"weathercode":3,"tempo":"nuvem","vento_kmh":11.8,"rajada_kmh":20.5,"vento_dir_graus":100,"et0_mm":1.88},{"data":"2026-07-26","tmax":20.7,"tmin":16.0,"precip_mm":15.6,"prob_chuva":44,"weathercode":95,"tempo":"trovoada","vento_kmh":11.3,"rajada_kmh":26.6,"vento_dir_graus":15,"et0_mm":0.87},{"data":"2026-07-27","tmax":19.4,"tmin":16.9,"precip_mm":40.5,"prob_chuva":82,"weathercode":96,"tempo":"trovoada","vento_kmh":15.9,"rajada_kmh":36.4,"vento_dir_graus":27,"et0_mm":0.42},{"data":"2026-07-28","tmax":19.7,"tmin":16.9,"precip_mm":39.6,"prob_chuva":78,"weathercode":95,"tempo":"trovoada","vento_kmh":21.3,"rajada_kmh":47.2,"vento_dir_graus":34,"et0_mm":0.82}],"fonte":"Open-Meteo","atualizado_em":"2026-07-22T05:27:13Z"},"colheita":{"pct_plantado":100.0,"pct_colhido":100.0,"area_soja_ha":20120,"fonte":"Emater/RS-Ascar - Informativo Conjuntural (fechamento)","data_referencia":"2026-05-14","granularidade":"regional (Ijuí) aplicado ao municipio","regiao":"Ijuí","derivado":true,"ha_plantado_estim":20120,"ha_colhido_estim":20120}},{"id":"boa_vista_do_cadeado","nome":"BOA VISTA DO CADEADO","ibge":4302220,"uf":"RS","lat":-28.5791,"lon":-53.8108,"area_soja_ha":41200,"clima":{"ibge":4302220,"nome":"BOA VISTA DO CADEADO","uf":"RS","lat":-28.5791,"lon":-53.8108,"atual":{"tmax":17.7,"tmin":13.2,"precip_mm":0.4,"prob_chuva":59,"weathercode":51,"tempo":"garoa"},"previsao_7d":[{"data":"2026-07-22","tmax":17.7,"tmin":13.2,"precip_mm":0.4,"prob_chuva":59,"weathercode":51,"tempo":"garoa","vento_kmh":23.1,"rajada_kmh":41.4,"vento_dir_graus":184,"et0_mm":0.81},{"data":"2026-07-23","tmax":17.8,"tmin":12.5,"precip_mm":0.0,"prob_chuva":0,"weathercode":3,"tempo":"nuvem","vento_kmh":22.6,"rajada_kmh":43.2,"vento_dir_graus":122,"et0_mm":1.97},{"data":"2026-07-24","tmax":21.3,"tmin":11.0,"precip_mm":0.5,"prob_chuva":27,"weathercode":51,"tempo":"garoa","vento_kmh":19.3,"rajada_kmh":33.1,"vento_dir_graus":103,"et0_mm":1.96},{"data":"2026-07-25","tmax":21.8,"tmin":11.7,"precip_mm":0.3,"prob_chuva":6,"weathercode":51,"tempo":"garoa","vento_kmh":12.4,"rajada_kmh":21.2,"vento_dir_graus":95,"et0_mm":1.75},{"data":"2026-07-26","tmax":20.1,"tmin":16.1,"precip_mm":19.2,"prob_chuva":45,"weathercode":95,"tempo":"trovoada","vento_kmh":14.8,"rajada_kmh":30.2,"vento_dir_graus":18,"et0_mm":0.93},{"data":"2026-07-27","tmax":19.3,"tmin":16.9,"precip_mm":41.0,"prob_chuva":80,"weathercode":95,"tempo":"trovoada","vento_kmh":18.1,"rajada_kmh":40.7,"vento_dir_graus":14,"et0_mm":0.43},{"data":"2026-07-28","tmax":20.0,"tmin":16.4,"precip_mm":41.8,"prob_chuva":75,"weathercode":95,"tempo":"trovoada","vento_kmh":19.0,"rajada_kmh":52.9,"vento_dir_graus":26,"et0_mm":0.8}],"fonte":"Open-Meteo","atualizado_em":"2026-07-22T05:27:13Z"},"colheita":{"pct_plantado":100.0,"pct_colhido":100.0,"area_soja_ha":41200,"fonte":"Emater/RS-Ascar - Informativo Conjuntural (fechamento)","data_referencia":"2026-05-14","granularidade":"regional (Ijuí) aplicado ao municipio","regiao":"Ijuí","derivado":true,"ha_plantado_estim":41200,"ha_colhido_estim":41200}},{"id":"boa_vista_do_incra","nome":"BOA VISTA DO INCRA","ibge":4302238,"uf":"RS","lat":-28.8185,"lon":-53.391,"area_soja_ha":31200,"clima":{"ibge":4302238,"nome":"BOA VISTA DO INCRA","uf":"RS","lat":-28.8185,"lon":-53.391,"atual":{"tmax":17.1,"tmin":13.0,"precip_mm":0.4,"prob_chuva":55,"weathercode":51,"tempo":"garoa"},"previsao_7d":[{"data":"2026-07-22","tmax":17.1,"tmin":13.0,"precip_mm":0.4,"prob_chuva":55,"weathercode":51,"tempo":"garoa","vento_kmh":22.1,"rajada_kmh":42.1,"vento_dir_graus":198,"et0_mm":0.72},{"data":"2026-07-23","tmax":17.5,"tmin":12.2,"precip_mm":0.0,"prob_chuva":8,"weathercode":3,"tempo":"nuvem","vento_kmh":20.7,"rajada_kmh":38.9,"vento_dir_graus":128,"et0_mm":1.72},{"data":"2026-07-24","tmax":20.8,"tmin":10.8,"precip_mm":1.3,"prob_chuva":37,"weathercode":51,"tempo":"garoa","vento_kmh":13.2,"rajada_kmh":25.2,"vento_dir_graus":84,"et0_mm":1.94},{"data":"2026-07-25","tmax":20.3,"tmin":11.9,"precip_mm":0.3,"prob_chuva":8,"weathercode":51,"tempo":"garoa","vento_kmh":7.7,"rajada_kmh":17.6,"vento_dir_graus":85,"et0_mm":1.53},{"data":"2026-07-26","tmax":21.1,"tmin":14.3,"precip_mm":9.9,"prob_chuva":45,"weathercode":55,"tempo":"garoa","vento_kmh":23.2,"rajada_kmh":44.3,"vento_dir_graus":356,"et0_mm":1.29},{"data":"2026-07-27","tmax":19.1,"tmin":16.9,"precip_mm":29.2,"prob_chuva":82,"weathercode":95,"tempo":"trovoada","vento_kmh":19.0,"rajada_kmh":42.5,"vento_dir_graus":358,"et0_mm":0.56},{"data":"2026-07-28","tmax":20.3,"tmin":16.0,"precip_mm":48.8,"prob_chuva":76,"weathercode":96,"tempo":"trovoada","vento_kmh":16.8,"rajada_kmh":43.9,"vento_dir_graus":12,"et0_mm":0.84}],"fonte":"Open-Meteo","atualizado_em":"2026-07-22T05:27:13Z"},"colheita":{"pct_plantado":100.0,"pct_colhido":100.0,"area_soja_ha":31200,"fonte":"Emater/RS-Ascar - Informativo Conjuntural (fechamento)","data_referencia":"2026-05-14","granularidade":"regional (Ijuí) aplicado ao municipio","regiao":"Ijuí","derivado":true,"ha_plantado_estim":31200,"ha_colhido_estim":31200}},{"id":"cruz_alta","nome":"CRUZ ALTA","ibge":4306106,"uf":"RS","lat":-28.645,"lon":-53.6048,"area_soja_ha":92400,"clima":{"ibge":4306106,"nome":"CRUZ ALTA","uf":"RS","lat":-28.645,"lon":-53.6048,"atual":{"tmax":17.4,"tmin":12.9,"precip_mm":0.7,"prob_chuva":55,"weathercode":51,"tempo":"garoa"},"previsao_7d":[{"data":"2026-07-22","tmax":17.4,"tmin":12.9,"precip_mm":0.7,"prob_chuva":55,"weathercode":51,"tempo":"garoa","vento_kmh":22.1,"rajada_kmh":41.4,"vento_dir_graus":191,"et0_mm":0.71},{"data":"2026-07-23","tmax":17.4,"tmin":12.2,"precip_mm":0.2,"prob_chuva":8,"weathercode":51,"tempo":"garoa","vento_kmh":21.4,"rajada_kmh":41.4,"vento_dir_graus":126,"et0_mm":1.77},{"data":"2026-07-24","tmax":20.7,"tmin":10.8,"precip_mm":0.7,"prob_chuva":37,"weathercode":51,"tempo":"garoa","vento_kmh":17.0,"rajada_kmh":29.9,"vento_dir_graus":89,"et0_mm":1.92},{"data":"2026-07-25","tmax":20.9,"tmin":11.5,"precip_mm":0.0,"prob_chuva":8,"weathercode":3,"tempo":"nuvem","vento_kmh":10.3,"rajada_kmh":18.4,"vento_dir_graus":93,"et0_mm":1.58},{"data":"2026-07-26","tmax":20.2,"tmin":15.3,"precip_mm":23.1,"prob_chuva":45,"weathercode":95,"tempo":"trovoada","vento_kmh":18.9,"rajada_kmh":37.4,"vento_dir_graus":3,"et0_mm":1.11},{"data":"2026-07-27","tmax":19.1,"tmin":16.9,"precip_mm":43.3,"prob_chuva":82,"weathercode":96,"tempo":"trovoada","vento_kmh":25.0,"rajada_kmh":46.1,"vento_dir_graus":360,"et0_mm":0.52},{"data":"2026-07-28","tmax":20.0,"tmin":16.0,"precip_mm":44.6,"prob_chuva":76,"weathercode":95,"tempo":"trovoada","vento_kmh":20.4,"rajada_kmh":55.1,"vento_dir_graus":6,"et0_mm":0.91}],"fonte":"Open-Meteo","atualizado_em":"2026-07-22T05:27:13Z"},"colheita":{"pct_plantado":100.0,"pct_colhido":100.0,"area_soja_ha":92400,"fonte":"Emater/RS-Ascar - Informativo Conjuntural (fechamento)","data_referencia":"2026-05-14","granularidade":"regional (Ijuí) aplicado ao municipio","regiao":"Ijuí","derivado":true,"ha_plantado_estim":92400,"ha_colhido_estim":92400}},{"id":"entre_ijuis","nome":"ENTRE-IJUÍS","ibge":4306932,"uf":"RS","lat":-28.3686,"lon":-54.2686,"area_soja_ha":35098,"clima":{"ibge":4306932,"nome":"ENTRE-IJUÍS","uf":"RS","lat":-28.3686,"lon":-54.2686,"atual":{"tmax":18.3,"tmin":14.9,"precip_mm":0.4,"prob_chuva":53,"weathercode":51,"tempo":"garoa"},"previsao_7d":[{"data":"2026-07-22","tmax":18.3,"tmin":14.9,"precip_mm":0.4,"prob_chuva":53,"weathercode":51,"tempo":"garoa","vento_kmh":16.3,"rajada_kmh":32.0,"vento_dir_graus":206,"et0_mm":0.85},{"data":"2026-07-23","tmax":19.5,"tmin":12.7,"precip_mm":0.0,"prob_chuva":0,"weathercode":3,"tempo":"nuvem","vento_kmh":21.2,"rajada_kmh":42.8,"vento_dir_graus":120,"et0_mm":2.21},{"data":"2026-07-24","tmax":22.5,"tmin":10.8,"precip_mm":0.3,"prob_chuva":22,"weathercode":51,"tempo":"garoa","vento_kmh":13.5,"rajada_kmh":24.5,"vento_dir_graus":125,"et0_mm":2.14},{"data":"2026-07-25","tmax":23.3,"tmin":11.3,"precip_mm":0.0,"prob_chuva":10,"weathercode":3,"tempo":"nuvem","vento_kmh":10.6,"rajada_kmh":20.5,"vento_dir_graus":98,"et0_mm":1.96},{"data":"2026-07-26","tmax":22.5,"tmin":16.1,"precip_mm":7.8,"prob_chuva":46,"weathercode":95,"tempo":"trovoada","vento_kmh":15.0,"rajada_kmh":33.1,"vento_dir_graus":3,"et0_mm":1.2},{"data":"2026-07-27","tmax":19.4,"tmin":17.4,"precip_mm":49.4,"prob_chuva":77,"weathercode":96,"tempo":"trovoada","vento_kmh":12.9,"rajada_kmh":41.4,"vento_dir_graus":40,"et0_mm":0.48},{"data":"2026-07-28","tmax":20.3,"tmin":17.0,"precip_mm":45.4,"prob_chuva":74,"weathercode":95,"tempo":"trovoada","vento_kmh":21.6,"rajada_kmh":44.3,"vento_dir_graus":38,"et0_mm":0.91}],"fonte":"Open-Meteo","atualizado_em":"2026-07-22T05:27:13Z"},"colheita":{"pct_plantado":100.0,"pct_colhido":100.0,"area_soja_ha":35098,"fonte":"Emater/RS-Ascar - Informativo Conjuntural (fechamento)","data_referencia":"2026-05-14","granularidade":"regional (Ijuí) aplicado ao municipio","regiao":"Ijuí","derivado":true,"ha_plantado_estim":35098,"ha_colhido_estim":35098}},{"id":"eugenio_de_castro","nome":"EUGÊNIO DE CASTRO","ibge":4307831,"uf":"RS","lat":-28.5315,"lon":-54.1506,"area_soja_ha":29500,"clima":{"ibge":4307831,"nome":"EUGÊNIO DE CASTRO","uf":"RS","lat":-28.5315,"lon":-54.1506,"atual":{"tmax":17.7,"tmin":13.6,"precip_mm":0.4,"prob_chuva":37,"weathercode":51,"tempo":"garoa"},"previsao_7d":[{"data":"2026-07-22","tmax":17.7,"tmin":13.6,"precip_mm":0.4,"prob_chuva":37,"weathercode":51,"tempo":"garoa","vento_kmh":18.3,"rajada_kmh":32.0,"vento_dir_graus":191,"et0_mm":0.82},{"data":"2026-07-23","tmax":18.4,"tmin":12.1,"precip_mm":0.0,"prob_chuva":0,"weathercode":3,"tempo":"nuvem","vento_kmh":23.7,"rajada_kmh":44.3,"vento_dir_graus":122,"et0_mm":2.08},{"data":"2026-07-24","tmax":21.8,"tmin":10.9,"precip_mm":0.2,"prob_chuva":18,"weathercode":51,"tempo":"garoa","vento_kmh":16.7,"rajada_kmh":29.5,"vento_dir_graus":121,"et0_mm":2.07},{"data":"2026-07-25","tmax":22.5,"tmin":11.3,"precip_mm":0.0,"prob_chuva":3,"weathercode":3,"tempo":"nuvem","vento_kmh":12.0,"rajada_kmh":20.5,"vento_dir_graus":97,"et0_mm":1.95},{"data":"2026-07-26","tmax":21.1,"tmin":15.8,"precip_mm":7.2,"prob_chuva":47,"weathercode":53,"tempo":"garoa","vento_kmh":17.0,"rajada_kmh":33.1,"vento_dir_graus":12,"et0_mm":1.03},{"data":"2026-07-27","tmax":19.2,"tmin":17.1,"precip_mm":41.6,"prob_chuva":80,"weathercode":96,"tempo":"trovoada","vento_kmh":15.0,"rajada_kmh":41.4,"vento_dir_graus":31,"et0_mm":0.47},{"data":"2026-07-28","tmax":19.6,"tmin":16.9,"precip_mm":40.6,"prob_chuva":79,"weathercode":95,"tempo":"trovoada","vento_kmh":23.4,"rajada_kmh":48.2,"vento_dir_graus":38,"et0_mm":0.81}],"fonte":"Open-Meteo","atualizado_em":"2026-07-22T05:27:13Z"},"colheita":{"pct_plantado":100.0,"pct_colhido":100.0,"area_soja_ha":29500,"fonte":"Emater/RS-Ascar - Informativo Conjuntural (fechamento)","data_referencia":"2026-05-14","granularidade":"regional (Ijuí) aplicado ao municipio","regiao":"Ijuí","derivado":true,"ha_plantado_estim":29500,"ha_colhido_estim":29500}},{"id":"jaguari","nome":"JAGUARI","ibge":4311106,"uf":"RS","lat":-29.4936,"lon":-54.703,"area_soja_ha":13800,"clima":{"ibge":4311106,"nome":"JAGUARI","uf":"RS","lat":-29.4936,"lon":-54.703,"atual":{"tmax":16.9,"tmin":12.3,"precip_mm":4.6,"prob_chuva":76,"weathercode":80,"tempo":"chuva"},"previsao_7d":[{"data":"2026-07-22","tmax":16.9,"tmin":12.3,"precip_mm":4.6,"prob_chuva":76,"weathercode":80,"tempo":"chuva","vento_kmh":18.9,"rajada_kmh":38.9,"vento_dir_graus":187,"et0_mm":0.66},{"data":"2026-07-23","tmax":17.2,"tmin":9.2,"precip_mm":0.2,"prob_chuva":4,"weathercode":51,"tempo":"garoa","vento_kmh":15.9,"rajada_kmh":37.8,"vento_dir_graus":123,"et0_mm":1.37},{"data":"2026-07-24","tmax":18.8,"tmin":9.6,"precip_mm":0.0,"prob_chuva":6,"weathercode":3,"tempo":"nuvem","vento_kmh":13.8,"rajada_kmh":30.6,"vento_dir_graus":133,"et0_mm":1.88},{"data":"2026-07-25","tmax":21.2,"tmin":10.1,"precip_mm":0.0,"prob_chuva":2,"weathercode":3,"tempo":"nuvem","vento_kmh":10.6,"rajada_kmh":26.3,"vento_dir_graus":108,"et0_mm":1.66},{"data":"2026-07-26","tmax":20.7,"tmin":15.3,"precip_mm":6.5,"prob_chuva":41,"weathercode":53,"tempo":"garoa","vento_kmh":6.9,"rajada_kmh":23.4,"vento_dir_graus":170,"et0_mm":1.01},{"data":"2026-07-27","tmax":21.0,"tmin":17.9,"precip_mm":18.5,"prob_chuva":83,"weathercode":95,"tempo":"trovoada","vento_kmh":17.8,"rajada_kmh":46.1,"vento_dir_graus":14,"et0_mm":0.82},{"data":"2026-07-28","tmax":22.6,"tmin":16.8,"precip_mm":31.2,"prob_chuva":78,"weathercode":96,"tempo":"trovoada","vento_kmh":14.9,"rajada_kmh":37.8,"vento_dir_graus":12,"et0_mm":1.15}],"fonte":"Open-Meteo","atualizado_em":"2026-07-22T05:27:13Z"},"colheita":{"pct_plantado":100.0,"pct_colhido":100.0,"area_soja_ha":13800,"fonte":"Emater/RS-Ascar - Informativo Conjuntural (fechamento)","data_referencia":"2026-05-14","granularidade":"regional (Santa Maria) aplicado ao municipio","regiao":"Santa Maria","derivado":true,"ha_plantado_estim":13800,"ha_colhido_estim":13800}},{"id":"jari","nome":"JARI","ibge":4311130,"uf":"RS","lat":-29.2922,"lon":-54.2237,"area_soja_ha":54000,"clima":{"ibge":4311130,"nome":"JARI","uf":"RS","lat":-29.2922,"lon":-54.2237,"atual":{"tmax":16.1,"tmin":11.5,"precip_mm":4.2,"prob_chuva":67,"weathercode":53,"tempo":"garoa"},"previsao_7d":[{"data":"2026-07-22","tmax":16.1,"tmin":11.5,"precip_mm":4.2,"prob_chuva":67,"weathercode":53,"tempo":"garoa","vento_kmh":25.2,"rajada_kmh":43.2,"vento_dir_graus":178,"et0_mm":0.57},{"data":"2026-07-23","tmax":16.6,"tmin":10.2,"precip_mm":0.2,"prob_chuva":0,"weathercode":51,"tempo":"garoa","vento_kmh":22.8,"rajada_kmh":40.3,"vento_dir_graus":124,"et0_mm":1.37},{"data":"2026-07-24","tmax":20.0,"tmin":10.1,"precip_mm":0.2,"prob_chuva":8,"weathercode":51,"tempo":"garoa","vento_kmh":19.6,"rajada_kmh":31.7,"vento_dir_graus":100,"et0_mm":1.88},{"data":"2026-07-25","tmax":20.4,"tmin":9.6,"precip_mm":0.0,"prob_chuva":3,"weathercode":3,"tempo":"nuvem","vento_kmh":12.7,"rajada_kmh":22.0,"vento_dir_graus":71,"et0_mm":2.02},{"data":"2026-07-26","tmax":21.0,"tmin":15.1,"precip_mm":20.4,"prob_chuva":39,"weathercode":96,"tempo":"trovoada","vento_kmh":17.7,"rajada_kmh":37.4,"vento_dir_graus":360,"et0_mm":1.42},{"data":"2026-07-27","tmax":19.7,"tmin":17.0,"precip_mm":24.5,"prob_chuva":89,"weathercode":96,"tempo":"trovoada","vento_kmh":22.4,"rajada_kmh":54.0,"vento_dir_graus":354,"et0_mm":0.76},{"data":"2026-07-28","tmax":19.8,"tmin":16.8,"precip_mm":42.4,"prob_chuva":80,"weathercode":95,"tempo":"trovoada","vento_kmh":18.0,"rajada_kmh":38.5,"vento_dir_graus":13,"et0_mm":0.76}],"fonte":"Open-Meteo","atualizado_em":"2026-07-22T05:27:13Z"},"colheita":{"pct_plantado":100.0,"pct_colhido":100.0,"area_soja_ha":54000,"fonte":"Emater/RS-Ascar - Informativo Conjuntural (fechamento)","data_referencia":"2026-05-14","granularidade":"regional (Santa Maria) aplicado ao municipio","regiao":"Santa Maria","derivado":true,"ha_plantado_estim":54000,"ha_colhido_estim":54000}},{"id":"joia","nome":"JÓIA","ibge":4311155,"uf":"RS","lat":-28.6435,"lon":-54.1141,"area_soja_ha":82900,"clima":{"ibge":4311155,"nome":"JÓIA","uf":"RS","lat":-28.6435,"lon":-54.1141,"atual":{"tmax":17.5,"tmin":13.0,"precip_mm":0.8,"prob_chuva":45,"weathercode":51,"tempo":"garoa"},"previsao_7d":[{"data":"2026-07-22","tmax":17.5,"tmin":13.0,"precip_mm":0.8,"prob_chuva":45,"weathercode":51,"tempo":"garoa","vento_kmh":21.1,"rajada_kmh":37.8,"vento_dir_graus":183,"et0_mm":0.85},{"data":"2026-07-23","tmax":18.1,"tmin":11.5,"precip_mm":0.0,"prob_chuva":0,"weathercode":3,"tempo":"nuvem","vento_kmh":23.6,"rajada_kmh":44.3,"vento_dir_graus":120,"et0_mm":1.94},{"data":"2026-07-24","tmax":21.4,"tmin":10.6,"precip_mm":0.0,"prob_chuva":24,"weathercode":3,"tempo":"nuvem","vento_kmh":18.3,"rajada_kmh":32.0,"vento_dir_graus":120,"et0_mm":2.03},{"data":"2026-07-25","tmax":22.0,"tmin":10.7,"precip_mm":0.0,"prob_chuva":2,"weathercode":3,"tempo":"nuvem","vento_kmh":12.3,"rajada_kmh":21.2,"vento_dir_graus":103,"et0_mm":1.81},{"data":"2026-07-26","tmax":20.5,"tmin":15.9,"precip_mm":7.8,"prob_chuva":41,"weathercode":53,"tempo":"garoa","vento_kmh":15.7,"rajada_kmh":30.2,"vento_dir_graus":11,"et0_mm":0.96},{"data":"2026-07-27","tmax":19.3,"tmin":16.9,"precip_mm":43.1,"prob_chuva":86,"weathercode":96,"tempo":"trovoada","vento_kmh":20.7,"rajada_kmh":47.2,"vento_dir_graus":21,"et0_mm":0.45},{"data":"2026-07-28","tmax":19.4,"tmin":17.0,"precip_mm":58.6,"prob_chuva":78,"weathercode":95,"tempo":"trovoada","vento_kmh":24.2,"rajada_kmh":48.2,"vento_dir_graus":22,"et0_mm":0.7}],"fonte":"Open-Meteo","atualizado_em":"2026-07-22T05:27:13Z"},"colheita":{"pct_plantado":100.0,"pct_colhido":100.0,"area_soja_ha":82900,"fonte":"Emater/RS-Ascar - Informativo Conjuntural (fechamento)","data_referencia":"2026-05-14","granularidade":"regional (Ijuí) aplicado ao municipio","regiao":"Ijuí","derivado":true,"ha_plantado_estim":82900,"ha_colhido_estim":82900}},{"id":"julio_de_castilhos","nome":"JÚLIO DE CASTILHOS","ibge":4311205,"uf":"RS","lat":-29.2299,"lon":-53.6772,"area_soja_ha":104200,"clima":{"ibge":4311205,"nome":"JÚLIO DE CASTILHOS","uf":"RS","lat":-29.2299,"lon":-53.6772,"atual":{"tmax":16.5,"tmin":11.4,"precip_mm":3.6,"prob_chuva":71,"weathercode":53,"tempo":"garoa"},"previsao_7d":[{"data":"2026-07-22","tmax":16.5,"tmin":11.4,"precip_mm":3.6,"prob_chuva":71,"weathercode":53,"tempo":"garoa","vento_kmh":26.4,"rajada_kmh":47.5,"vento_dir_graus":179,"et0_mm":0.64},{"data":"2026-07-23","tmax":16.6,"tmin":10.1,"precip_mm":0.2,"prob_chuva":4,"weathercode":51,"tempo":"garoa","vento_kmh":21.7,"rajada_kmh":41.4,"vento_dir_graus":126,"et0_mm":1.51},{"data":"2026-07-24","tmax":20.3,"tmin":9.8,"precip_mm":0.6,"prob_chuva":28,"weathercode":51,"tempo":"garoa","vento_kmh":17.1,"rajada_kmh":29.9,"vento_dir_graus":106,"et0_mm":1.9},{"data":"2026-07-25","tmax":18.8,"tmin":10.1,"precip_mm":0.0,"prob_chuva":3,"weathercode":3,"tempo":"nuvem","vento_kmh":9.6,"rajada_kmh":22.0,"vento_dir_graus":91,"et0_mm":1.52},{"data":"2026-07-26","tmax":20.2,"tmin":14.0,"precip_mm":8.9,"prob_chuva":35,"weathercode":80,"tempo":"chuva","vento_kmh":22.1,"rajada_kmh":43.9,"vento_dir_graus":357,"et0_mm":1.32},{"data":"2026-07-27","tmax":18.7,"tmin":16.3,"precip_mm":18.4,"prob_chuva":88,"weathercode":95,"tempo":"trovoada","vento_kmh":22.8,"rajada_kmh":50.8,"vento_dir_graus":348,"et0_mm":0.57},{"data":"2026-07-28","tmax":18.5,"tmin":15.5,"precip_mm":58.4,"prob_chuva":80,"weathercode":96,"tempo":"trovoada","vento_kmh":12.4,"rajada_kmh":33.1,"vento_dir_graus":20,"et0_mm":0.55}],"fonte":"Open-Meteo","atualizado_em":"2026-07-22T05:27:13Z"},"colheita":{"pct_plantado":100.0,"pct_colhido":100.0,"area_soja_ha":104200,"fonte":"Emater/RS-Ascar - Informativo Conjuntural (fechamento)","data_referencia":"2026-05-14","granularidade":"regional (Santa Maria) aplicado ao municipio","regiao":"Santa Maria","derivado":true,"ha_plantado_estim":104200,"ha_colhido_estim":104200}},{"id":"nova_esperanca_do_sul","nome":"NOVA ESPERANÇA DO SUL","ibge":4313037,"uf":"RS","lat":-29.4066,"lon":-54.8293,"area_soja_ha":4500,"clima":{"ibge":4313037,"nome":"NOVA ESPERANÇA DO SUL","uf":"RS","lat":-29.4066,"lon":-54.8293,"atual":{"tmax":16.1,"tmin":11.3,"precip_mm":5.1,"prob_chuva":76,"weathercode":53,"tempo":"garoa"},"previsao_7d":[{"data":"2026-07-22","tmax":16.1,"tmin":11.3,"precip_mm":5.1,"prob_chuva":76,"weathercode":53,"tempo":"garoa","vento_kmh":18.1,"rajada_kmh":33.8,"vento_dir_graus":179,"et0_mm":0.63},{"data":"2026-07-23","tmax":15.7,"tmin":8.3,"precip_mm":0.2,"prob_chuva":4,"weathercode":51,"tempo":"garoa","vento_kmh":16.6,"rajada_kmh":34.9,"vento_dir_graus":123,"et0_mm":1.19},{"data":"2026-07-24","tmax":18.7,"tmin":9.2,"precip_mm":0.0,"prob_chuva":6,"weathercode":3,"tempo":"nuvem","vento_kmh":11.5,"rajada_kmh":22.3,"vento_dir_graus":127,"et0_mm":1.88},{"data":"2026-07-25","tmax":20.3,"tmin":9.8,"precip_mm":0.0,"prob_chuva":2,"weathercode":3,"tempo":"nuvem","vento_kmh":10.8,"rajada_kmh":24.1,"vento_dir_graus":100,"et0_mm":1.71},{"data":"2026-07-26","tmax":21.3,"tmin":15.9,"precip_mm":2.0,"prob_chuva":41,"weathercode":51,"tempo":"garoa","vento_kmh":16.3,"rajada_kmh":36.7,"vento_dir_graus":344,"et0_mm":1.0},{"data":"2026-07-27","tmax":19.7,"tmin":17.1,"precip_mm":12.3,"prob_chuva":83,"weathercode":95,"tempo":"trovoada","vento_kmh":18.2,"rajada_kmh":54.0,"vento_dir_graus":2,"et0_mm":0.82},{"data":"2026-07-28","tmax":21.5,"tmin":16.4,"precip_mm":34.8,"prob_chuva":78,"weathercode":96,"tempo":"trovoada","vento_kmh":18.3,"rajada_kmh":40.0,"vento_dir_graus":2,"et0_mm":1.07}],"fonte":"Open-Meteo","atualizado_em":"2026-07-22T05:27:13Z"},"colheita":{"pct_plantado":100.0,"pct_colhido":100.0,"area_soja_ha":4500,"fonte":"Emater/RS-Ascar - Informativo Conjuntural (fechamento)","data_referencia":"2026-05-14","granularidade":"regional (Santa Maria) aplicado ao municipio","regiao":"Santa Maria","derivado":true,"ha_plantado_estim":4500,"ha_colhido_estim":4500}},{"id":"pejucara","nome":"PEJUÇARA","ibge":4314308,"uf":"RS","lat":-28.4283,"lon":-53.6579,"area_soja_ha":29400,"clima":{"ibge":4314308,"nome":"PEJUÇARA","uf":"RS","lat":-28.4283,"lon":-53.6579,"atual":{"tmax":17.7,"tmin":13.3,"precip_mm":0.5,"prob_chuva":59,"weathercode":51,"tempo":"garoa"},"previsao_7d":[{"data":"2026-07-22","tmax":17.7,"tmin":13.3,"precip_mm":0.5,"prob_chuva":59,"weathercode":51,"tempo":"garoa","vento_kmh":20.4,"rajada_kmh":39.6,"vento_dir_graus":215,"et0_mm":0.7},{"data":"2026-07-23","tmax":17.6,"tmin":12.6,"precip_mm":0.0,"prob_chuva":0,"weathercode":3,"tempo":"nuvem","vento_kmh":22.4,"rajada_kmh":42.5,"vento_dir_graus":123,"et0_mm":1.92},{"data":"2026-07-24","tmax":21.0,"tmin":11.4,"precip_mm":0.4,"prob_chuva":27,"weathercode":51,"tempo":"garoa","vento_kmh":19.6,"rajada_kmh":34.6,"vento_dir_graus":87,"et0_mm":1.93},{"data":"2026-07-25","tmax":21.5,"tmin":11.2,"precip_mm":0.3,"prob_chuva":6,"weathercode":51,"tempo":"garoa","vento_kmh":11.7,"rajada_kmh":20.5,"vento_dir_graus":96,"et0_mm":1.82},{"data":"2026-07-26","tmax":19.7,"tmin":16.3,"precip_mm":22.5,"prob_chuva":45,"weathercode":95,"tempo":"trovoada","vento_kmh":14.2,"rajada_kmh":32.8,"vento_dir_graus":19,"et0_mm":0.97},{"data":"2026-07-27","tmax":19.5,"tmin":16.8,"precip_mm":47.9,"prob_chuva":80,"weathercode":95,"tempo":"trovoada","vento_kmh":15.4,"rajada_kmh":41.4,"vento_dir_graus":20,"et0_mm":0.43},{"data":"2026-07-28","tmax":20.4,"tmin":16.6,"precip_mm":40.0,"prob_chuva":75,"weathercode":95,"tempo":"trovoada","vento_kmh":20.0,"rajada_kmh":49.7,"vento_dir_graus":29,"et0_mm":0.9}],"fonte":"Open-Meteo","atualizado_em":"2026-07-22T05:27:13Z"},"colheita":{"pct_plantado":100.0,"pct_colhido":100.0,"area_soja_ha":29400,"fonte":"Emater/RS-Ascar - Informativo Conjuntural (fechamento)","data_referencia":"2026-05-14","granularidade":"regional (Ijuí) aplicado ao municipio","regiao":"Ijuí","derivado":true,"ha_plantado_estim":29400,"ha_colhido_estim":29400}},{"id":"pinhal_grande","nome":"PINHAL GRANDE","ibge":4314472,"uf":"RS","lat":-29.345,"lon":-53.3206,"area_soja_ha":21350,"clima":{"ibge":4314472,"nome":"PINHAL GRANDE","uf":"RS","lat":-29.345,"lon":-53.3206,"atual":{"tmax":16.4,"tmin":11.6,"precip_mm":10.5,"prob_chuva":75,"weathercode":95,"tempo":"trovoada"},"previsao_7d":[{"data":"2026-07-22","tmax":16.4,"tmin":11.6,"precip_mm":10.5,"prob_chuva":75,"weathercode":95,"tempo":"trovoada","vento_kmh":23.2,"rajada_kmh":45.4,"vento_dir_graus":189,"et0_mm":0.56},{"data":"2026-07-23","tmax":17.2,"tmin":10.2,"precip_mm":0.3,"prob_chuva":16,"weathercode":51,"tempo":"garoa","vento_kmh":15.7,"rajada_kmh":32.8,"vento_dir_graus":137,"et0_mm":1.45},{"data":"2026-07-24","tmax":20.4,"tmin":10.0,"precip_mm":0.3,"prob_chuva":25,"weathercode":51,"tempo":"garoa","vento_kmh":12.8,"rajada_kmh":24.1,"vento_dir_graus":99,"et0_mm":1.94},{"data":"2026-07-25","tmax":19.9,"tmin":11.0,"precip_mm":0.0,"prob_chuva":4,"weathercode":3,"tempo":"nuvem","vento_kmh":8.3,"rajada_kmh":20.9,"vento_dir_graus":57,"et0_mm":1.58},{"data":"2026-07-26","tmax":20.7,"tmin":13.2,"precip_mm":4.6,"prob_chuva":33,"weathercode":53,"tempo":"garoa","vento_kmh":18.7,"rajada_kmh":41.8,"vento_dir_graus":351,"et0_mm":1.4},{"data":"2026-07-27","tmax":19.3,"tmin":16.1,"precip_mm":51.9,"prob_chuva":84,"weathercode":96,"tempo":"trovoada","vento_kmh":21.4,"rajada_kmh":46.4,"vento_dir_graus":360,"et0_mm":0.66},{"data":"2026-07-28","tmax":17.9,"tmin":15.0,"precip_mm":59.2,"prob_chuva":80,"weathercode":96,"tempo":"trovoada","vento_kmh":14.7,"rajada_kmh":38.2,"vento_dir_graus":32,"et0_mm":0.44}],"fonte":"Open-Meteo","atualizado_em":"2026-07-22T05:27:13Z"},"colheita":{"pct_plantado":100.0,"pct_colhido":100.0,"area_soja_ha":21350,"fonte":"Emater/RS-Ascar - Informativo Conjuntural (fechamento)","data_referencia":"2026-05-14","granularidade":"regional (Santa Maria) aplicado ao municipio","regiao":"Santa Maria","derivado":true,"ha_plantado_estim":21350,"ha_colhido_estim":21350}},{"id":"quevedos","nome":"QUEVEDOS","ibge":4315321,"uf":"RS","lat":-29.3504,"lon":-54.0789,"area_soja_ha":30000,"clima":{"ibge":4315321,"nome":"QUEVEDOS","uf":"RS","lat":-29.3504,"lon":-54.0789,"atual":{"tmax":16.2,"tmin":11.9,"precip_mm":4.7,"prob_chuva":67,"weathercode":53,"tempo":"garoa"},"previsao_7d":[{"data":"2026-07-22","tmax":16.2,"tmin":11.9,"precip_mm":4.7,"prob_chuva":67,"weathercode":53,"tempo":"garoa","vento_kmh":23.0,"rajada_kmh":41.8,"vento_dir_graus":185,"et0_mm":0.59},{"data":"2026-07-23","tmax":16.9,"tmin":10.6,"precip_mm":0.0,"prob_chuva":4,"weathercode":3,"tempo":"nuvem","vento_kmh":21.3,"rajada_kmh":41.4,"vento_dir_graus":121,"et0_mm":1.33},{"data":"2026-07-24","tmax":20.5,"tmin":10.2,"precip_mm":0.3,"prob_chuva":22,"weathercode":51,"tempo":"garoa","vento_kmh":14.8,"rajada_kmh":25.2,"vento_dir_graus":87,"et0_mm":1.88},{"data":"2026-07-25","tmax":21.1,"tmin":9.0,"precip_mm":0.0,"prob_chuva":4,"weathercode":3,"tempo":"nuvem","vento_kmh":11.7,"rajada_kmh":25.2,"vento_dir_graus":50,"et0_mm":2.16},{"data":"2026-07-26","tmax":21.5,"tmin":14.6,"precip_mm":32.8,"prob_chuva":37,"weathercode":96,"tempo":"trovoada","vento_kmh":19.0,"rajada_kmh":36.0,"vento_dir_graus":1,"et0_mm":1.41},{"data":"2026-07-27","tmax":19.6,"tmin":17.1,"precip_mm":16.2,"prob_chuva":85,"weathercode":95,"tempo":"trovoada","vento_kmh":24.2,"rajada_kmh":51.8,"vento_dir_graus":354,"et0_mm":0.7},{"data":"2026-07-28","tmax":19.7,"tmin":16.2,"precip_mm":43.0,"prob_chuva":80,"weathercode":96,"tempo":"trovoada","vento_kmh":15.6,"rajada_kmh":39.2,"vento_dir_graus":28,"et0_mm":0.71}],"fonte":"Open-Meteo","atualizado_em":"2026-07-22T05:27:13Z"},"colheita":{"pct_plantado":100.0,"pct_colhido":100.0,"area_soja_ha":30000,"fonte":"Emater/RS-Ascar - Informativo Conjuntural (fechamento)","data_referencia":"2026-05-14","granularidade":"regional (Santa Maria) aplicado ao municipio","regiao":"Santa Maria","derivado":true,"ha_plantado_estim":30000,"ha_colhido_estim":30000}},{"id":"santiago","nome":"SANTIAGO","ibge":4317400,"uf":"RS","lat":-29.1897,"lon":-54.8666,"area_soja_ha":57281,"clima":{"ibge":4317400,"nome":"SANTIAGO","uf":"RS","lat":-29.1897,"lon":-54.8666,"atual":{"tmax":17.1,"tmin":11.8,"precip_mm":1.7,"prob_chuva":61,"weathercode":51,"tempo":"garoa"},"previsao_7d":[{"data":"2026-07-22","tmax":17.1,"tmin":11.8,"precip_mm":1.7,"prob_chuva":61,"weathercode":51,"tempo":"garoa","vento_kmh":21.3,"rajada_kmh":40.0,"vento_dir_graus":169,"et0_mm":0.83},{"data":"2026-07-23","tmax":16.1,"tmin":9.4,"precip_mm":0.0,"prob_chuva":4,"weathercode":3,"tempo":"nuvem","vento_kmh":20.8,"rajada_kmh":41.8,"vento_dir_graus":122,"et0_mm":1.45},{"data":"2026-07-24","tmax":19.9,"tmin":9.6,"precip_mm":0.0,"prob_chuva":6,"weathercode":3,"tempo":"nuvem","vento_kmh":17.1,"rajada_kmh":30.6,"vento_dir_graus":126,"et0_mm":2.05},{"data":"2026-07-25","tmax":21.4,"tmin":9.8,"precip_mm":0.0,"prob_chuva":4,"weathercode":3,"tempo":"nuvem","vento_kmh":10.6,"rajada_kmh":26.3,"vento_dir_graus":101,"et0_mm":1.83},{"data":"2026-07-26","tmax":21.8,"tmin":15.8,"precip_mm":2.6,"prob_chuva":27,"weathercode":51,"tempo":"garoa","vento_kmh":15.9,"rajada_kmh":32.8,"vento_dir_graus":351,"et0_mm":1.24},{"data":"2026-07-27","tmax":19.4,"tmin":16.8,"precip_mm":22.0,"prob_chuva":84,"weathercode":95,"tempo":"trovoada","vento_kmh":34.1,"rajada_kmh":65.2,"vento_dir_graus":2,"et0_mm":0.66},{"data":"2026-07-28","tmax":20.6,"tmin":16.3,"precip_mm":38.0,"prob_chuva":78,"weathercode":96,"tempo":"trovoada","vento_kmh":21.7,"rajada_kmh":46.1,"vento_dir_graus":5,"et0_mm":0.96}],"fonte":"Open-Meteo","atualizado_em":"2026-07-22T05:27:13Z"},"colheita":{"pct_plantado":100.0,"pct_colhido":100.0,"area_soja_ha":57281,"fonte":"Emater/RS-Ascar - Informativo Conjuntural (fechamento)","data_referencia":"2026-05-14","granularidade":"regional (Santa Maria) aplicado ao municipio","regiao":"Santa Maria","derivado":true,"ha_plantado_estim":57281,"ha_colhido_estim":57281}},{"id":"sao_francisco_de_assis","nome":"SÃO FRANCISCO DE ASSIS","ibge":4318101,"uf":"RS","lat":-29.5547,"lon":-55.1253,"area_soja_ha":57000,"clima":{"ibge":4318101,"nome":"SÃO FRANCISCO DE ASSIS","uf":"RS","lat":-29.5547,"lon":-55.1253,"atual":{"tmax":17.7,"tmin":12.0,"precip_mm":2.7,"prob_chuva":68,"weathercode":53,"tempo":"garoa"},"previsao_7d":[{"data":"2026-07-22","tmax":17.7,"tmin":12.0,"precip_mm":2.7,"prob_chuva":68,"weathercode":53,"tempo":"garoa","vento_kmh":18.7,"rajada_kmh":32.8,"vento_dir_graus":165,"et0_mm":0.79},{"data":"2026-07-23","tmax":16.7,"tmin":8.9,"precip_mm":0.0,"prob_chuva":0,"weathercode":3,"tempo":"nuvem","vento_kmh":21.4,"rajada_kmh":40.3,"vento_dir_graus":115,"et0_mm":1.34},{"data":"2026-07-24","tmax":18.7,"tmin":10.7,"precip_mm":0.0,"prob_chuva":2,"weathercode":3,"tempo":"nuvem","vento_kmh":18.9,"rajada_kmh":33.5,"vento_dir_graus":115,"et0_mm":1.82},{"data":"2026-07-25","tmax":20.0,"tmin":9.3,"precip_mm":0.0,"prob_chuva":5,"weathercode":3,"tempo":"nuvem","vento_kmh":12.5,"rajada_kmh":30.2,"vento_dir_graus":100,"et0_mm":1.7},{"data":"2026-07-26","tmax":21.5,"tmin":15.5,"precip_mm":3.8,"prob_chuva":31,"weathercode":53,"tempo":"garoa","vento_kmh":12.5,"rajada_kmh":23.0,"vento_dir_graus":70,"et0_mm":0.87},{"data":"2026-07-27","tmax":21.1,"tmin":17.7,"precip_mm":10.0,"prob_chuva":78,"weathercode":55,"tempo":"garoa","vento_kmh":14.4,"rajada_kmh":51.1,"vento_dir_graus":7,"et0_mm":0.94},{"data":"2026-07-28","tmax":23.1,"tmin":16.6,"precip_mm":29.2,"prob_chuva":75,"weathercode":95,"tempo":"trovoada","vento_kmh":15.5,"rajada_kmh":33.5,"vento_dir_graus":21,"et0_mm":1.31}],"fonte":"Open-Meteo","atualizado_em":"2026-07-22T05:27:13Z"},"colheita":{"pct_plantado":100.0,"pct_colhido":100.0,"area_soja_ha":57000,"fonte":"Emater/RS-Ascar - Informativo Conjuntural (fechamento)","data_referencia":"2026-05-14","granularidade":"regional (Santa Maria) aplicado ao municipio","regiao":"Santa Maria","derivado":true,"ha_plantado_estim":57000,"ha_colhido_estim":57000}},{"id":"sao_martinho_da_serra","nome":"SÃO MARTINHO DA SERRA","ibge":4319125,"uf":"RS","lat":-29.5397,"lon":-53.859,"area_soja_ha":35500,"clima":{"ibge":4319125,"nome":"SÃO MARTINHO DA SERRA","uf":"RS","lat":-29.5397,"lon":-53.859,"atual":{"tmax":15.5,"tmin":11.4,"precip_mm":13.3,"prob_chuva":93,"weathercode":81,"tempo":"chuva"},"previsao_7d":[{"data":"2026-07-22","tmax":15.5,"tmin":11.4,"precip_mm":13.3,"prob_chuva":93,"weathercode":81,"tempo":"chuva","vento_kmh":19.8,"rajada_kmh":41.0,"vento_dir_graus":171,"et0_mm":0.5},{"data":"2026-07-23","tmax":16.3,"tmin":9.7,"precip_mm":0.2,"prob_chuva":16,"weathercode":51,"tempo":"garoa","vento_kmh":17.6,"rajada_kmh":39.2,"vento_dir_graus":119,"et0_mm":1.23},{"data":"2026-07-24","tmax":20.5,"tmin":9.9,"precip_mm":0.2,"prob_chuva":25,"weathercode":51,"tempo":"garoa","vento_kmh":16.5,"rajada_kmh":34.2,"vento_dir_graus":94,"et0_mm":1.89},{"data":"2026-07-25","tmax":21.7,"tmin":10.6,"precip_mm":0.0,"prob_chuva":4,"weathercode":3,"tempo":"nuvem","vento_kmh":12.0,"rajada_kmh":24.5,"vento_dir_graus":55,"et0_mm":2.22},{"data":"2026-07-26","tmax":20.3,"tmin":14.9,"precip_mm":12.6,"prob_chuva":49,"weathercode":96,"tempo":"trovoada","vento_kmh":19.7,"rajada_kmh":44.3,"vento_dir_graus":355,"et0_mm":1.15},{"data":"2026-07-27","tmax":19.8,"tmin":17.0,"precip_mm":17.9,"prob_chuva":86,"weathercode":80,"tempo":"chuva","vento_kmh":23.3,"rajada_kmh":50.8,"vento_dir_graus":356,"et0_mm":0.76},{"data":"2026-07-28","tmax":20.1,"tmin":15.8,"precip_mm":39.2,"prob_chuva":79,"weathercode":96,"tempo":"trovoada","vento_kmh":17.7,"rajada_kmh":47.2,"vento_dir_graus":22,"et0_mm":0.72}],"fonte":"Open-Meteo","atualizado_em":"2026-07-22T05:27:13Z"},"colheita":{"pct_plantado":100.0,"pct_colhido":100.0,"area_soja_ha":35500,"fonte":"Emater/RS-Ascar - Informativo Conjuntural (fechamento)","data_referencia":"2026-05-14","granularidade":"regional (Santa Maria) aplicado ao municipio","regiao":"Santa Maria","derivado":true,"ha_plantado_estim":35500,"ha_colhido_estim":35500}},{"id":"sao_miguel_das_missoes","nome":"SÃO MIGUEL DAS MISSÕES","ibge":4319158,"uf":"RS","lat":-28.556,"lon":-54.5559,"area_soja_ha":74200,"clima":{"ibge":4319158,"nome":"SÃO MIGUEL DAS MISSÕES","uf":"RS","lat":-28.556,"lon":-54.5559,"atual":{"tmax":18.0,"tmin":14.0,"precip_mm":0.8,"prob_chuva":37,"weathercode":51,"tempo":"garoa"},"previsao_7d":[{"data":"2026-07-22","tmax":18.0,"tmin":14.0,"precip_mm":0.8,"prob_chuva":37,"weathercode":51,"tempo":"garoa","vento_kmh":16.9,"rajada_kmh":31.0,"vento_dir_graus":191,"et0_mm":0.88},{"data":"2026-07-23","tmax":18.9,"tmin":11.6,"precip_mm":0.0,"prob_chuva":0,"weathercode":3,"tempo":"nuvem","vento_kmh":21.9,"rajada_kmh":43.6,"vento_dir_graus":116,"et0_mm":2.13},{"data":"2026-07-24","tmax":21.6,"tmin":11.0,"precip_mm":0.0,"prob_chuva":12,"weathercode":3,"tempo":"nuvem","vento_kmh":16.3,"rajada_kmh":29.5,"vento_dir_graus":108,"et0_mm":2.09},{"data":"2026-07-25","tmax":23.2,"tmin":11.1,"precip_mm":0.0,"prob_chuva":4,"weathercode":3,"tempo":"nuvem","vento_kmh":12.9,"rajada_kmh":22.3,"vento_dir_graus":87,"et0_mm":2.09},{"data":"2026-07-26","tmax":22.8,"tmin":16.9,"precip_mm":5.4,"prob_chuva":43,"weathercode":53,"tempo":"garoa","vento_kmh":16.2,"rajada_kmh":33.8,"vento_dir_graus":3,"et0_mm":1.43},{"data":"2026-07-27","tmax":19.9,"tmin":17.5,"precip_mm":62.3,"prob_chuva":81,"weathercode":96,"tempo":"trovoada","vento_kmh":17.5,"rajada_kmh":38.5,"vento_dir_graus":30,"et0_mm":0.65},{"data":"2026-07-28","tmax":19.6,"tmin":17.2,"precip_mm":52.2,"prob_chuva":76,"weathercode":96,"tempo":"trovoada","vento_kmh":22.7,"rajada_kmh":45.7,"vento_dir_graus":21,"et0_mm":0.65}],"fonte":"Open-Meteo","atualizado_em":"2026-07-22T05:27:13Z"},"colheita":{"pct_plantado":100.0,"pct_colhido":100.0,"area_soja_ha":74200,"fonte":"Emater/RS-Ascar - Informativo Conjuntural (fechamento)","data_referencia":"2026-05-14","granularidade":"regional (Ijuí) aplicado ao municipio","regiao":"Ijuí","derivado":true,"ha_plantado_estim":74200,"ha_colhido_estim":74200}},{"id":"tupancireta","nome":"TUPANCIRETÃ","ibge":4322202,"uf":"RS","lat":-29.0858,"lon":-53.8445,"area_soja_ha":147919,"clima":{"ibge":4322202,"nome":"TUPANCIRETÃ","uf":"RS","lat":-29.0858,"lon":-53.8445,"atual":{"tmax":16.3,"tmin":12.1,"precip_mm":2.3,"prob_chuva":40,"weathercode":51,"tempo":"garoa"},"previsao_7d":[{"data":"2026-07-22","tmax":16.3,"tmin":12.1,"precip_mm":2.3,"prob_chuva":40,"weathercode":51,"tempo":"garoa","vento_kmh":22.3,"rajada_kmh":40.7,"vento_dir_graus":186,"et0_mm":0.69},{"data":"2026-07-23","tmax":16.9,"tmin":10.9,"precip_mm":0.0,"prob_chuva":4,"weathercode":3,"tempo":"nuvem","vento_kmh":22.4,"rajada_kmh":45.0,"vento_dir_graus":120,"et0_mm":1.61},{"data":"2026-07-24","tmax":20.1,"tmin":10.0,"precip_mm":0.1,"prob_chuva":27,"weathercode":51,"tempo":"garoa","vento_kmh":18.2,"rajada_kmh":32.4,"vento_dir_graus":105,"et0_mm":1.96},{"data":"2026-07-25","tmax":19.4,"tmin":10.1,"precip_mm":0.0,"prob_chuva":4,"weathercode":3,"tempo":"nuvem","vento_kmh":11.4,"rajada_kmh":23.0,"vento_dir_graus":83,"et0_mm":1.51},{"data":"2026-07-26","tmax":19.9,"tmin":14.4,"precip_mm":37.4,"prob_chuva":39,"weathercode":95,"tempo":"trovoada","vento_kmh":15.2,"rajada_kmh":37.4,"vento_dir_graus":11,"et0_mm":1.14},{"data":"2026-07-27","tmax":18.8,"tmin":16.5,"precip_mm":25.0,"prob_chuva":87,"weathercode":96,"tempo":"trovoada","vento_kmh":17.5,"rajada_kmh":42.5,"vento_dir_graus":355,"et0_mm":0.56},{"data":"2026-07-28","tmax":19.1,"tmin":15.7,"precip_mm":67.4,"prob_chuva":80,"weathercode":95,"tempo":"trovoada","vento_kmh":15.7,"rajada_kmh":36.7,"vento_dir_graus":14,"et0_mm":0.61}],"fonte":"Open-Meteo","atualizado_em":"2026-07-22T05:27:13Z"},"colheita":{"pct_plantado":100.0,"pct_colhido":100.0,"area_soja_ha":147919,"fonte":"Emater/RS-Ascar - Informativo Conjuntural (fechamento)","data_referencia":"2026-05-14","granularidade":"regional (Santa Maria) aplicado ao municipio","regiao":"Santa Maria","derivado":true,"ha_plantado_estim":147919,"ha_colhido_estim":147919}},{"id":"vitoria_das_missoes","nome":"VITÓRIA DAS MISSÕES","ibge":4323754,"uf":"RS","lat":-28.3516,"lon":-54.504,"area_soja_ha":10450,"clima":{"ibge":4323754,"nome":"VITÓRIA DAS MISSÕES","uf":"RS","lat":-28.3516,"lon":-54.504,"atual":{"tmax":18.5,"tmin":15.5,"precip_mm":0.4,"prob_chuva":51,"weathercode":51,"tempo":"garoa"},"previsao_7d":[{"data":"2026-07-22","tmax":18.5,"tmin":15.5,"precip_mm":0.4,"prob_chuva":51,"weathercode":51,"tempo":"garoa","vento_kmh":16.4,"rajada_kmh":31.7,"vento_dir_graus":201,"et0_mm":0.93},{"data":"2026-07-23","tmax":19.8,"tmin":12.3,"precip_mm":0.0,"prob_chuva":0,"weathercode":3,"tempo":"nuvem","vento_kmh":20.9,"rajada_kmh":42.1,"vento_dir_graus":122,"et0_mm":2.21},{"data":"2026-07-24","tmax":22.0,"tmin":10.9,"precip_mm":0.0,"prob_chuva":14,"weathercode":3,"tempo":"nuvem","vento_kmh":15.7,"rajada_kmh":27.7,"vento_dir_graus":125,"et0_mm":2.14},{"data":"2026-07-25","tmax":22.8,"tmin":11.6,"precip_mm":0.0,"prob_chuva":10,"weathercode":3,"tempo":"nuvem","vento_kmh":11.4,"rajada_kmh":21.2,"vento_dir_graus":101,"et0_mm":1.97},{"data":"2026-07-26","tmax":23.2,"tmin":16.8,"precip_mm":5.4,"prob_chuva":43,"weathercode":53,"tempo":"garoa","vento_kmh":16.1,"rajada_kmh":35.3,"vento_dir_graus":1,"et0_mm":1.54},{"data":"2026-07-27","tmax":20.0,"tmin":17.2,"precip_mm":66.2,"prob_chuva":79,"weathercode":96,"tempo":"trovoada","vento_kmh":13.1,"rajada_kmh":44.3,"vento_dir_graus":51,"et0_mm":0.63},{"data":"2026-07-28","tmax":20.0,"tmin":17.0,"precip_mm":49.6,"prob_chuva":74,"weathercode":95,"tempo":"trovoada","vento_kmh":19.8,"rajada_kmh":45.4,"vento_dir_graus":42,"et0_mm":0.82}],"fonte":"Open-Meteo","atualizado_em":"2026-07-22T05:27:13Z"},"colheita":{"pct_plantado":100.0,"pct_colhido":100.0,"area_soja_ha":10450,"fonte":"Emater/RS-Ascar (regional Santa Rosa, Fenasoja 30/04)","data_referencia":"2026-05-14","granularidade":"regional (Santa Rosa) aplicado ao municipio","regiao":"Santa Rosa","derivado":true,"ha_plantado_estim":10450,"ha_colhido_estim":10450}}],"alertas":{"ativos":[],"ufs":["RS"]},"colheita":{"status":"validado","fonte":"Emater/RS-Ascar - Informativo Conjuntural (via SEAPI-RS / Canal Rural)","granularidade":"estadual","data_referencia":"2026-06-11","cultura":"soja","itens":[{"regiao":"Rio Grande do Sul","uf":"RS","granularidade":"estadual","pct_plantado":100,"pct_colhido":100,"vs_media5anos":null,"vs_safra_anterior":null,"condicao_lavoura":"Safra encerrada; forte variabilidade regional (1.200-4.200 kg/ha); produtividade -14,8% vs projeção inicial","fonte":"Emater/RS-Ascar - Informativo Conjuntural (via SEAPI-RS / Canal Rural)","data_referencia":"2026-06-11","safra":"2025/2026","produtividade_kg_ha":2707,"area_ha":6690000,"producao_t":18132401,"var_producao_pct":32.9,"preco_rs_sc":129,"preco_data":"2026-07-03","preco_fonte":"Grao Direto (Centro Ocidental RS)"}]},"preco":{"valor":129,"uf":"RS","data":"2026-07-03","fonte":"Grao Direto (Centro Ocidental RS)","unidade":"R$/sc 60kg"}}