{"distrito":{"id":"patos_de_minas_soja","nome":"PATOS DE MINAS-SOJA","regional":"CENTRO SOJA","codigo_regional":"CESO","uf":"MG","ufs":["MG"],"cultura_principal":"soja"},"gerado_em":"2026-06-26T22:05:05+00:00","municipios":[{"id":"buritizeiro","nome":"BURITIZEIRO","ibge":3109402,"uf":"MG","lat":-17.3656,"lon":-44.9606,"area_soja_ha":25500,"clima":{"ibge":3109402,"nome":"BURITIZEIRO","uf":"MG","lat":-17.3656,"lon":-44.9606,"atual":{"tmax":28.2,"tmin":16.8,"precip_mm":0.0,"prob_chuva":0,"weathercode":1,"tempo":"parcial"},"previsao_7d":[{"data":"2026-06-26","tmax":28.2,"tmin":16.8,"precip_mm":0.0,"prob_chuva":0,"weathercode":1,"tempo":"parcial"},{"data":"2026-06-27","tmax":28.1,"tmin":17.3,"precip_mm":0.0,"prob_chuva":0,"weathercode":2,"tempo":"parcial"},{"data":"2026-06-28","tmax":27.6,"tmin":17.2,"precip_mm":0.0,"prob_chuva":0,"weathercode":2,"tempo":"parcial"},{"data":"2026-06-29","tmax":27.8,"tmin":16.0,"precip_mm":0.0,"prob_chuva":0,"weathercode":0,"tempo":"sol"},{"data":"2026-06-30","tmax":28.5,"tmin":17.2,"precip_mm":0.0,"prob_chuva":0,"weathercode":0,"tempo":"sol"},{"data":"2026-07-01","tmax":29.0,"tmin":16.6,"precip_mm":0.0,"prob_chuva":2,"weathercode":0,"tempo":"sol"},{"data":"2026-07-02","tmax":29.4,"tmin":17.5,"precip_mm":0.0,"prob_chuva":0,"weathercode":0,"tempo":"sol"}],"fonte":"Open-Meteo","atualizado_em":"2026-06-26T22:05:04Z"},"colheita":{"pct_plantado":100,"pct_colhido":100,"area_soja_ha":25500,"fonte":"Conab - 9o Levantamento Safra de Graos (jun/2026)","data_referencia":"2026-06-11","granularidade":"estadual aplicado ao municipio","derivado":true,"ha_plantado_estim":25500,"ha_colhido_estim":25500}},{"id":"coromandel","nome":"COROMANDEL","ibge":3119302,"uf":"MG","lat":-18.4734,"lon":-47.1933,"area_soja_ha":70000,"clima":{"ibge":3119302,"nome":"COROMANDEL","uf":"MG","lat":-18.4734,"lon":-47.1933,"atual":{"tmax":24.6,"tmin":16.7,"precip_mm":0.0,"prob_chuva":0,"weathercode":3,"tempo":"nuvem"},"previsao_7d":[{"data":"2026-06-26","tmax":24.6,"tmin":16.7,"precip_mm":0.0,"prob_chuva":0,"weathercode":3,"tempo":"nuvem"},{"data":"2026-06-27","tmax":25.1,"tmin":15.9,"precip_mm":0.0,"prob_chuva":0,"weathercode":3,"tempo":"nuvem"},{"data":"2026-06-28","tmax":24.3,"tmin":15.0,"precip_mm":0.0,"prob_chuva":0,"weathercode":3,"tempo":"nuvem"},{"data":"2026-06-29","tmax":24.4,"tmin":14.4,"precip_mm":0.0,"prob_chuva":0,"weathercode":0,"tempo":"sol"},{"data":"2026-06-30","tmax":25.1,"tmin":14.7,"precip_mm":0.0,"prob_chuva":0,"weathercode":0,"tempo":"sol"},{"data":"2026-07-01","tmax":25.8,"tmin":14.5,"precip_mm":0.0,"prob_chuva":0,"weathercode":0,"tempo":"sol"},{"data":"2026-07-02","tmax":25.7,"tmin":14.7,"precip_mm":0.0,"prob_chuva":0,"weathercode":0,"tempo":"sol"}],"fonte":"Open-Meteo","atualizado_em":"2026-06-26T22:05:04Z"},"colheita":{"pct_plantado":100,"pct_colhido":100,"area_soja_ha":70000,"fonte":"Conab - 9o Levantamento Safra de Graos (jun/2026)","data_referencia":"2026-06-11","granularidade":"estadual aplicado ao municipio","derivado":true,"ha_plantado_estim":70000,"ha_colhido_estim":70000}},{"id":"curvelo","nome":"CURVELO","ibge":3120904,"uf":"MG","lat":-18.7527,"lon":-44.4303,"area_soja_ha":1500,"clima":{"ibge":3120904,"nome":"CURVELO","uf":"MG","lat":-18.7527,"lon":-44.4303,"atual":{"tmax":26.9,"tmin":15.5,"precip_mm":0.0,"prob_chuva":0,"weathercode":2,"tempo":"parcial"},"previsao_7d":[{"data":"2026-06-26","tmax":26.9,"tmin":15.5,"precip_mm":0.0,"prob_chuva":0,"weathercode":2,"tempo":"parcial"},{"data":"2026-06-27","tmax":26.6,"tmin":16.1,"precip_mm":0.0,"prob_chuva":0,"weathercode":3,"tempo":"nuvem"},{"data":"2026-06-28","tmax":26.3,"tmin":16.0,"precip_mm":0.0,"prob_chuva":0,"weathercode":3,"tempo":"nuvem"},{"data":"2026-06-29","tmax":26.1,"tmin":14.9,"precip_mm":0.0,"prob_chuva":0,"weathercode":0,"tempo":"sol"},{"data":"2026-06-30","tmax":26.9,"tmin":15.2,"precip_mm":0.0,"prob_chuva":0,"weathercode":0,"tempo":"sol"},{"data":"2026-07-01","tmax":27.3,"tmin":15.4,"precip_mm":0.0,"prob_chuva":0,"weathercode":2,"tempo":"parcial"},{"data":"2026-07-02","tmax":27.9,"tmin":15.7,"precip_mm":0.0,"prob_chuva":0,"weathercode":3,"tempo":"nuvem"}],"fonte":"Open-Meteo","atualizado_em":"2026-06-26T22:05:04Z"},"colheita":{"pct_plantado":100,"pct_colhido":100,"area_soja_ha":1500,"fonte":"Conab - 9o Levantamento Safra de Graos (jun/2026)","data_referencia":"2026-06-11","granularidade":"estadual aplicado ao municipio","derivado":true,"ha_plantado_estim":1500,"ha_colhido_estim":1500}},{"id":"ibia","nome":"IBIÁ","ibge":3129509,"uf":"MG","lat":-19.4749,"lon":-46.5474,"area_soja_ha":56500,"clima":{"ibge":3129509,"nome":"IBIÁ","uf":"MG","lat":-19.4749,"lon":-46.5474,"atual":{"tmax":23.9,"tmin":15.6,"precip_mm":0.3,"prob_chuva":67,"weathercode":51,"tempo":"garoa"},"previsao_7d":[{"data":"2026-06-26","tmax":23.9,"tmin":15.6,"precip_mm":0.3,"prob_chuva":67,"weathercode":51,"tempo":"garoa"},{"data":"2026-06-27","tmax":25.4,"tmin":14.6,"precip_mm":0.0,"prob_chuva":0,"weathercode":3,"tempo":"nuvem"},{"data":"2026-06-28","tmax":25.3,"tmin":14.1,"precip_mm":0.0,"prob_chuva":0,"weathercode":1,"tempo":"parcial"},{"data":"2026-06-29","tmax":25.2,"tmin":13.6,"precip_mm":0.0,"prob_chuva":0,"weathercode":1,"tempo":"parcial"},{"data":"2026-06-30","tmax":25.8,"tmin":13.2,"precip_mm":0.0,"prob_chuva":0,"weathercode":0,"tempo":"sol"},{"data":"2026-07-01","tmax":26.6,"tmin":14.1,"precip_mm":0.0,"prob_chuva":2,"weathercode":0,"tempo":"sol"},{"data":"2026-07-02","tmax":26.4,"tmin":14.0,"precip_mm":0.0,"prob_chuva":1,"weathercode":0,"tempo":"sol"}],"fonte":"Open-Meteo","atualizado_em":"2026-06-26T22:05:04Z"},"colheita":{"pct_plantado":100,"pct_colhido":100,"area_soja_ha":56500,"fonte":"Conab - 9o Levantamento Safra de Graos (jun/2026)","data_referencia":"2026-06-11","granularidade":"estadual aplicado ao municipio","derivado":true,"ha_plantado_estim":56500,"ha_colhido_estim":56500}},{"id":"joao_pinheiro","nome":"JOÃO PINHEIRO","ibge":3136306,"uf":"MG","lat":-17.7398,"lon":-46.1715,"area_soja_ha":6000,"clima":{"ibge":3136306,"nome":"JOÃO PINHEIRO","uf":"MG","lat":-17.7398,"lon":-46.1715,"atual":{"tmax":26.7,"tmin":17.4,"precip_mm":0.0,"prob_chuva":0,"weathercode":3,"tempo":"nuvem"},"previsao_7d":[{"data":"2026-06-26","tmax":26.7,"tmin":17.4,"precip_mm":0.0,"prob_chuva":0,"weathercode":3,"tempo":"nuvem"},{"data":"2026-06-27","tmax":27.2,"tmin":17.3,"precip_mm":0.0,"prob_chuva":0,"weathercode":2,"tempo":"parcial"},{"data":"2026-06-28","tmax":26.7,"tmin":17.5,"precip_mm":0.0,"prob_chuva":0,"weathercode":3,"tempo":"nuvem"},{"data":"2026-06-29","tmax":25.9,"tmin":16.7,"precip_mm":0.0,"prob_chuva":0,"weathercode":0,"tempo":"sol"},{"data":"2026-06-30","tmax":27.0,"tmin":16.9,"precip_mm":0.0,"prob_chuva":0,"weathercode":0,"tempo":"sol"},{"data":"2026-07-01","tmax":27.0,"tmin":17.3,"precip_mm":0.0,"prob_chuva":2,"weathercode":0,"tempo":"sol"},{"data":"2026-07-02","tmax":26.9,"tmin":17.7,"precip_mm":0.0,"prob_chuva":0,"weathercode":0,"tempo":"sol"}],"fonte":"Open-Meteo","atualizado_em":"2026-06-26T22:05:04Z"},"colheita":{"pct_plantado":100,"pct_colhido":100,"area_soja_ha":6000,"fonte":"Conab - 9o Levantamento Safra de Graos (jun/2026)","data_referencia":"2026-06-11","granularidade":"estadual aplicado ao municipio","derivado":true,"ha_plantado_estim":6000,"ha_colhido_estim":6000}},{"id":"martinho_campos","nome":"MARTINHO CAMPOS","ibge":3140506,"uf":"MG","lat":-19.3306,"lon":-45.2434,"area_soja_ha":4000,"clima":{"ibge":3140506,"nome":"MARTINHO CAMPOS","uf":"MG","lat":-19.3306,"lon":-45.2434,"atual":{"tmax":25.3,"tmin":15.7,"precip_mm":0.0,"prob_chuva":0,"weathercode":3,"tempo":"nuvem"},"previsao_7d":[{"data":"2026-06-26","tmax":25.3,"tmin":15.7,"precip_mm":0.0,"prob_chuva":0,"weathercode":3,"tempo":"nuvem"},{"data":"2026-06-27","tmax":25.7,"tmin":15.9,"precip_mm":0.0,"prob_chuva":0,"weathercode":3,"tempo":"nuvem"},{"data":"2026-06-28","tmax":25.7,"tmin":15.3,"precip_mm":0.0,"prob_chuva":0,"weathercode":3,"tempo":"nuvem"},{"data":"2026-06-29","tmax":24.7,"tmin":14.5,"precip_mm":0.0,"prob_chuva":0,"weathercode":0,"tempo":"sol"},{"data":"2026-06-30","tmax":25.7,"tmin":14.0,"precip_mm":0.0,"prob_chuva":0,"weathercode":0,"tempo":"sol"},{"data":"2026-07-01","tmax":26.1,"tmin":14.7,"precip_mm":0.0,"prob_chuva":2,"weathercode":0,"tempo":"sol"},{"data":"2026-07-02","tmax":26.1,"tmin":14.5,"precip_mm":0.0,"prob_chuva":0,"weathercode":1,"tempo":"parcial"}],"fonte":"Open-Meteo","atualizado_em":"2026-06-26T22:05:04Z"},"colheita":{"pct_plantado":100,"pct_colhido":100,"area_soja_ha":4000,"fonte":"Conab - 9o Levantamento Safra de Graos (jun/2026)","data_referencia":"2026-06-11","granularidade":"estadual aplicado ao municipio","derivado":true,"ha_plantado_estim":4000,"ha_colhido_estim":4000}},{"id":"patos_de_minas","nome":"PATOS DE MINAS","ibge":3148004,"uf":"MG","lat":-18.5699,"lon":-46.5013,"area_soja_ha":29150,"clima":{"ibge":3148004,"nome":"PATOS DE MINAS","uf":"MG","lat":-18.5699,"lon":-46.5013,"atual":{"tmax":25.1,"tmin":16.0,"precip_mm":0.0,"prob_chuva":4,"weathercode":3,"tempo":"nuvem"},"previsao_7d":[{"data":"2026-06-26","tmax":25.1,"tmin":16.0,"precip_mm":0.0,"prob_chuva":4,"weathercode":3,"tempo":"nuvem"},{"data":"2026-06-27","tmax":25.8,"tmin":15.8,"precip_mm":0.0,"prob_chuva":0,"weathercode":3,"tempo":"nuvem"},{"data":"2026-06-28","tmax":25.3,"tmin":15.2,"precip_mm":0.0,"prob_chuva":0,"weathercode":3,"tempo":"nuvem"},{"data":"2026-06-29","tmax":25.0,"tmin":14.8,"precip_mm":0.0,"prob_chuva":0,"weathercode":0,"tempo":"sol"},{"data":"2026-06-30","tmax":25.7,"tmin":13.3,"precip_mm":0.0,"prob_chuva":0,"weathercode":0,"tempo":"sol"},{"data":"2026-07-01","tmax":26.3,"tmin":14.7,"precip_mm":0.0,"prob_chuva":0,"weathercode":0,"tempo":"sol"},{"data":"2026-07-02","tmax":26.2,"tmin":14.0,"precip_mm":0.0,"prob_chuva":0,"weathercode":1,"tempo":"parcial"}],"fonte":"Open-Meteo","atualizado_em":"2026-06-26T22:05:04Z"},"colheita":{"pct_plantado":100,"pct_colhido":100,"area_soja_ha":29150,"fonte":"Conab - 9o Levantamento Safra de Graos (jun/2026)","data_referencia":"2026-06-11","granularidade":"estadual aplicado ao municipio","derivado":true,"ha_plantado_estim":29150,"ha_colhido_estim":29150}},{"id":"patrocinio","nome":"PATROCÍNIO","ibge":3148103,"uf":"MG","lat":-18.9379,"lon":-46.9934,"area_soja_ha":37500,"clima":{"ibge":3148103,"nome":"PATROCÍNIO","uf":"MG","lat":-18.9379,"lon":-46.9934,"atual":{"tmax":24.1,"tmin":16.0,"precip_mm":0.0,"prob_chuva":29,"weathercode":3,"tempo":"nuvem"},"previsao_7d":[{"data":"2026-06-26","tmax":24.1,"tmin":16.0,"precip_mm":0.0,"prob_chuva":29,"weathercode":3,"tempo":"nuvem"},{"data":"2026-06-27","tmax":24.9,"tmin":15.5,"precip_mm":0.0,"prob_chuva":0,"weathercode":3,"tempo":"nuvem"},{"data":"2026-06-28","tmax":24.8,"tmin":14.8,"precip_mm":0.0,"prob_chuva":0,"weathercode":3,"tempo":"nuvem"},{"data":"2026-06-29","tmax":24.6,"tmin":14.6,"precip_mm":0.0,"prob_chuva":0,"weathercode":0,"tempo":"sol"},{"data":"2026-06-30","tmax":25.2,"tmin":14.0,"precip_mm":0.0,"prob_chuva":0,"weathercode":0,"tempo":"sol"},{"data":"2026-07-01","tmax":25.9,"tmin":14.5,"precip_mm":0.0,"prob_chuva":0,"weathercode":0,"tempo":"sol"},{"data":"2026-07-02","tmax":26.0,"tmin":14.3,"precip_mm":0.0,"prob_chuva":0,"weathercode":0,"tempo":"sol"}],"fonte":"Open-Meteo","atualizado_em":"2026-06-26T22:05:04Z"},"colheita":{"pct_plantado":100,"pct_colhido":100,"area_soja_ha":37500,"fonte":"Conab - 9o Levantamento Safra de Graos (jun/2026)","data_referencia":"2026-06-11","granularidade":"estadual aplicado ao municipio","derivado":true,"ha_plantado_estim":37500,"ha_colhido_estim":37500}},{"id":"perdizes","nome":"PERDIZES","ibge":3149804,"uf":"MG","lat":-19.3434,"lon":-47.2963,"area_soja_ha":46000,"clima":{"ibge":3149804,"nome":"PERDIZES","uf":"MG","lat":-19.3434,"lon":-47.2963,"atual":{"tmax":22.8,"tmin":15.4,"precip_mm":1.5,"prob_chuva":59,"weathercode":53,"tempo":"garoa"},"previsao_7d":[{"data":"2026-06-26","tmax":22.8,"tmin":15.4,"precip_mm":1.5,"prob_chuva":59,"weathercode":53,"tempo":"garoa"},{"data":"2026-06-27","tmax":24.0,"tmin":14.0,"precip_mm":0.0,"prob_chuva":0,"weathercode":3,"tempo":"nuvem"},{"data":"2026-06-28","tmax":23.8,"tmin":13.4,"precip_mm":0.0,"prob_chuva":0,"weathercode":1,"tempo":"parcial"},{"data":"2026-06-29","tmax":23.5,"tmin":12.7,"precip_mm":0.0,"prob_chuva":0,"weathercode":1,"tempo":"parcial"},{"data":"2026-06-30","tmax":24.2,"tmin":13.1,"precip_mm":0.0,"prob_chuva":0,"weathercode":0,"tempo":"sol"},{"data":"2026-07-01","tmax":24.9,"tmin":12.6,"precip_mm":0.0,"prob_chuva":0,"weathercode":0,"tempo":"sol"},{"data":"2026-07-02","tmax":24.9,"tmin":12.8,"precip_mm":0.0,"prob_chuva":0,"weathercode":0,"tempo":"sol"}],"fonte":"Open-Meteo","atualizado_em":"2026-06-26T22:05:04Z"},"colheita":{"pct_plantado":100,"pct_colhido":100,"area_soja_ha":46000,"fonte":"Conab - 9o Levantamento Safra de Graos (jun/2026)","data_referencia":"2026-06-11","granularidade":"estadual aplicado ao municipio","derivado":true,"ha_plantado_estim":46000,"ha_colhido_estim":46000}},{"id":"pirapora","nome":"PIRAPORA","ibge":3151206,"uf":"MG","lat":-17.3392,"lon":-44.934,"area_soja_ha":400,"clima":{"ibge":3151206,"nome":"PIRAPORA","uf":"MG","lat":-17.3392,"lon":-44.934,"atual":{"tmax":28.8,"tmin":18.0,"precip_mm":0.0,"prob_chuva":0,"weathercode":1,"tempo":"parcial"},"previsao_7d":[{"data":"2026-06-26","tmax":28.8,"tmin":18.0,"precip_mm":0.0,"prob_chuva":0,"weathercode":1,"tempo":"parcial"},{"data":"2026-06-27","tmax":28.6,"tmin":17.8,"precip_mm":0.0,"prob_chuva":0,"weathercode":2,"tempo":"parcial"},{"data":"2026-06-28","tmax":28.0,"tmin":18.1,"precip_mm":0.0,"prob_chuva":0,"weathercode":2,"tempo":"parcial"},{"data":"2026-06-29","tmax":28.4,"tmin":16.8,"precip_mm":0.0,"prob_chuva":0,"weathercode":0,"tempo":"sol"},{"data":"2026-06-30","tmax":29.1,"tmin":17.7,"precip_mm":0.0,"prob_chuva":0,"weathercode":0,"tempo":"sol"},{"data":"2026-07-01","tmax":29.6,"tmin":17.5,"precip_mm":0.0,"prob_chuva":2,"weathercode":0,"tempo":"sol"},{"data":"2026-07-02","tmax":29.7,"tmin":18.5,"precip_mm":0.0,"prob_chuva":0,"weathercode":0,"tempo":"sol"}],"fonte":"Open-Meteo","atualizado_em":"2026-06-26T22:05:04Z"},"colheita":{"pct_plantado":100,"pct_colhido":100,"area_soja_ha":400,"fonte":"Conab - 9o Levantamento Safra de Graos (jun/2026)","data_referencia":"2026-06-11","granularidade":"estadual aplicado ao municipio","derivado":true,"ha_plantado_estim":400,"ha_colhido_estim":400}},{"id":"pompeu","nome":"POMPÉU","ibge":3152006,"uf":"MG","lat":-19.2257,"lon":-45.0141,"area_soja_ha":1500,"clima":{"ibge":3152006,"nome":"POMPÉU","uf":"MG","lat":-19.2257,"lon":-45.0141,"atual":{"tmax":26.2,"tmin":16.1,"precip_mm":0.0,"prob_chuva":0,"weathercode":3,"tempo":"nuvem"},"previsao_7d":[{"data":"2026-06-26","tmax":26.2,"tmin":16.1,"precip_mm":0.0,"prob_chuva":0,"weathercode":3,"tempo":"nuvem"},{"data":"2026-06-27","tmax":26.8,"tmin":16.8,"precip_mm":0.0,"prob_chuva":0,"weathercode":3,"tempo":"nuvem"},{"data":"2026-06-28","tmax":26.9,"tmin":16.5,"precip_mm":0.0,"prob_chuva":0,"weathercode":2,"tempo":"parcial"},{"data":"2026-06-29","tmax":25.8,"tmin":15.4,"precip_mm":0.0,"prob_chuva":0,"weathercode":0,"tempo":"sol"},{"data":"2026-06-30","tmax":27.0,"tmin":14.8,"precip_mm":0.0,"prob_chuva":0,"weathercode":0,"tempo":"sol"},{"data":"2026-07-01","tmax":27.5,"tmin":15.9,"precip_mm":0.0,"prob_chuva":2,"weathercode":1,"tempo":"parcial"},{"data":"2026-07-02","tmax":27.6,"tmin":14.9,"precip_mm":0.0,"prob_chuva":0,"weathercode":0,"tempo":"sol"}],"fonte":"Open-Meteo","atualizado_em":"2026-06-26T22:05:04Z"},"colheita":{"pct_plantado":100,"pct_colhido":100,"area_soja_ha":1500,"fonte":"Conab - 9o Levantamento Safra de Graos (jun/2026)","data_referencia":"2026-06-11","granularidade":"estadual aplicado ao municipio","derivado":true,"ha_plantado_estim":1500,"ha_colhido_estim":1500}},{"id":"santa_luzia","nome":"SANTA LUZIA","ibge":3157807,"uf":"MG","lat":-19.7548,"lon":-43.8497,"area_soja_ha":0,"clima":{"ibge":3157807,"nome":"SANTA LUZIA","uf":"MG","lat":-19.7548,"lon":-43.8497,"atual":{"tmax":25.5,"tmin":16.2,"precip_mm":0.0,"prob_chuva":4,"weathercode":3,"tempo":"nuvem"},"previsao_7d":[{"data":"2026-06-26","tmax":25.5,"tmin":16.2,"precip_mm":0.0,"prob_chuva":4,"weathercode":3,"tempo":"nuvem"},{"data":"2026-06-27","tmax":25.5,"tmin":16.7,"precip_mm":0.0,"prob_chuva":0,"weathercode":3,"tempo":"nuvem"},{"data":"2026-06-28","tmax":25.2,"tmin":16.2,"precip_mm":0.0,"prob_chuva":0,"weathercode":3,"tempo":"nuvem"},{"data":"2026-06-29","tmax":25.4,"tmin":15.3,"precip_mm":0.0,"prob_chuva":2,"weathercode":2,"tempo":"parcial"},{"data":"2026-06-30","tmax":26.3,"tmin":15.1,"precip_mm":0.0,"prob_chuva":0,"weathercode":0,"tempo":"sol"},{"data":"2026-07-01","tmax":25.6,"tmin":15.7,"precip_mm":0.0,"prob_chuva":4,"weathercode":3,"tempo":"nuvem"},{"data":"2026-07-02","tmax":27.5,"tmin":15.1,"precip_mm":0.0,"prob_chuva":0,"weathercode":2,"tempo":"parcial"}],"fonte":"Open-Meteo","atualizado_em":"2026-06-26T22:05:04Z"},"colheita":{"pct_plantado":100,"pct_colhido":100,"area_soja_ha":0,"fonte":"Conab - 9o Levantamento Safra de Graos (jun/2026)","data_referencia":"2026-06-11","granularidade":"estadual aplicado ao municipio","derivado":true,"ha_plantado_estim":0,"ha_colhido_estim":0}},{"id":"sao_goncalo_do_abaete","nome":"SÃO GONÇALO DO ABAETÉ","ibge":3161700,"uf":"MG","lat":-18.3315,"lon":-45.8265,"area_soja_ha":2300,"clima":{"ibge":3161700,"nome":"SÃO GONÇALO DO ABAETÉ","uf":"MG","lat":-18.3315,"lon":-45.8265,"atual":{"tmax":25.4,"tmin":15.3,"precip_mm":0.0,"prob_chuva":0,"weathercode":3,"tempo":"nuvem"},"previsao_7d":[{"data":"2026-06-26","tmax":25.4,"tmin":15.3,"precip_mm":0.0,"prob_chuva":0,"weathercode":3,"tempo":"nuvem"},{"data":"2026-06-27","tmax":25.3,"tmin":15.4,"precip_mm":0.0,"prob_chuva":0,"weathercode":2,"tempo":"parcial"},{"data":"2026-06-28","tmax":25.5,"tmin":15.3,"precip_mm":0.0,"prob_chuva":0,"weathercode":3,"tempo":"nuvem"},{"data":"2026-06-29","tmax":25.7,"tmin":14.7,"precip_mm":0.0,"prob_chuva":0,"weathercode":0,"tempo":"sol"},{"data":"2026-06-30","tmax":26.2,"tmin":14.3,"precip_mm":0.0,"prob_chuva":0,"weathercode":0,"tempo":"sol"},{"data":"2026-07-01","tmax":26.8,"tmin":14.7,"precip_mm":0.0,"prob_chuva":2,"weathercode":0,"tempo":"sol"},{"data":"2026-07-02","tmax":27.1,"tmin":15.3,"precip_mm":0.0,"prob_chuva":0,"weathercode":0,"tempo":"sol"}],"fonte":"Open-Meteo","atualizado_em":"2026-06-26T22:05:04Z"},"colheita":{"pct_plantado":100,"pct_colhido":100,"area_soja_ha":2300,"fonte":"Conab - 9o Levantamento Safra de Graos (jun/2026)","data_referencia":"2026-06-11","granularidade":"estadual aplicado ao municipio","derivado":true,"ha_plantado_estim":2300,"ha_colhido_estim":2300}},{"id":"sao_gotardo","nome":"SÃO GOTARDO","ibge":3162104,"uf":"MG","lat":-19.3087,"lon":-46.0465,"area_soja_ha":1500,"clima":{"ibge":3162104,"nome":"SÃO GOTARDO","uf":"MG","lat":-19.3087,"lon":-46.0465,"atual":{"tmax":21.5,"tmin":14.4,"precip_mm":0.0,"prob_chuva":20,"weathercode":3,"tempo":"nuvem"},"previsao_7d":[{"data":"2026-06-26","tmax":21.5,"tmin":14.4,"precip_mm":0.0,"prob_chuva":20,"weathercode":3,"tempo":"nuvem"},{"data":"2026-06-27","tmax":22.3,"tmin":14.1,"precip_mm":0.0,"prob_chuva":0,"weathercode":3,"tempo":"nuvem"},{"data":"2026-06-28","tmax":21.2,"tmin":13.7,"precip_mm":0.0,"prob_chuva":18,"weathercode":3,"tempo":"nuvem"},{"data":"2026-06-29","tmax":22.2,"tmin":13.2,"precip_mm":0.0,"prob_chuva":0,"weathercode":1,"tempo":"parcial"},{"data":"2026-06-30","tmax":22.7,"tmin":12.4,"precip_mm":0.0,"prob_chuva":0,"weathercode":0,"tempo":"sol"},{"data":"2026-07-01","tmax":23.1,"tmin":12.9,"precip_mm":0.0,"prob_chuva":6,"weathercode":0,"tempo":"sol"},{"data":"2026-07-02","tmax":23.3,"tmin":13.5,"precip_mm":0.0,"prob_chuva":1,"weathercode":0,"tempo":"sol"}],"fonte":"Open-Meteo","atualizado_em":"2026-06-26T22:05:04Z"},"colheita":{"pct_plantado":100,"pct_colhido":100,"area_soja_ha":1500,"fonte":"Conab - 9o Levantamento Safra de Graos (jun/2026)","data_referencia":"2026-06-11","granularidade":"estadual aplicado ao municipio","derivado":true,"ha_plantado_estim":1500,"ha_colhido_estim":1500}}],"alertas":{"ativos":[],"ufs":["MG"]},"colheita":{"status":"validado","fonte":"Conab - 9o Levantamento Safra de Graos (jun/2026)","granularidade":"estadual","data_referencia":"2026-06-11","cultura":"soja","itens":[{"regiao":"Minas Gerais","uf":"MG","granularidade":"estadual","pct_plantado":100,"pct_colhido":100,"vs_media5anos":null,"vs_safra_anterior":null,"condicao_lavoura":"Safra 2025/26 encerrada","fonte":"Conab - 9o Levantamento Safra de Graos (jun/2026)","data_referencia":"2026-06-11","safra":"2025/2026","produtividade_kg_ha":null,"area_ha":null,"producao_t":null,"var_producao_pct":null,"preco_rs_sc":113,"preco_data":"2026-05-06","preco_fonte":"Portal Agron (Triangulo Mineiro)"}]},"preco":{"valor":113,"uf":"MG","data":"2026-05-06","fonte":"Portal Agron (Triangulo Mineiro)","unidade":"R$/sc 60kg"}}