{"distrito":{"id":"palmas_soja_ics","nome":"PALMAS-SOJA/ICS","regional":"CERL SOJA","codigo_regional":"CERL","uf":"TO","ufs":["TO"],"cultura_principal":"soja"},"gerado_em":"2026-06-15T13:53:53+00:00","municipios":[{"id":"alvorada","nome":"ALVORADA","ibge":1700707,"uf":"TO","lat":-12.4785,"lon":-49.1249,"area_soja_ha":null,"clima":{"ibge":1700707,"nome":"ALVORADA","uf":"TO","lat":-12.4785,"lon":-49.1249,"atual":{"tmax":34.6,"tmin":22.2,"precip_mm":0.0,"prob_chuva":0,"weathercode":1,"tempo":"parcial"},"previsao_7d":[{"data":"2026-06-15","tmax":34.6,"tmin":22.2,"precip_mm":0.0,"prob_chuva":0,"weathercode":1,"tempo":"parcial"},{"data":"2026-06-16","tmax":34.7,"tmin":23.0,"precip_mm":0.0,"prob_chuva":10,"weathercode":0,"tempo":"sol"},{"data":"2026-06-17","tmax":34.8,"tmin":23.4,"precip_mm":0.0,"prob_chuva":14,"weathercode":1,"tempo":"parcial"},{"data":"2026-06-18","tmax":34.5,"tmin":23.7,"precip_mm":0.1,"prob_chuva":16,"weathercode":51,"tempo":"garoa"},{"data":"2026-06-19","tmax":34.4,"tmin":24.1,"precip_mm":0.0,"prob_chuva":2,"weathercode":1,"tempo":"parcial"},{"data":"2026-06-20","tmax":34.8,"tmin":22.3,"precip_mm":0.0,"prob_chuva":2,"weathercode":3,"tempo":"nuvem"},{"data":"2026-06-21","tmax":35.0,"tmin":23.7,"precip_mm":0.0,"prob_chuva":0,"weathercode":2,"tempo":"parcial"}],"fonte":"Open-Meteo","atualizado_em":"2026-06-15T13:53:52Z"}},{"id":"brejinho_de_nazare","nome":"BREJINHO DE NAZARÉ","ibge":1703701,"uf":"TO","lat":-11.0058,"lon":-48.5683,"area_soja_ha":null,"clima":{"ibge":1703701,"nome":"BREJINHO DE NAZARÉ","uf":"TO","lat":-11.0058,"lon":-48.5683,"atual":{"tmax":35.2,"tmin":22.8,"precip_mm":0.0,"prob_chuva":0,"weathercode":1,"tempo":"parcial"},"previsao_7d":[{"data":"2026-06-15","tmax":35.2,"tmin":22.8,"precip_mm":0.0,"prob_chuva":0,"weathercode":1,"tempo":"parcial"},{"data":"2026-06-16","tmax":35.1,"tmin":23.2,"precip_mm":0.0,"prob_chuva":2,"weathercode":3,"tempo":"nuvem"},{"data":"2026-06-17","tmax":35.5,"tmin":23.3,"precip_mm":0.0,"prob_chuva":4,"weathercode":0,"tempo":"sol"},{"data":"2026-06-18","tmax":34.6,"tmin":24.4,"precip_mm":0.1,"prob_chuva":12,"weathercode":51,"tempo":"garoa"},{"data":"2026-06-19","tmax":34.5,"tmin":23.6,"precip_mm":0.0,"prob_chuva":2,"weathercode":1,"tempo":"parcial"},{"data":"2026-06-20","tmax":34.6,"tmin":23.2,"precip_mm":0.0,"prob_chuva":0,"weathercode":1,"tempo":"parcial"},{"data":"2026-06-21","tmax":34.9,"tmin":24.6,"precip_mm":0.0,"prob_chuva":2,"weathercode":0,"tempo":"sol"}],"fonte":"Open-Meteo","atualizado_em":"2026-06-15T13:53:52Z"}},{"id":"cariri_do_tocantins","nome":"CARIRI DO TOCANTINS","ibge":1703867,"uf":"TO","lat":-11.8881,"lon":-49.1609,"area_soja_ha":null,"clima":{"ibge":1703867,"nome":"CARIRI DO TOCANTINS","uf":"TO","lat":-11.8881,"lon":-49.1609,"atual":{"tmax":33.6,"tmin":21.5,"precip_mm":0.0,"prob_chuva":0,"weathercode":1,"tempo":"parcial"},"previsao_7d":[{"data":"2026-06-15","tmax":33.6,"tmin":21.5,"precip_mm":0.0,"prob_chuva":0,"weathercode":1,"tempo":"parcial"},{"data":"2026-06-16","tmax":33.5,"tmin":22.1,"precip_mm":0.0,"prob_chuva":10,"weathercode":0,"tempo":"sol"},{"data":"2026-06-17","tmax":33.4,"tmin":22.6,"precip_mm":0.0,"prob_chuva":6,"weathercode":1,"tempo":"parcial"},{"data":"2026-06-18","tmax":33.5,"tmin":22.7,"precip_mm":0.0,"prob_chuva":14,"weathercode":3,"tempo":"nuvem"},{"data":"2026-06-19","tmax":33.8,"tmin":23.5,"precip_mm":0.0,"prob_chuva":0,"weathercode":0,"tempo":"sol"},{"data":"2026-06-20","tmax":34.3,"tmin":22.3,"precip_mm":0.0,"prob_chuva":2,"weathercode":0,"tempo":"sol"},{"data":"2026-06-21","tmax":34.2,"tmin":23.5,"precip_mm":0.0,"prob_chuva":0,"weathercode":0,"tempo":"sol"}],"fonte":"Open-Meteo","atualizado_em":"2026-06-15T13:53:52Z"}},{"id":"caseara","nome":"CASEARA","ibge":1703909,"uf":"TO","lat":-9.27612,"lon":-49.9521,"area_soja_ha":null,"clima":{"ibge":1703909,"nome":"CASEARA","uf":"TO","lat":-9.27612,"lon":-49.9521,"atual":{"tmax":33.8,"tmin":23.2,"precip_mm":0.0,"prob_chuva":2,"weathercode":1,"tempo":"parcial"},"previsao_7d":[{"data":"2026-06-15","tmax":33.8,"tmin":23.2,"precip_mm":0.0,"prob_chuva":2,"weathercode":1,"tempo":"parcial"},{"data":"2026-06-16","tmax":34.1,"tmin":23.4,"precip_mm":0.0,"prob_chuva":6,"weathercode":1,"tempo":"parcial"},{"data":"2026-06-17","tmax":33.7,"tmin":23.5,"precip_mm":0.0,"prob_chuva":14,"weathercode":2,"tempo":"parcial"},{"data":"2026-06-18","tmax":33.1,"tmin":23.8,"precip_mm":0.8,"prob_chuva":55,"weathercode":53,"tempo":"garoa"},{"data":"2026-06-19","tmax":32.2,"tmin":23.5,"precip_mm":0.3,"prob_chuva":35,"weathercode":95,"tempo":"trovoada"},{"data":"2026-06-20","tmax":32.9,"tmin":23.4,"precip_mm":0.0,"prob_chuva":12,"weathercode":1,"tempo":"parcial"},{"data":"2026-06-21","tmax":31.7,"tmin":24.0,"precip_mm":0.0,"prob_chuva":7,"weathercode":0,"tempo":"sol"}],"fonte":"Open-Meteo","atualizado_em":"2026-06-15T13:53:52Z"}},{"id":"colinas_do_tocantins","nome":"COLINAS DO TOCANTINS","ibge":1705508,"uf":"TO","lat":-8.05764,"lon":-48.4757,"area_soja_ha":null,"clima":{"ibge":1705508,"nome":"COLINAS DO TOCANTINS","uf":"TO","lat":-8.05764,"lon":-48.4757,"atual":{"tmax":35.0,"tmin":22.3,"precip_mm":0.0,"prob_chuva":0,"weathercode":0,"tempo":"sol"},"previsao_7d":[{"data":"2026-06-15","tmax":35.0,"tmin":22.3,"precip_mm":0.0,"prob_chuva":0,"weathercode":0,"tempo":"sol"},{"data":"2026-06-16","tmax":34.6,"tmin":22.3,"precip_mm":0.0,"prob_chuva":16,"weathercode":0,"tempo":"sol"},{"data":"2026-06-17","tmax":33.3,"tmin":22.2,"precip_mm":0.2,"prob_chuva":35,"weathercode":51,"tempo":"garoa"},{"data":"2026-06-18","tmax":33.5,"tmin":23.1,"precip_mm":1.4,"prob_chuva":59,"weathercode":53,"tempo":"garoa"},{"data":"2026-06-19","tmax":32.1,"tmin":21.2,"precip_mm":0.6,"prob_chuva":27,"weathercode":51,"tempo":"garoa"},{"data":"2026-06-20","tmax":32.2,"tmin":21.9,"precip_mm":0.3,"prob_chuva":20,"weathercode":51,"tempo":"garoa"},{"data":"2026-06-21","tmax":33.0,"tmin":22.9,"precip_mm":1.2,"prob_chuva":10,"weathercode":51,"tempo":"garoa"}],"fonte":"Open-Meteo","atualizado_em":"2026-06-15T13:53:52Z"}},{"id":"crixas_do_tocantins","nome":"CRIXÁS DO TOCANTINS","ibge":1706258,"uf":"TO","lat":-11.0994,"lon":-48.9152,"area_soja_ha":null,"clima":{"ibge":1706258,"nome":"CRIXÁS DO TOCANTINS","uf":"TO","lat":-11.0994,"lon":-48.9152,"atual":{"tmax":35.4,"tmin":22.4,"precip_mm":0.0,"prob_chuva":0,"weathercode":0,"tempo":"sol"},"previsao_7d":[{"data":"2026-06-15","tmax":35.4,"tmin":22.4,"precip_mm":0.0,"prob_chuva":0,"weathercode":0,"tempo":"sol"},{"data":"2026-06-16","tmax":35.5,"tmin":23.7,"precip_mm":0.0,"prob_chuva":2,"weathercode":3,"tempo":"nuvem"},{"data":"2026-06-17","tmax":35.6,"tmin":23.7,"precip_mm":0.0,"prob_chuva":8,"weathercode":1,"tempo":"parcial"},{"data":"2026-06-18","tmax":34.8,"tmin":24.7,"precip_mm":0.3,"prob_chuva":14,"weathercode":51,"tempo":"garoa"},{"data":"2026-06-19","tmax":34.6,"tmin":23.7,"precip_mm":0.0,"prob_chuva":2,"weathercode":1,"tempo":"parcial"},{"data":"2026-06-20","tmax":35.5,"tmin":22.8,"precip_mm":0.0,"prob_chuva":4,"weathercode":1,"tempo":"parcial"},{"data":"2026-06-21","tmax":34.9,"tmin":24.5,"precip_mm":0.0,"prob_chuva":4,"weathercode":0,"tempo":"sol"}],"fonte":"Open-Meteo","atualizado_em":"2026-06-15T13:53:52Z"}},{"id":"divinopolis_do_tocantins","nome":"DIVINÓPOLIS DO TOCANTINS","ibge":1707108,"uf":"TO","lat":-9.80018,"lon":-49.2169,"area_soja_ha":null,"clima":{"ibge":1707108,"nome":"DIVINÓPOLIS DO TOCANTINS","uf":"TO","lat":-9.80018,"lon":-49.2169,"atual":{"tmax":35.7,"tmin":23.7,"precip_mm":0.0,"prob_chuva":0,"weathercode":1,"tempo":"parcial"},"previsao_7d":[{"data":"2026-06-15","tmax":35.7,"tmin":23.7,"precip_mm":0.0,"prob_chuva":0,"weathercode":1,"tempo":"parcial"},{"data":"2026-06-16","tmax":35.6,"tmin":24.0,"precip_mm":0.0,"prob_chuva":0,"weathercode":2,"tempo":"parcial"},{"data":"2026-06-17","tmax":35.2,"tmin":23.8,"precip_mm":0.0,"prob_chuva":8,"weathercode":2,"tempo":"parcial"},{"data":"2026-06-18","tmax":34.1,"tmin":24.2,"precip_mm":0.3,"prob_chuva":47,"weathercode":51,"tempo":"garoa"},{"data":"2026-06-19","tmax":34.4,"tmin":23.6,"precip_mm":0.9,"prob_chuva":24,"weathercode":51,"tempo":"garoa"},{"data":"2026-06-20","tmax":34.3,"tmin":22.9,"precip_mm":0.0,"prob_chuva":2,"weathercode":0,"tempo":"sol"},{"data":"2026-06-21","tmax":33.8,"tmin":24.9,"precip_mm":0.0,"prob_chuva":4,"weathercode":0,"tempo":"sol"}],"fonte":"Open-Meteo","atualizado_em":"2026-06-15T13:53:52Z"}},{"id":"dois_irmaos_do_tocantins","nome":"DOIS IRMÃOS DO TOCANTINS","ibge":1707207,"uf":"TO","lat":-9.25534,"lon":-49.0638,"area_soja_ha":null,"clima":{"ibge":1707207,"nome":"DOIS IRMÃOS DO TOCANTINS","uf":"TO","lat":-9.25534,"lon":-49.0638,"atual":{"tmax":35.7,"tmin":24.3,"precip_mm":0.0,"prob_chuva":0,"weathercode":0,"tempo":"sol"},"previsao_7d":[{"data":"2026-06-15","tmax":35.7,"tmin":24.3,"precip_mm":0.0,"prob_chuva":0,"weathercode":0,"tempo":"sol"},{"data":"2026-06-16","tmax":36.4,"tmin":23.8,"precip_mm":0.0,"prob_chuva":2,"weathercode":1,"tempo":"parcial"},{"data":"2026-06-17","tmax":34.8,"tmin":24.4,"precip_mm":0.0,"prob_chuva":16,"weathercode":3,"tempo":"nuvem"},{"data":"2026-06-18","tmax":33.9,"tmin":24.5,"precip_mm":0.8,"prob_chuva":41,"weathercode":51,"tempo":"garoa"},{"data":"2026-06-19","tmax":34.1,"tmin":24.0,"precip_mm":0.0,"prob_chuva":24,"weathercode":1,"tempo":"parcial"},{"data":"2026-06-20","tmax":35.0,"tmin":23.5,"precip_mm":0.0,"prob_chuva":6,"weathercode":0,"tempo":"sol"},{"data":"2026-06-21","tmax":34.0,"tmin":24.8,"precip_mm":0.6,"prob_chuva":4,"weathercode":51,"tempo":"garoa"}],"fonte":"Open-Meteo","atualizado_em":"2026-06-15T13:53:52Z"}},{"id":"fatima","nome":"FÁTIMA","ibge":1707553,"uf":"TO","lat":-10.7603,"lon":-48.9076,"area_soja_ha":null,"clima":{"ibge":1707553,"nome":"FÁTIMA","uf":"TO","lat":-10.7603,"lon":-48.9076,"atual":{"tmax":34.8,"tmin":22.5,"precip_mm":0.0,"prob_chuva":0,"weathercode":0,"tempo":"sol"},"previsao_7d":[{"data":"2026-06-15","tmax":34.8,"tmin":22.5,"precip_mm":0.0,"prob_chuva":0,"weathercode":0,"tempo":"sol"},{"data":"2026-06-16","tmax":35.1,"tmin":23.8,"precip_mm":0.0,"prob_chuva":4,"weathercode":1,"tempo":"parcial"},{"data":"2026-06-17","tmax":35.1,"tmin":23.6,"precip_mm":0.0,"prob_chuva":8,"weathercode":1,"tempo":"parcial"},{"data":"2026-06-18","tmax":34.1,"tmin":24.4,"precip_mm":0.3,"prob_chuva":29,"weathercode":51,"tempo":"garoa"},{"data":"2026-06-19","tmax":33.9,"tmin":23.0,"precip_mm":0.0,"prob_chuva":8,"weathercode":1,"tempo":"parcial"},{"data":"2026-06-20","tmax":34.8,"tmin":22.8,"precip_mm":0.0,"prob_chuva":2,"weathercode":2,"tempo":"parcial"},{"data":"2026-06-21","tmax":33.6,"tmin":24.6,"precip_mm":0.0,"prob_chuva":2,"weathercode":0,"tempo":"sol"}],"fonte":"Open-Meteo","atualizado_em":"2026-06-15T13:53:52Z"}},{"id":"figueiropolis","nome":"FIGUEIRÓPOLIS","ibge":1707652,"uf":"TO","lat":-12.1312,"lon":-49.1748,"area_soja_ha":null,"clima":{"ibge":1707652,"nome":"FIGUEIRÓPOLIS","uf":"TO","lat":-12.1312,"lon":-49.1748,"atual":{"tmax":34.4,"tmin":22.2,"precip_mm":0.0,"prob_chuva":0,"weathercode":0,"tempo":"sol"},"previsao_7d":[{"data":"2026-06-15","tmax":34.4,"tmin":22.2,"precip_mm":0.0,"prob_chuva":0,"weathercode":0,"tempo":"sol"},{"data":"2026-06-16","tmax":34.7,"tmin":22.6,"precip_mm":0.0,"prob_chuva":10,"weathercode":1,"tempo":"parcial"},{"data":"2026-06-17","tmax":34.6,"tmin":23.4,"precip_mm":0.0,"prob_chuva":12,"weathercode":0,"tempo":"sol"},{"data":"2026-06-18","tmax":34.4,"tmin":23.4,"precip_mm":0.0,"prob_chuva":4,"weathercode":3,"tempo":"nuvem"},{"data":"2026-06-19","tmax":34.5,"tmin":24.6,"precip_mm":0.0,"prob_chuva":2,"weathercode":1,"tempo":"parcial"},{"data":"2026-06-20","tmax":34.9,"tmin":22.6,"precip_mm":0.0,"prob_chuva":4,"weathercode":2,"tempo":"parcial"},{"data":"2026-06-21","tmax":34.4,"tmin":23.7,"precip_mm":0.0,"prob_chuva":0,"weathercode":1,"tempo":"parcial"}],"fonte":"Open-Meteo","atualizado_em":"2026-06-15T13:53:52Z"}},{"id":"formoso_do_araguaia","nome":"FORMOSO DO ARAGUAIA","ibge":1708205,"uf":"TO","lat":-11.7976,"lon":-49.5316,"area_soja_ha":null,"clima":{"ibge":1708205,"nome":"FORMOSO DO ARAGUAIA","uf":"TO","lat":-11.7976,"lon":-49.5316,"atual":{"tmax":35.8,"tmin":24.1,"precip_mm":0.0,"prob_chuva":0,"weathercode":0,"tempo":"sol"},"previsao_7d":[{"data":"2026-06-15","tmax":35.8,"tmin":24.1,"precip_mm":0.0,"prob_chuva":0,"weathercode":0,"tempo":"sol"},{"data":"2026-06-16","tmax":35.5,"tmin":24.5,"precip_mm":0.1,"prob_chuva":24,"weathercode":51,"tempo":"garoa"},{"data":"2026-06-17","tmax":35.4,"tmin":25.1,"precip_mm":0.1,"prob_chuva":20,"weathercode":51,"tempo":"garoa"},{"data":"2026-06-18","tmax":35.1,"tmin":25.2,"precip_mm":0.3,"prob_chuva":24,"weathercode":51,"tempo":"garoa"},{"data":"2026-06-19","tmax":35.1,"tmin":25.2,"precip_mm":0.0,"prob_chuva":2,"weathercode":1,"tempo":"parcial"},{"data":"2026-06-20","tmax":35.8,"tmin":24.1,"precip_mm":0.0,"prob_chuva":4,"weathercode":0,"tempo":"sol"},{"data":"2026-06-21","tmax":35.1,"tmin":24.7,"precip_mm":0.0,"prob_chuva":0,"weathercode":1,"tempo":"parcial"}],"fonte":"Open-Meteo","atualizado_em":"2026-06-15T13:53:52Z"}},{"id":"guarai","nome":"GUARAÍ","ibge":1709302,"uf":"TO","lat":-8.83543,"lon":-48.5114,"area_soja_ha":null,"clima":{"ibge":1709302,"nome":"GUARAÍ","uf":"TO","lat":-8.83543,"lon":-48.5114,"atual":{"tmax":34.7,"tmin":23.0,"precip_mm":0.0,"prob_chuva":0,"weathercode":0,"tempo":"sol"},"previsao_7d":[{"data":"2026-06-15","tmax":34.7,"tmin":23.0,"precip_mm":0.0,"prob_chuva":0,"weathercode":0,"tempo":"sol"},{"data":"2026-06-16","tmax":34.9,"tmin":23.7,"precip_mm":0.0,"prob_chuva":2,"weathercode":1,"tempo":"parcial"},{"data":"2026-06-17","tmax":33.7,"tmin":22.0,"precip_mm":0.1,"prob_chuva":22,"weathercode":51,"tempo":"garoa"},{"data":"2026-06-18","tmax":33.1,"tmin":22.3,"precip_mm":0.9,"prob_chuva":55,"weathercode":51,"tempo":"garoa"},{"data":"2026-06-19","tmax":33.5,"tmin":21.6,"precip_mm":0.3,"prob_chuva":27,"weathercode":51,"tempo":"garoa"},{"data":"2026-06-20","tmax":33.6,"tmin":21.3,"precip_mm":0.0,"prob_chuva":4,"weathercode":1,"tempo":"parcial"},{"data":"2026-06-21","tmax":32.6,"tmin":23.0,"precip_mm":0.6,"prob_chuva":20,"weathercode":51,"tempo":"garoa"}],"fonte":"Open-Meteo","atualizado_em":"2026-06-15T13:53:52Z"}},{"id":"gurupi","nome":"GURUPI","ibge":1709500,"uf":"TO","lat":-11.7279,"lon":-49.068,"area_soja_ha":null,"clima":{"ibge":1709500,"nome":"GURUPI","uf":"TO","lat":-11.7279,"lon":-49.068,"atual":{"tmax":34.9,"tmin":22.5,"precip_mm":0.0,"prob_chuva":0,"weathercode":0,"tempo":"sol"},"previsao_7d":[{"data":"2026-06-15","tmax":34.9,"tmin":22.5,"precip_mm":0.0,"prob_chuva":0,"weathercode":0,"tempo":"sol"},{"data":"2026-06-16","tmax":34.9,"tmin":23.5,"precip_mm":0.0,"prob_chuva":2,"weathercode":1,"tempo":"parcial"},{"data":"2026-06-17","tmax":34.4,"tmin":23.9,"precip_mm":0.2,"prob_chuva":10,"weathercode":51,"tempo":"garoa"},{"data":"2026-06-18","tmax":34.2,"tmin":24.3,"precip_mm":0.0,"prob_chuva":6,"weathercode":2,"tempo":"parcial"},{"data":"2026-06-19","tmax":34.3,"tmin":24.5,"precip_mm":0.0,"prob_chuva":0,"weathercode":0,"tempo":"sol"},{"data":"2026-06-20","tmax":34.9,"tmin":24.9,"precip_mm":0.0,"prob_chuva":4,"weathercode":1,"tempo":"parcial"},{"data":"2026-06-21","tmax":34.7,"tmin":25.0,"precip_mm":0.0,"prob_chuva":0,"weathercode":0,"tempo":"sol"}],"fonte":"Open-Meteo","atualizado_em":"2026-06-15T13:53:52Z"}},{"id":"lagoa_da_confusao","nome":"LAGOA DA CONFUSÃO","ibge":1711902,"uf":"TO","lat":-10.7906,"lon":-49.6199,"area_soja_ha":null,"clima":{"ibge":1711902,"nome":"LAGOA DA CONFUSÃO","uf":"TO","lat":-10.7906,"lon":-49.6199,"atual":{"tmax":36.5,"tmin":22.8,"precip_mm":0.0,"prob_chuva":0,"weathercode":0,"tempo":"sol"},"previsao_7d":[{"data":"2026-06-15","tmax":36.5,"tmin":22.8,"precip_mm":0.0,"prob_chuva":0,"weathercode":0,"tempo":"sol"},{"data":"2026-06-16","tmax":36.3,"tmin":24.0,"precip_mm":0.0,"prob_chuva":6,"weathercode":1,"tempo":"parcial"},{"data":"2026-06-17","tmax":35.9,"tmin":24.2,"precip_mm":0.0,"prob_chuva":6,"weathercode":3,"tempo":"nuvem"},{"data":"2026-06-18","tmax":35.6,"tmin":23.8,"precip_mm":0.0,"prob_chuva":41,"weathercode":3,"tempo":"nuvem"},{"data":"2026-06-19","tmax":34.8,"tmin":23.8,"precip_mm":0.3,"prob_chuva":14,"weathercode":51,"tempo":"garoa"},{"data":"2026-06-20","tmax":36.3,"tmin":23.8,"precip_mm":0.0,"prob_chuva":6,"weathercode":0,"tempo":"sol"},{"data":"2026-06-21","tmax":34.2,"tmin":25.1,"precip_mm":0.0,"prob_chuva":4,"weathercode":1,"tempo":"parcial"}],"fonte":"Open-Meteo","atualizado_em":"2026-06-15T13:53:52Z"}},{"id":"marianopolis_do_tocantins","nome":"MARIANÓPOLIS DO TOCANTINS","ibge":1712504,"uf":"TO","lat":-9.79377,"lon":-49.6553,"area_soja_ha":null,"clima":{"ibge":1712504,"nome":"MARIANÓPOLIS DO TOCANTINS","uf":"TO","lat":-9.79377,"lon":-49.6553,"atual":{"tmax":36.9,"tmin":24.0,"precip_mm":0.0,"prob_chuva":0,"weathercode":1,"tempo":"parcial"},"previsao_7d":[{"data":"2026-06-15","tmax":36.9,"tmin":24.0,"precip_mm":0.0,"prob_chuva":0,"weathercode":1,"tempo":"parcial"},{"data":"2026-06-16","tmax":36.7,"tmin":23.5,"precip_mm":0.0,"prob_chuva":0,"weathercode":0,"tempo":"sol"},{"data":"2026-06-17","tmax":36.0,"tmin":23.9,"precip_mm":0.0,"prob_chuva":12,"weathercode":1,"tempo":"parcial"},{"data":"2026-06-18","tmax":34.8,"tmin":23.9,"precip_mm":0.3,"prob_chuva":53,"weathercode":51,"tempo":"garoa"},{"data":"2026-06-19","tmax":34.2,"tmin":23.6,"precip_mm":0.0,"prob_chuva":25,"weathercode":0,"tempo":"sol"},{"data":"2026-06-20","tmax":34.8,"tmin":23.3,"precip_mm":0.0,"prob_chuva":2,"weathercode":0,"tempo":"sol"},{"data":"2026-06-21","tmax":34.0,"tmin":24.8,"precip_mm":0.0,"prob_chuva":6,"weathercode":1,"tempo":"parcial"}],"fonte":"Open-Meteo","atualizado_em":"2026-06-15T13:53:52Z"}},{"id":"miranorte","nome":"MIRANORTE","ibge":1713304,"uf":"TO","lat":-9.52907,"lon":-48.5922,"area_soja_ha":null,"clima":{"ibge":1713304,"nome":"MIRANORTE","uf":"TO","lat":-9.52907,"lon":-48.5922,"atual":{"tmax":36.1,"tmin":23.0,"precip_mm":0.0,"prob_chuva":0,"weathercode":0,"tempo":"sol"},"previsao_7d":[{"data":"2026-06-15","tmax":36.1,"tmin":23.0,"precip_mm":0.0,"prob_chuva":0,"weathercode":0,"tempo":"sol"},{"data":"2026-06-16","tmax":35.7,"tmin":23.0,"precip_mm":0.0,"prob_chuva":0,"weathercode":3,"tempo":"nuvem"},{"data":"2026-06-17","tmax":35.3,"tmin":23.8,"precip_mm":0.0,"prob_chuva":4,"weathercode":2,"tempo":"parcial"},{"data":"2026-06-18","tmax":34.7,"tmin":24.1,"precip_mm":0.3,"prob_chuva":37,"weathercode":51,"tempo":"garoa"},{"data":"2026-06-19","tmax":35.2,"tmin":23.5,"precip_mm":0.0,"prob_chuva":10,"weathercode":0,"tempo":"sol"},{"data":"2026-06-20","tmax":35.0,"tmin":22.5,"precip_mm":0.0,"prob_chuva":4,"weathercode":1,"tempo":"parcial"},{"data":"2026-06-21","tmax":34.2,"tmin":24.0,"precip_mm":0.6,"prob_chuva":5,"weathercode":51,"tempo":"garoa"}],"fonte":"Open-Meteo","atualizado_em":"2026-06-15T13:53:52Z"}},{"id":"palmas","nome":"PALMAS","ibge":1721000,"uf":"TO","lat":-10.24,"lon":-48.3558,"area_soja_ha":null,"clima":{"ibge":1721000,"nome":"PALMAS","uf":"TO","lat":-10.24,"lon":-48.3558,"atual":{"tmax":33.8,"tmin":24.6,"precip_mm":0.0,"prob_chuva":0,"weathercode":0,"tempo":"sol"},"previsao_7d":[{"data":"2026-06-15","tmax":33.8,"tmin":24.6,"precip_mm":0.0,"prob_chuva":0,"weathercode":0,"tempo":"sol"},{"data":"2026-06-16","tmax":33.8,"tmin":26.3,"precip_mm":0.0,"prob_chuva":2,"weathercode":0,"tempo":"sol"},{"data":"2026-06-17","tmax":33.8,"tmin":26.8,"precip_mm":0.5,"prob_chuva":16,"weathercode":51,"tempo":"garoa"},{"data":"2026-06-18","tmax":33.9,"tmin":26.8,"precip_mm":0.7,"prob_chuva":39,"weathercode":51,"tempo":"garoa"},{"data":"2026-06-19","tmax":33.3,"tmin":25.0,"precip_mm":0.0,"prob_chuva":14,"weathercode":1,"tempo":"parcial"},{"data":"2026-06-20","tmax":33.0,"tmin":24.0,"precip_mm":0.0,"prob_chuva":6,"weathercode":0,"tempo":"sol"},{"data":"2026-06-21","tmax":33.4,"tmin":25.6,"precip_mm":0.0,"prob_chuva":10,"weathercode":0,"tempo":"sol"}],"fonte":"Open-Meteo","atualizado_em":"2026-06-15T13:53:52Z"}},{"id":"palmeirante","nome":"PALMEIRANTE","ibge":1715705,"uf":"TO","lat":-7.84786,"lon":-47.9242,"area_soja_ha":null,"clima":{"ibge":1715705,"nome":"PALMEIRANTE","uf":"TO","lat":-7.84786,"lon":-47.9242,"atual":{"tmax":35.2,"tmin":23.1,"precip_mm":0.0,"prob_chuva":0,"weathercode":1,"tempo":"parcial"},"previsao_7d":[{"data":"2026-06-15","tmax":35.2,"tmin":23.1,"precip_mm":0.0,"prob_chuva":0,"weathercode":1,"tempo":"parcial"},{"data":"2026-06-16","tmax":35.2,"tmin":23.0,"precip_mm":0.0,"prob_chuva":4,"weathercode":1,"tempo":"parcial"},{"data":"2026-06-17","tmax":34.2,"tmin":23.7,"precip_mm":0.0,"prob_chuva":23,"weathercode":1,"tempo":"parcial"},{"data":"2026-06-18","tmax":33.9,"tmin":24.3,"precip_mm":1.5,"prob_chuva":41,"weathercode":55,"tempo":"garoa"},{"data":"2026-06-19","tmax":33.9,"tmin":23.8,"precip_mm":0.3,"prob_chuva":18,"weathercode":51,"tempo":"garoa"},{"data":"2026-06-20","tmax":32.7,"tmin":23.4,"precip_mm":0.0,"prob_chuva":18,"weathercode":2,"tempo":"parcial"},{"data":"2026-06-21","tmax":33.5,"tmin":24.5,"precip_mm":0.6,"prob_chuva":4,"weathercode":51,"tempo":"garoa"}],"fonte":"Open-Meteo","atualizado_em":"2026-06-15T13:53:52Z"}},{"id":"paraiso_do_tocantins","nome":"PARAÍSO DO TOCANTINS","ibge":1716109,"uf":"TO","lat":-10.175,"lon":-48.8823,"area_soja_ha":null,"clima":{"ibge":1716109,"nome":"PARAÍSO DO TOCANTINS","uf":"TO","lat":-10.175,"lon":-48.8823,"atual":{"tmax":32.9,"tmin":24.2,"precip_mm":0.0,"prob_chuva":0,"weathercode":0,"tempo":"sol"},"previsao_7d":[{"data":"2026-06-15","tmax":32.9,"tmin":24.2,"precip_mm":0.0,"prob_chuva":0,"weathercode":0,"tempo":"sol"},{"data":"2026-06-16","tmax":33.1,"tmin":22.7,"precip_mm":0.0,"prob_chuva":2,"weathercode":0,"tempo":"sol"},{"data":"2026-06-17","tmax":33.3,"tmin":23.0,"precip_mm":0.3,"prob_chuva":2,"weathercode":51,"tempo":"garoa"},{"data":"2026-06-18","tmax":32.9,"tmin":23.9,"precip_mm":0.4,"prob_chuva":35,"weathercode":51,"tempo":"garoa"},{"data":"2026-06-19","tmax":32.4,"tmin":21.6,"precip_mm":0.0,"prob_chuva":16,"weathercode":0,"tempo":"sol"},{"data":"2026-06-20","tmax":33.0,"tmin":22.9,"precip_mm":0.0,"prob_chuva":4,"weathercode":0,"tempo":"sol"},{"data":"2026-06-21","tmax":32.7,"tmin":23.5,"precip_mm":0.0,"prob_chuva":4,"weathercode":0,"tempo":"sol"}],"fonte":"Open-Meteo","atualizado_em":"2026-06-15T13:53:52Z"}},{"id":"pedro_afonso","nome":"PEDRO AFONSO","ibge":1716505,"uf":"TO","lat":-8.97034,"lon":-48.1729,"area_soja_ha":null,"clima":{"ibge":1716505,"nome":"PEDRO AFONSO","uf":"TO","lat":-8.97034,"lon":-48.1729,"atual":{"tmax":35.7,"tmin":23.3,"precip_mm":0.0,"prob_chuva":0,"weathercode":0,"tempo":"sol"},"previsao_7d":[{"data":"2026-06-15","tmax":35.7,"tmin":23.3,"precip_mm":0.0,"prob_chuva":0,"weathercode":0,"tempo":"sol"},{"data":"2026-06-16","tmax":35.5,"tmin":23.0,"precip_mm":0.0,"prob_chuva":0,"weathercode":1,"tempo":"parcial"},{"data":"2026-06-17","tmax":34.5,"tmin":24.2,"precip_mm":0.0,"prob_chuva":16,"weathercode":3,"tempo":"nuvem"},{"data":"2026-06-18","tmax":33.5,"tmin":23.0,"precip_mm":0.5,"prob_chuva":41,"weathercode":51,"tempo":"garoa"},{"data":"2026-06-19","tmax":35.2,"tmin":22.9,"precip_mm":0.0,"prob_chuva":10,"weathercode":0,"tempo":"sol"},{"data":"2026-06-20","tmax":34.2,"tmin":23.3,"precip_mm":0.0,"prob_chuva":6,"weathercode":0,"tempo":"sol"},{"data":"2026-06-21","tmax":34.3,"tmin":24.3,"precip_mm":0.0,"prob_chuva":4,"weathercode":2,"tempo":"parcial"}],"fonte":"Open-Meteo","atualizado_em":"2026-06-15T13:53:52Z"}},{"id":"peixe","nome":"PEIXE","ibge":1716604,"uf":"TO","lat":-12.0254,"lon":-48.5395,"area_soja_ha":null,"clima":{"ibge":1716604,"nome":"PEIXE","uf":"TO","lat":-12.0254,"lon":-48.5395,"atual":{"tmax":35.4,"tmin":23.8,"precip_mm":0.0,"prob_chuva":0,"weathercode":0,"tempo":"sol"},"previsao_7d":[{"data":"2026-06-15","tmax":35.4,"tmin":23.8,"precip_mm":0.0,"prob_chuva":0,"weathercode":0,"tempo":"sol"},{"data":"2026-06-16","tmax":34.9,"tmin":23.2,"precip_mm":0.0,"prob_chuva":4,"weathercode":1,"tempo":"parcial"},{"data":"2026-06-17","tmax":35.0,"tmin":24.1,"precip_mm":0.0,"prob_chuva":10,"weathercode":1,"tempo":"parcial"},{"data":"2026-06-18","tmax":34.7,"tmin":25.7,"precip_mm":0.3,"prob_chuva":12,"weathercode":51,"tempo":"garoa"},{"data":"2026-06-19","tmax":34.4,"tmin":26.1,"precip_mm":0.0,"prob_chuva":0,"weathercode":2,"tempo":"parcial"},{"data":"2026-06-20","tmax":34.5,"tmin":23.7,"precip_mm":0.0,"prob_chuva":2,"weathercode":1,"tempo":"parcial"},{"data":"2026-06-21","tmax":34.8,"tmin":24.0,"precip_mm":0.0,"prob_chuva":0,"weathercode":1,"tempo":"parcial"}],"fonte":"Open-Meteo","atualizado_em":"2026-06-15T13:53:52Z"}},{"id":"porto_nacional","nome":"PORTO NACIONAL","ibge":1718204,"uf":"TO","lat":-10.7027,"lon":-48.408,"area_soja_ha":null,"clima":{"ibge":1718204,"nome":"PORTO NACIONAL","uf":"TO","lat":-10.7027,"lon":-48.408,"atual":{"tmax":32.9,"tmin":24.0,"precip_mm":0.0,"prob_chuva":0,"weathercode":0,"tempo":"sol"},"previsao_7d":[{"data":"2026-06-15","tmax":32.9,"tmin":24.0,"precip_mm":0.0,"prob_chuva":0,"weathercode":0,"tempo":"sol"},{"data":"2026-06-16","tmax":32.9,"tmin":24.6,"precip_mm":0.0,"prob_chuva":0,"weathercode":3,"tempo":"nuvem"},{"data":"2026-06-17","tmax":33.4,"tmin":24.6,"precip_mm":0.0,"prob_chuva":2,"weathercode":1,"tempo":"parcial"},{"data":"2026-06-18","tmax":32.6,"tmin":24.9,"precip_mm":0.4,"prob_chuva":18,"weathercode":51,"tempo":"garoa"},{"data":"2026-06-19","tmax":32.5,"tmin":25.2,"precip_mm":0.0,"prob_chuva":4,"weathercode":1,"tempo":"parcial"},{"data":"2026-06-20","tmax":32.6,"tmin":24.2,"precip_mm":0.0,"prob_chuva":2,"weathercode":0,"tempo":"sol"},{"data":"2026-06-21","tmax":32.7,"tmin":25.3,"precip_mm":0.0,"prob_chuva":0,"weathercode":1,"tempo":"parcial"}],"fonte":"Open-Meteo","atualizado_em":"2026-06-15T13:53:52Z"}},{"id":"santa_rosa_do_tocantins","nome":"SANTA ROSA DO TOCANTINS","ibge":1718907,"uf":"TO","lat":-11.4474,"lon":-48.1216,"area_soja_ha":null,"clima":{"ibge":1718907,"nome":"SANTA ROSA DO TOCANTINS","uf":"TO","lat":-11.4474,"lon":-48.1216,"atual":{"tmax":36.1,"tmin":23.6,"precip_mm":0.0,"prob_chuva":0,"weathercode":0,"tempo":"sol"},"previsao_7d":[{"data":"2026-06-15","tmax":36.1,"tmin":23.6,"precip_mm":0.0,"prob_chuva":0,"weathercode":0,"tempo":"sol"},{"data":"2026-06-16","tmax":35.9,"tmin":23.9,"precip_mm":0.0,"prob_chuva":2,"weathercode":1,"tempo":"parcial"},{"data":"2026-06-17","tmax":35.6,"tmin":25.1,"precip_mm":0.0,"prob_chuva":2,"weathercode":1,"tempo":"parcial"},{"data":"2026-06-18","tmax":34.9,"tmin":26.0,"precip_mm":0.1,"prob_chuva":10,"weathercode":51,"tempo":"garoa"},{"data":"2026-06-19","tmax":35.2,"tmin":25.2,"precip_mm":0.0,"prob_chuva":2,"weathercode":2,"tempo":"parcial"},{"data":"2026-06-20","tmax":35.1,"tmin":24.1,"precip_mm":0.0,"prob_chuva":0,"weathercode":0,"tempo":"sol"},{"data":"2026-06-21","tmax":35.3,"tmin":24.5,"precip_mm":0.0,"prob_chuva":0,"weathercode":1,"tempo":"parcial"}],"fonte":"Open-Meteo","atualizado_em":"2026-06-15T13:53:52Z"}},{"id":"silvanopolis","nome":"SILVANÓPOLIS","ibge":1720655,"uf":"TO","lat":-11.1471,"lon":-48.1694,"area_soja_ha":null,"clima":{"ibge":1720655,"nome":"SILVANÓPOLIS","uf":"TO","lat":-11.1471,"lon":-48.1694,"atual":{"tmax":34.9,"tmin":22.7,"precip_mm":0.0,"prob_chuva":0,"weathercode":3,"tempo":"nuvem"},"previsao_7d":[{"data":"2026-06-15","tmax":34.9,"tmin":22.7,"precip_mm":0.0,"prob_chuva":0,"weathercode":3,"tempo":"nuvem"},{"data":"2026-06-16","tmax":34.9,"tmin":23.6,"precip_mm":0.0,"prob_chuva":0,"weathercode":3,"tempo":"nuvem"},{"data":"2026-06-17","tmax":35.5,"tmin":23.9,"precip_mm":0.0,"prob_chuva":2,"weathercode":1,"tempo":"parcial"},{"data":"2026-06-18","tmax":34.6,"tmin":24.5,"precip_mm":0.1,"prob_chuva":10,"weathercode":51,"tempo":"garoa"},{"data":"2026-06-19","tmax":34.5,"tmin":24.6,"precip_mm":0.0,"prob_chuva":1,"weathercode":1,"tempo":"parcial"},{"data":"2026-06-20","tmax":34.2,"tmin":23.5,"precip_mm":0.0,"prob_chuva":2,"weathercode":0,"tempo":"sol"},{"data":"2026-06-21","tmax":34.6,"tmin":24.8,"precip_mm":0.0,"prob_chuva":0,"weathercode":1,"tempo":"parcial"}],"fonte":"Open-Meteo","atualizado_em":"2026-06-15T13:53:52Z"}},{"id":"tabocao","nome":"TABOCÃO","ibge":1708254,"uf":"TO","lat":-9.05611,"lon":-48.5206,"area_soja_ha":null,"clima":{"ibge":1708254,"nome":"TABOCÃO","uf":"TO","lat":-9.05611,"lon":-48.5206,"atual":{"tmax":34.9,"tmin":23.2,"precip_mm":0.0,"prob_chuva":0,"weathercode":0,"tempo":"sol"},"previsao_7d":[{"data":"2026-06-15","tmax":34.9,"tmin":23.2,"precip_mm":0.0,"prob_chuva":0,"weathercode":0,"tempo":"sol"},{"data":"2026-06-16","tmax":35.6,"tmin":23.0,"precip_mm":0.0,"prob_chuva":0,"weathercode":1,"tempo":"parcial"},{"data":"2026-06-17","tmax":34.3,"tmin":21.8,"precip_mm":0.2,"prob_chuva":20,"weathercode":51,"tempo":"garoa"},{"data":"2026-06-18","tmax":34.0,"tmin":21.3,"precip_mm":0.3,"prob_chuva":63,"weathercode":51,"tempo":"garoa"},{"data":"2026-06-19","tmax":34.4,"tmin":20.9,"precip_mm":0.0,"prob_chuva":15,"weathercode":0,"tempo":"sol"},{"data":"2026-06-20","tmax":34.2,"tmin":20.4,"precip_mm":0.0,"prob_chuva":8,"weathercode":0,"tempo":"sol"},{"data":"2026-06-21","tmax":33.3,"tmin":22.7,"precip_mm":0.0,"prob_chuva":4,"weathercode":0,"tempo":"sol"}],"fonte":"Open-Meteo","atualizado_em":"2026-06-15T13:53:52Z"}},{"id":"tupirama","nome":"TUPIRAMA","ibge":1721257,"uf":"TO","lat":-8.97168,"lon":-48.1883,"area_soja_ha":null,"clima":{"ibge":1721257,"nome":"TUPIRAMA","uf":"TO","lat":-8.97168,"lon":-48.1883,"atual":{"tmax":35.7,"tmin":23.3,"precip_mm":0.0,"prob_chuva":0,"weathercode":0,"tempo":"sol"},"previsao_7d":[{"data":"2026-06-15","tmax":35.7,"tmin":23.3,"precip_mm":0.0,"prob_chuva":0,"weathercode":0,"tempo":"sol"},{"data":"2026-06-16","tmax":35.5,"tmin":23.0,"precip_mm":0.0,"prob_chuva":0,"weathercode":1,"tempo":"parcial"},{"data":"2026-06-17","tmax":34.5,"tmin":24.2,"precip_mm":0.0,"prob_chuva":16,"weathercode":3,"tempo":"nuvem"},{"data":"2026-06-18","tmax":33.5,"tmin":23.0,"precip_mm":0.5,"prob_chuva":41,"weathercode":51,"tempo":"garoa"},{"data":"2026-06-19","tmax":35.2,"tmin":22.9,"precip_mm":0.0,"prob_chuva":10,"weathercode":0,"tempo":"sol"},{"data":"2026-06-20","tmax":34.2,"tmin":23.3,"precip_mm":0.0,"prob_chuva":6,"weathercode":0,"tempo":"sol"},{"data":"2026-06-21","tmax":34.3,"tmin":24.3,"precip_mm":0.0,"prob_chuva":4,"weathercode":2,"tempo":"parcial"}],"fonte":"Open-Meteo","atualizado_em":"2026-06-15T13:53:52Z"}}],"alertas":{"ativos":[],"ufs":["TO"]},"colheita":{"status":"pendente","fonte":null,"itens":[]}}