{"distrito":{"id":"ijui_soja","nome":"IJUI-SOJA","regional":"RS SOJA","codigo_regional":"RSSO","uf":"RS","ufs":["RS"],"cultura_principal":"soja"},"gerado_em":"2026-06-26T12:01:40+00:00","municipios":[{"id":"ajuricaba","nome":"AJURICABA","ibge":4300208,"uf":"RS","lat":-28.2342,"lon":-53.7757,"area_soja_ha":21560,"clima":{"ibge":4300208,"nome":"AJURICABA","uf":"RS","lat":-28.2342,"lon":-53.7757,"atual":{"tmax":17.8,"tmin":3.2,"precip_mm":0.0,"prob_chuva":0,"weathercode":0,"tempo":"sol"},"previsao_7d":[{"data":"2026-06-26","tmax":17.8,"tmin":3.2,"precip_mm":0.0,"prob_chuva":0,"weathercode":0,"tempo":"sol"},{"data":"2026-06-27","tmax":22.3,"tmin":7.4,"precip_mm":6.2,"prob_chuva":92,"weathercode":95,"tempo":"trovoada"},{"data":"2026-06-28","tmax":18.1,"tmin":15.6,"precip_mm":32.2,"prob_chuva":100,"weathercode":96,"tempo":"trovoada"},{"data":"2026-06-29","tmax":17.3,"tmin":8.6,"precip_mm":0.0,"prob_chuva":14,"weathercode":3,"tempo":"nuvem"},{"data":"2026-06-30","tmax":18.8,"tmin":11.5,"precip_mm":26.0,"prob_chuva":85,"weathercode":96,"tempo":"trovoada"},{"data":"2026-07-01","tmax":18.6,"tmin":13.8,"precip_mm":18.7,"prob_chuva":82,"weathercode":96,"tempo":"trovoada"},{"data":"2026-07-02","tmax":14.2,"tmin":10.0,"precip_mm":3.0,"prob_chuva":36,"weathercode":51,"tempo":"garoa"}],"fonte":"Open-Meteo","atualizado_em":"2026-06-26T12:01:40Z"},"colheita":{"pct_plantado":100,"pct_colhido":100,"area_soja_ha":21560,"fonte":"Emater/RS-Ascar - Informativo Conjuntural (via SEAPI-RS / Canal Rural)","data_referencia":"2026-06-11","granularidade":"estadual aplicado ao municipio","derivado":true,"ha_plantado_estim":21560,"ha_colhido_estim":21560}},{"id":"bozano","nome":"BOZANO","ibge":4302584,"uf":"RS","lat":-28.3659,"lon":-53.772,"area_soja_ha":13880,"clima":{"ibge":4302584,"nome":"BOZANO","uf":"RS","lat":-28.3659,"lon":-53.772,"atual":{"tmax":17.4,"tmin":3.5,"precip_mm":0.0,"prob_chuva":0,"weathercode":1,"tempo":"parcial"},"previsao_7d":[{"data":"2026-06-26","tmax":17.4,"tmin":3.5,"precip_mm":0.0,"prob_chuva":0,"weathercode":1,"tempo":"parcial"},{"data":"2026-06-27","tmax":22.1,"tmin":7.6,"precip_mm":6.1,"prob_chuva":92,"weathercode":81,"tempo":"chuva"},{"data":"2026-06-28","tmax":18.0,"tmin":15.0,"precip_mm":36.9,"prob_chuva":100,"weathercode":96,"tempo":"trovoada"},{"data":"2026-06-29","tmax":17.1,"tmin":8.2,"precip_mm":0.0,"prob_chuva":14,"weathercode":3,"tempo":"nuvem"},{"data":"2026-06-30","tmax":18.6,"tmin":10.9,"precip_mm":13.1,"prob_chuva":85,"weathercode":95,"tempo":"trovoada"},{"data":"2026-07-01","tmax":18.4,"tmin":13.4,"precip_mm":24.1,"prob_chuva":82,"weathercode":96,"tempo":"trovoada"},{"data":"2026-07-02","tmax":13.6,"tmin":9.4,"precip_mm":0.0,"prob_chuva":36,"weathercode":3,"tempo":"nuvem"}],"fonte":"Open-Meteo","atualizado_em":"2026-06-26T12:01:40Z"},"colheita":{"pct_plantado":100,"pct_colhido":100,"area_soja_ha":13880,"fonte":"Emater/RS-Ascar - Informativo Conjuntural (via SEAPI-RS / Canal Rural)","data_referencia":"2026-06-11","granularidade":"estadual aplicado ao municipio","derivado":true,"ha_plantado_estim":13880,"ha_colhido_estim":13880}},{"id":"catuipe","nome":"CATUÍPE","ibge":4305009,"uf":"RS","lat":-28.2554,"lon":-54.0132,"area_soja_ha":36000,"clima":{"ibge":4305009,"nome":"CATUÍPE","uf":"RS","lat":-28.2554,"lon":-54.0132,"atual":{"tmax":17.8,"tmin":3.8,"precip_mm":0.0,"prob_chuva":0,"weathercode":1,"tempo":"parcial"},"previsao_7d":[{"data":"2026-06-26","tmax":17.8,"tmin":3.8,"precip_mm":0.0,"prob_chuva":0,"weathercode":1,"tempo":"parcial"},{"data":"2026-06-27","tmax":22.0,"tmin":7.3,"precip_mm":4.6,"prob_chuva":91,"weathercode":80,"tempo":"chuva"},{"data":"2026-06-28","tmax":18.3,"tmin":15.0,"precip_mm":40.8,"prob_chuva":100,"weathercode":96,"tempo":"trovoada"},{"data":"2026-06-29","tmax":17.7,"tmin":8.3,"precip_mm":0.0,"prob_chuva":12,"weathercode":3,"tempo":"nuvem"},{"data":"2026-06-30","tmax":18.7,"tmin":10.7,"precip_mm":16.9,"prob_chuva":83,"weathercode":95,"tempo":"trovoada"},{"data":"2026-07-01","tmax":18.2,"tmin":14.1,"precip_mm":22.4,"prob_chuva":81,"weathercode":95,"tempo":"trovoada"},{"data":"2026-07-02","tmax":14.1,"tmin":10.2,"precip_mm":0.0,"prob_chuva":36,"weathercode":3,"tempo":"nuvem"}],"fonte":"Open-Meteo","atualizado_em":"2026-06-26T12:01:40Z"},"colheita":{"pct_plantado":100,"pct_colhido":100,"area_soja_ha":36000,"fonte":"Emater/RS-Ascar - Informativo Conjuntural (via SEAPI-RS / Canal Rural)","data_referencia":"2026-06-11","granularidade":"estadual aplicado ao municipio","derivado":true,"ha_plantado_estim":36000,"ha_colhido_estim":36000}},{"id":"chiapetta","nome":"CHIAPETTA","ibge":4305405,"uf":"RS","lat":-27.923,"lon":-53.9419,"area_soja_ha":29500,"clima":{"ibge":4305405,"nome":"CHIAPETTA","uf":"RS","lat":-27.923,"lon":-53.9419,"atual":{"tmax":17.4,"tmin":4.8,"precip_mm":0.0,"prob_chuva":0,"weathercode":1,"tempo":"parcial"},"previsao_7d":[{"data":"2026-06-26","tmax":17.4,"tmin":4.8,"precip_mm":0.0,"prob_chuva":0,"weathercode":1,"tempo":"parcial"},{"data":"2026-06-27","tmax":21.3,"tmin":9.7,"precip_mm":4.5,"prob_chuva":89,"weathercode":80,"tempo":"chuva"},{"data":"2026-06-28","tmax":17.9,"tmin":15.3,"precip_mm":30.5,"prob_chuva":100,"weathercode":96,"tempo":"trovoada"},{"data":"2026-06-29","tmax":17.4,"tmin":9.1,"precip_mm":0.1,"prob_chuva":18,"weathercode":51,"tempo":"garoa"},{"data":"2026-06-30","tmax":19.1,"tmin":11.9,"precip_mm":32.9,"prob_chuva":86,"weathercode":96,"tempo":"trovoada"},{"data":"2026-07-01","tmax":18.1,"tmin":14.4,"precip_mm":23.2,"prob_chuva":86,"weathercode":95,"tempo":"trovoada"},{"data":"2026-07-02","tmax":14.3,"tmin":9.9,"precip_mm":4.8,"prob_chuva":36,"weathercode":53,"tempo":"garoa"}],"fonte":"Open-Meteo","atualizado_em":"2026-06-26T12:01:40Z"},"colheita":{"pct_plantado":100,"pct_colhido":100,"area_soja_ha":29500,"fonte":"Emater/RS-Ascar - Informativo Conjuntural (via SEAPI-RS / Canal Rural)","data_referencia":"2026-06-11","granularidade":"estadual aplicado ao municipio","derivado":true,"ha_plantado_estim":29500,"ha_colhido_estim":29500}},{"id":"condor","nome":"CONDOR","ibge":4305702,"uf":"RS","lat":-28.2075,"lon":-53.4905,"area_soja_ha":30400,"clima":{"ibge":4305702,"nome":"CONDOR","uf":"RS","lat":-28.2075,"lon":-53.4905,"atual":{"tmax":17.2,"tmin":4.0,"precip_mm":0.0,"prob_chuva":0,"weathercode":1,"tempo":"parcial"},"previsao_7d":[{"data":"2026-06-26","tmax":17.2,"tmin":4.0,"precip_mm":0.0,"prob_chuva":0,"weathercode":1,"tempo":"parcial"},{"data":"2026-06-27","tmax":21.8,"tmin":7.2,"precip_mm":2.8,"prob_chuva":90,"weathercode":55,"tempo":"garoa"},{"data":"2026-06-28","tmax":17.9,"tmin":15.1,"precip_mm":26.7,"prob_chuva":100,"weathercode":96,"tempo":"trovoada"},{"data":"2026-06-29","tmax":15.8,"tmin":8.8,"precip_mm":0.1,"prob_chuva":24,"weathercode":51,"tempo":"garoa"},{"data":"2026-06-30","tmax":18.1,"tmin":11.4,"precip_mm":28.6,"prob_chuva":84,"weathercode":95,"tempo":"trovoada"},{"data":"2026-07-01","tmax":17.9,"tmin":13.6,"precip_mm":19.4,"prob_chuva":82,"weathercode":95,"tempo":"trovoada"},{"data":"2026-07-02","tmax":13.5,"tmin":9.1,"precip_mm":4.8,"prob_chuva":35,"weathercode":51,"tempo":"garoa"}],"fonte":"Open-Meteo","atualizado_em":"2026-06-26T12:01:40Z"},"colheita":{"pct_plantado":100,"pct_colhido":100,"area_soja_ha":30400,"fonte":"Emater/RS-Ascar - Informativo Conjuntural (via SEAPI-RS / Canal Rural)","data_referencia":"2026-06-11","granularidade":"estadual aplicado ao municipio","derivado":true,"ha_plantado_estim":30400,"ha_colhido_estim":30400}},{"id":"coronel_barros","nome":"CORONEL BARROS","ibge":4305871,"uf":"RS","lat":-28.3921,"lon":-54.0686,"area_soja_ha":11890,"clima":{"ibge":4305871,"nome":"CORONEL BARROS","uf":"RS","lat":-28.3921,"lon":-54.0686,"atual":{"tmax":18.1,"tmin":2.7,"precip_mm":0.0,"prob_chuva":0,"weathercode":1,"tempo":"parcial"},"previsao_7d":[{"data":"2026-06-26","tmax":18.1,"tmin":2.7,"precip_mm":0.0,"prob_chuva":0,"weathercode":1,"tempo":"parcial"},{"data":"2026-06-27","tmax":22.7,"tmin":6.9,"precip_mm":5.6,"prob_chuva":93,"weathercode":95,"tempo":"trovoada"},{"data":"2026-06-28","tmax":18.4,"tmin":15.1,"precip_mm":52.9,"prob_chuva":100,"weathercode":96,"tempo":"trovoada"},{"data":"2026-06-29","tmax":17.8,"tmin":8.1,"precip_mm":0.0,"prob_chuva":8,"weathercode":3,"tempo":"nuvem"},{"data":"2026-06-30","tmax":19.1,"tmin":10.4,"precip_mm":7.8,"prob_chuva":78,"weathercode":80,"tempo":"chuva"},{"data":"2026-07-01","tmax":18.1,"tmin":13.4,"precip_mm":12.6,"prob_chuva":80,"weathercode":95,"tempo":"trovoada"},{"data":"2026-07-02","tmax":14.2,"tmin":10.3,"precip_mm":0.0,"prob_chuva":33,"weathercode":3,"tempo":"nuvem"}],"fonte":"Open-Meteo","atualizado_em":"2026-06-26T12:01:40Z"},"colheita":{"pct_plantado":100,"pct_colhido":100,"area_soja_ha":11890,"fonte":"Emater/RS-Ascar - Informativo Conjuntural (via SEAPI-RS / Canal Rural)","data_referencia":"2026-06-11","granularidade":"estadual aplicado ao municipio","derivado":true,"ha_plantado_estim":11890,"ha_colhido_estim":11890}},{"id":"ijui","nome":"IJUÍ","ibge":4310207,"uf":"RS","lat":-28.388,"lon":-53.92,"area_soja_ha":40700,"clima":{"ibge":4310207,"nome":"IJUÍ","uf":"RS","lat":-28.388,"lon":-53.92,"atual":{"tmax":18.0,"tmin":3.4,"precip_mm":0.0,"prob_chuva":0,"weathercode":1,"tempo":"parcial"},"previsao_7d":[{"data":"2026-06-26","tmax":18.0,"tmin":3.4,"precip_mm":0.0,"prob_chuva":0,"weathercode":1,"tempo":"parcial"},{"data":"2026-06-27","tmax":22.8,"tmin":7.7,"precip_mm":5.9,"prob_chuva":93,"weathercode":80,"tempo":"chuva"},{"data":"2026-06-28","tmax":18.3,"tmin":15.3,"precip_mm":39.7,"prob_chuva":100,"weathercode":96,"tempo":"trovoada"},{"data":"2026-06-29","tmax":17.7,"tmin":8.2,"precip_mm":0.0,"prob_chuva":8,"weathercode":3,"tempo":"nuvem"},{"data":"2026-06-30","tmax":18.9,"tmin":10.6,"precip_mm":12.1,"prob_chuva":78,"weathercode":81,"tempo":"chuva"},{"data":"2026-07-01","tmax":18.2,"tmin":13.3,"precip_mm":18.5,"prob_chuva":80,"weathercode":96,"tempo":"trovoada"},{"data":"2026-07-02","tmax":14.1,"tmin":10.0,"precip_mm":0.0,"prob_chuva":33,"weathercode":3,"tempo":"nuvem"}],"fonte":"Open-Meteo","atualizado_em":"2026-06-26T12:01:40Z"},"colheita":{"pct_plantado":100,"pct_colhido":100,"area_soja_ha":40700,"fonte":"Emater/RS-Ascar - Informativo Conjuntural (via SEAPI-RS / Canal Rural)","data_referencia":"2026-06-11","granularidade":"estadual aplicado ao municipio","derivado":true,"ha_plantado_estim":40700,"ha_colhido_estim":40700}},{"id":"nova_ramada","nome":"NOVA RAMADA","ibge":4313334,"uf":"RS","lat":-28.0667,"lon":-53.6992,"area_soja_ha":16330,"clima":{"ibge":4313334,"nome":"NOVA RAMADA","uf":"RS","lat":-28.0667,"lon":-53.6992,"atual":{"tmax":16.8,"tmin":5.3,"precip_mm":0.0,"prob_chuva":0,"weathercode":0,"tempo":"sol"},"previsao_7d":[{"data":"2026-06-26","tmax":16.8,"tmin":5.3,"precip_mm":0.0,"prob_chuva":0,"weathercode":0,"tempo":"sol"},{"data":"2026-06-27","tmax":21.2,"tmin":9.1,"precip_mm":2.5,"prob_chuva":83,"weathercode":80,"tempo":"chuva"},{"data":"2026-06-28","tmax":17.9,"tmin":14.9,"precip_mm":32.0,"prob_chuva":100,"weathercode":96,"tempo":"trovoada"},{"data":"2026-06-29","tmax":16.2,"tmin":8.7,"precip_mm":0.2,"prob_chuva":20,"weathercode":51,"tempo":"garoa"},{"data":"2026-06-30","tmax":18.9,"tmin":11.5,"precip_mm":28.6,"prob_chuva":87,"weathercode":96,"tempo":"trovoada"},{"data":"2026-07-01","tmax":18.1,"tmin":13.9,"precip_mm":20.0,"prob_chuva":83,"weathercode":96,"tempo":"trovoada"},{"data":"2026-07-02","tmax":13.6,"tmin":8.9,"precip_mm":8.4,"prob_chuva":37,"weathercode":53,"tempo":"garoa"}],"fonte":"Open-Meteo","atualizado_em":"2026-06-26T12:01:40Z"},"colheita":{"pct_plantado":100,"pct_colhido":100,"area_soja_ha":16330,"fonte":"Emater/RS-Ascar - Informativo Conjuntural (via SEAPI-RS / Canal Rural)","data_referencia":"2026-06-11","granularidade":"estadual aplicado ao municipio","derivado":true,"ha_plantado_estim":16330,"ha_colhido_estim":16330}},{"id":"panambi","nome":"PANAMBI","ibge":4313904,"uf":"RS","lat":-28.2833,"lon":-53.5023,"area_soja_ha":26000,"clima":{"ibge":4313904,"nome":"PANAMBI","uf":"RS","lat":-28.2833,"lon":-53.5023,"atual":{"tmax":17.0,"tmin":4.0,"precip_mm":0.0,"prob_chuva":0,"weathercode":1,"tempo":"parcial"},"previsao_7d":[{"data":"2026-06-26","tmax":17.0,"tmin":4.0,"precip_mm":0.0,"prob_chuva":0,"weathercode":1,"tempo":"parcial"},{"data":"2026-06-27","tmax":21.7,"tmin":7.2,"precip_mm":3.7,"prob_chuva":90,"weathercode":95,"tempo":"trovoada"},{"data":"2026-06-28","tmax":17.8,"tmin":15.0,"precip_mm":30.2,"prob_chuva":100,"weathercode":96,"tempo":"trovoada"},{"data":"2026-06-29","tmax":15.6,"tmin":8.5,"precip_mm":0.0,"prob_chuva":24,"weathercode":3,"tempo":"nuvem"},{"data":"2026-06-30","tmax":17.6,"tmin":10.7,"precip_mm":25.2,"prob_chuva":84,"weathercode":95,"tempo":"trovoada"},{"data":"2026-07-01","tmax":17.8,"tmin":13.3,"precip_mm":18.3,"prob_chuva":82,"weathercode":95,"tempo":"trovoada"},{"data":"2026-07-02","tmax":13.2,"tmin":8.7,"precip_mm":3.0,"prob_chuva":35,"weathercode":51,"tempo":"garoa"}],"fonte":"Open-Meteo","atualizado_em":"2026-06-26T12:01:40Z"},"colheita":{"pct_plantado":100,"pct_colhido":100,"area_soja_ha":26000,"fonte":"Emater/RS-Ascar - Informativo Conjuntural (via SEAPI-RS / Canal Rural)","data_referencia":"2026-06-11","granularidade":"estadual aplicado ao municipio","derivado":true,"ha_plantado_estim":26000,"ha_colhido_estim":26000}},{"id":"santa_barbara_do_sul","nome":"SANTA BÁRBARA DO SUL","ibge":4316709,"uf":"RS","lat":-28.3653,"lon":-53.251,"area_soja_ha":75000,"clima":{"ibge":4316709,"nome":"SANTA BÁRBARA DO SUL","uf":"RS","lat":-28.3653,"lon":-53.251,"atual":{"tmax":16.3,"tmin":4.0,"precip_mm":0.0,"prob_chuva":0,"weathercode":0,"tempo":"sol"},"previsao_7d":[{"data":"2026-06-26","tmax":16.3,"tmin":4.0,"precip_mm":0.0,"prob_chuva":0,"weathercode":0,"tempo":"sol"},{"data":"2026-06-27","tmax":21.2,"tmin":6.0,"precip_mm":1.1,"prob_chuva":90,"weathercode":53,"tempo":"garoa"},{"data":"2026-06-28","tmax":17.8,"tmin":14.8,"precip_mm":23.0,"prob_chuva":100,"weathercode":96,"tempo":"trovoada"},{"data":"2026-06-29","tmax":15.2,"tmin":8.9,"precip_mm":0.0,"prob_chuva":24,"weathercode":3,"tempo":"nuvem"},{"data":"2026-06-30","tmax":16.8,"tmin":10.7,"precip_mm":24.0,"prob_chuva":84,"weathercode":95,"tempo":"trovoada"},{"data":"2026-07-01","tmax":17.8,"tmin":12.8,"precip_mm":15.3,"prob_chuva":82,"weathercode":95,"tempo":"trovoada"},{"data":"2026-07-02","tmax":12.9,"tmin":8.2,"precip_mm":6.2,"prob_chuva":40,"weathercode":53,"tempo":"garoa"}],"fonte":"Open-Meteo","atualizado_em":"2026-06-26T12:01:40Z"},"colheita":{"pct_plantado":100,"pct_colhido":100,"area_soja_ha":75000,"fonte":"Emater/RS-Ascar - Informativo Conjuntural (via SEAPI-RS / Canal Rural)","data_referencia":"2026-06-11","granularidade":"estadual aplicado ao municipio","derivado":true,"ha_plantado_estim":75000,"ha_colhido_estim":75000}}],"alertas":{"ativos":[],"ufs":["RS"]},"colheita":{"status":"validado","fonte":"Emater/RS-Ascar - Informativo Conjuntural (via SEAPI-RS / Canal Rural)","granularidade":"estadual","data_referencia":"2026-06-11","cultura":"soja","itens":[{"regiao":"Rio Grande do Sul","uf":"RS","granularidade":"estadual","pct_plantado":100,"pct_colhido":100,"vs_media5anos":null,"vs_safra_anterior":null,"condicao_lavoura":"Safra encerrada; forte variabilidade regional (1.200-4.200 kg/ha); produtividade -14,8% vs projeção inicial","fonte":"Emater/RS-Ascar - Informativo Conjuntural (via SEAPI-RS / Canal Rural)","data_referencia":"2026-06-11","safra":"2025/2026","produtividade_kg_ha":2707,"area_ha":6690000,"producao_t":18132401,"var_producao_pct":32.9,"preco_rs_sc":128.74,"preco_data":"2026-06-12","preco_fonte":"Grao Direto (Centro Ocidental RS)"}]},"preco":{"valor":128.74,"uf":"RS","data":"2026-06-12","fonte":"Grao Direto (Centro Ocidental RS)","unidade":"R$/sc 60kg"}}