{"distrito":{"id":"santa_rosa_soja","nome":"SANTA ROSA-SOJA","regional":"RS SOJA","codigo_regional":"RSSO","uf":"RS","ufs":["RS"],"cultura_principal":"soja"},"gerado_em":"2026-07-15T05:07:39+00:00","municipios":[{"id":"alecrim","nome":"ALECRIM","ibge":4300307,"uf":"RS","lat":-27.6579,"lon":-54.7649,"area_soja_ha":2405,"clima":{"ibge":4300307,"nome":"ALECRIM","uf":"RS","lat":-27.6579,"lon":-54.7649,"atual":{"tmax":23.3,"tmin":8.8,"precip_mm":0.0,"prob_chuva":0,"weathercode":0,"tempo":"sol"},"previsao_7d":[{"data":"2026-07-15","tmax":23.3,"tmin":8.8,"precip_mm":0.0,"prob_chuva":0,"weathercode":0,"tempo":"sol","vento_kmh":14.9,"rajada_kmh":31.3,"vento_dir_graus":61,"et0_mm":2.87},{"data":"2026-07-16","tmax":27.4,"tmin":12.6,"precip_mm":0.0,"prob_chuva":0,"weathercode":0,"tempo":"sol","vento_kmh":20.8,"rajada_kmh":42.5,"vento_dir_graus":52,"et0_mm":3.86},{"data":"2026-07-17","tmax":28.2,"tmin":21.2,"precip_mm":0.0,"prob_chuva":2,"weathercode":1,"tempo":"parcial","vento_kmh":29.8,"rajada_kmh":59.0,"vento_dir_graus":23,"et0_mm":4.76},{"data":"2026-07-18","tmax":28.1,"tmin":19.8,"precip_mm":7.2,"prob_chuva":67,"weathercode":96,"tempo":"trovoada","vento_kmh":22.4,"rajada_kmh":51.5,"vento_dir_graus":3,"et0_mm":4.05},{"data":"2026-07-19","tmax":28.2,"tmin":18.0,"precip_mm":48.5,"prob_chuva":78,"weathercode":96,"tempo":"trovoada","vento_kmh":20.9,"rajada_kmh":47.9,"vento_dir_graus":28,"et0_mm":3.19},{"data":"2026-07-20","tmax":24.9,"tmin":18.6,"precip_mm":12.2,"prob_chuva":68,"weathercode":95,"tempo":"trovoada","vento_kmh":28.6,"rajada_kmh":58.3,"vento_dir_graus":10,"et0_mm":3.64},{"data":"2026-07-21","tmax":21.8,"tmin":17.3,"precip_mm":21.4,"prob_chuva":72,"weathercode":80,"tempo":"chuva","vento_kmh":12.8,"rajada_kmh":35.6,"vento_dir_graus":148,"et0_mm":1.27}],"fonte":"Open-Meteo","atualizado_em":"2026-07-15T05:07:38Z"},"colheita":{"pct_plantado":100.0,"pct_colhido":100.0,"area_soja_ha":2405,"fonte":"Emater/RS-Ascar (regional Santa Rosa, Fenasoja 30/04)","data_referencia":"2026-05-14","granularidade":"regional (Santa Rosa) aplicado ao municipio","regiao":"Santa Rosa","derivado":true,"ha_plantado_estim":2405,"ha_colhido_estim":2405}},{"id":"alegria","nome":"ALEGRIA","ibge":4300455,"uf":"RS","lat":-27.8345,"lon":-54.0557,"area_soja_ha":7660,"clima":{"ibge":4300455,"nome":"ALEGRIA","uf":"RS","lat":-27.8345,"lon":-54.0557,"atual":{"tmax":22.0,"tmin":10.7,"precip_mm":0.0,"prob_chuva":0,"weathercode":0,"tempo":"sol"},"previsao_7d":[{"data":"2026-07-15","tmax":22.0,"tmin":10.7,"precip_mm":0.0,"prob_chuva":0,"weathercode":0,"tempo":"sol","vento_kmh":17.6,"rajada_kmh":32.4,"vento_dir_graus":47,"et0_mm":3.15},{"data":"2026-07-16","tmax":26.2,"tmin":14.7,"precip_mm":0.0,"prob_chuva":0,"weathercode":0,"tempo":"sol","vento_kmh":23.2,"rajada_kmh":43.6,"vento_dir_graus":42,"et0_mm":4.17},{"data":"2026-07-17","tmax":27.8,"tmin":21.3,"precip_mm":0.0,"prob_chuva":2,"weathercode":1,"tempo":"parcial","vento_kmh":30.3,"rajada_kmh":59.0,"vento_dir_graus":19,"et0_mm":5.01},{"data":"2026-07-18","tmax":28.3,"tmin":19.6,"precip_mm":9.3,"prob_chuva":46,"weathercode":96,"tempo":"trovoada","vento_kmh":30.9,"rajada_kmh":56.5,"vento_dir_graus":1,"et0_mm":4.64},{"data":"2026-07-19","tmax":27.0,"tmin":18.8,"precip_mm":33.6,"prob_chuva":71,"weathercode":96,"tempo":"trovoada","vento_kmh":27.9,"rajada_kmh":51.5,"vento_dir_graus":30,"et0_mm":3.13},{"data":"2026-07-20","tmax":26.2,"tmin":19.2,"precip_mm":18.4,"prob_chuva":63,"weathercode":95,"tempo":"trovoada","vento_kmh":32.3,"rajada_kmh":73.1,"vento_dir_graus":7,"et0_mm":4.27},{"data":"2026-07-21","tmax":20.8,"tmin":19.1,"precip_mm":31.0,"prob_chuva":67,"weathercode":96,"tempo":"trovoada","vento_kmh":14.0,"rajada_kmh":41.8,"vento_dir_graus":113,"et0_mm":1.03}],"fonte":"Open-Meteo","atualizado_em":"2026-07-15T05:07:38Z"},"colheita":{"pct_plantado":100.0,"pct_colhido":100.0,"area_soja_ha":7660,"fonte":"Emater/RS-Ascar (regional Santa Rosa, Fenasoja 30/04)","data_referencia":"2026-05-14","granularidade":"regional (Santa Rosa) aplicado ao municipio","regiao":"Santa Rosa","derivado":true,"ha_plantado_estim":7660,"ha_colhido_estim":7660}},{"id":"boa_vista_do_burica","nome":"BOA VISTA DO BURICÁ","ibge":4302204,"uf":"RS","lat":-27.6693,"lon":-54.1082,"area_soja_ha":2350,"clima":{"ibge":4302204,"nome":"BOA VISTA DO BURICÁ","uf":"RS","lat":-27.6693,"lon":-54.1082,"atual":{"tmax":22.6,"tmin":9.9,"precip_mm":0.0,"prob_chuva":0,"weathercode":0,"tempo":"sol"},"previsao_7d":[{"data":"2026-07-15","tmax":22.6,"tmin":9.9,"precip_mm":0.0,"prob_chuva":0,"weathercode":0,"tempo":"sol","vento_kmh":14.4,"rajada_kmh":29.2,"vento_dir_graus":50,"et0_mm":2.95},{"data":"2026-07-16","tmax":26.9,"tmin":14.0,"precip_mm":0.0,"prob_chuva":0,"weathercode":0,"tempo":"sol","vento_kmh":21.9,"rajada_kmh":41.4,"vento_dir_graus":44,"et0_mm":4.07},{"data":"2026-07-17","tmax":28.8,"tmin":21.9,"precip_mm":0.0,"prob_chuva":2,"weathercode":1,"tempo":"parcial","vento_kmh":29.5,"rajada_kmh":57.6,"vento_dir_graus":20,"et0_mm":5.18},{"data":"2026-07-18","tmax":28.9,"tmin":19.9,"precip_mm":8.0,"prob_chuva":46,"weathercode":95,"tempo":"trovoada","vento_kmh":27.4,"rajada_kmh":67.3,"vento_dir_graus":6,"et0_mm":4.55},{"data":"2026-07-19","tmax":28.0,"tmin":19.1,"precip_mm":18.4,"prob_chuva":71,"weathercode":95,"tempo":"trovoada","vento_kmh":27.4,"rajada_kmh":51.5,"vento_dir_graus":33,"et0_mm":3.3},{"data":"2026-07-20","tmax":26.6,"tmin":19.5,"precip_mm":18.2,"prob_chuva":63,"weathercode":95,"tempo":"trovoada","vento_kmh":30.5,"rajada_kmh":64.1,"vento_dir_graus":10,"et0_mm":4.23},{"data":"2026-07-21","tmax":21.4,"tmin":19.5,"precip_mm":35.2,"prob_chuva":67,"weathercode":95,"tempo":"trovoada","vento_kmh":10.3,"rajada_kmh":33.5,"vento_dir_graus":109,"et0_mm":1.04}],"fonte":"Open-Meteo","atualizado_em":"2026-07-15T05:07:38Z"},"colheita":{"pct_plantado":100.0,"pct_colhido":100.0,"area_soja_ha":2350,"fonte":"Emater/RS-Ascar (regional Santa Rosa, Fenasoja 30/04)","data_referencia":"2026-05-14","granularidade":"regional (Santa Rosa) aplicado ao municipio","regiao":"Santa Rosa","derivado":true,"ha_plantado_estim":2350,"ha_colhido_estim":2350}},{"id":"bom_progresso","nome":"BOM PROGRESSO","ibge":4302378,"uf":"RS","lat":-27.5399,"lon":-53.8716,"area_soja_ha":4400,"clima":{"ibge":4302378,"nome":"BOM PROGRESSO","uf":"RS","lat":-27.5399,"lon":-53.8716,"atual":{"tmax":21.6,"tmin":9.6,"precip_mm":0.0,"prob_chuva":0,"weathercode":0,"tempo":"sol"},"previsao_7d":[{"data":"2026-07-15","tmax":21.6,"tmin":9.6,"precip_mm":0.0,"prob_chuva":0,"weathercode":0,"tempo":"sol","vento_kmh":17.3,"rajada_kmh":33.5,"vento_dir_graus":56,"et0_mm":3.01},{"data":"2026-07-16","tmax":25.8,"tmin":13.3,"precip_mm":0.0,"prob_chuva":0,"weathercode":0,"tempo":"sol","vento_kmh":21.9,"rajada_kmh":40.3,"vento_dir_graus":51,"et0_mm":3.93},{"data":"2026-07-17","tmax":27.0,"tmin":20.4,"precip_mm":0.0,"prob_chuva":2,"weathercode":0,"tempo":"sol","vento_kmh":29.7,"rajada_kmh":56.2,"vento_dir_graus":26,"et0_mm":4.72},{"data":"2026-07-18","tmax":27.9,"tmin":20.1,"precip_mm":5.2,"prob_chuva":37,"weathercode":96,"tempo":"trovoada","vento_kmh":25.7,"rajada_kmh":55.1,"vento_dir_graus":17,"et0_mm":4.64},{"data":"2026-07-19","tmax":26.9,"tmin":18.1,"precip_mm":25.4,"prob_chuva":60,"weathercode":96,"tempo":"trovoada","vento_kmh":27.1,"rajada_kmh":51.8,"vento_dir_graus":35,"et0_mm":3.21},{"data":"2026-07-20","tmax":25.8,"tmin":19.1,"precip_mm":26.1,"prob_chuva":57,"weathercode":95,"tempo":"trovoada","vento_kmh":27.0,"rajada_kmh":68.0,"vento_dir_graus":12,"et0_mm":3.95},{"data":"2026-07-21","tmax":20.5,"tmin":18.8,"precip_mm":80.8,"prob_chuva":71,"weathercode":96,"tempo":"trovoada","vento_kmh":12.1,"rajada_kmh":39.2,"vento_dir_graus":64,"et0_mm":1.07}],"fonte":"Open-Meteo","atualizado_em":"2026-07-15T05:07:38Z"},"colheita":{"pct_plantado":100.0,"pct_colhido":100.0,"area_soja_ha":4400,"fonte":"Emater/RS-Ascar - Informativo Conjuntural (fechamento)","data_referencia":"2026-05-14","granularidade":"regional (Frederico Westphalen) aplicado ao municipio","regiao":"Frederico Westphalen","derivado":true,"ha_plantado_estim":4400,"ha_colhido_estim":4400}},{"id":"braga","nome":"BRAGA","ibge":4302600,"uf":"RS","lat":-27.6173,"lon":-53.7405,"area_soja_ha":8000,"clima":{"ibge":4302600,"nome":"BRAGA","uf":"RS","lat":-27.6173,"lon":-53.7405,"atual":{"tmax":20.9,"tmin":9.2,"precip_mm":0.0,"prob_chuva":0,"weathercode":0,"tempo":"sol"},"previsao_7d":[{"data":"2026-07-15","tmax":20.9,"tmin":9.2,"precip_mm":0.0,"prob_chuva":0,"weathercode":0,"tempo":"sol","vento_kmh":17.5,"rajada_kmh":33.5,"vento_dir_graus":51,"et0_mm":2.87},{"data":"2026-07-16","tmax":25.2,"tmin":12.6,"precip_mm":0.0,"prob_chuva":0,"weathercode":0,"tempo":"sol","vento_kmh":21.8,"rajada_kmh":40.0,"vento_dir_graus":48,"et0_mm":3.73},{"data":"2026-07-17","tmax":26.2,"tmin":19.5,"precip_mm":0.0,"prob_chuva":2,"weathercode":1,"tempo":"parcial","vento_kmh":32.9,"rajada_kmh":59.4,"vento_dir_graus":26,"et0_mm":4.51},{"data":"2026-07-18","tmax":27.0,"tmin":19.2,"precip_mm":4.4,"prob_chuva":37,"weathercode":95,"tempo":"trovoada","vento_kmh":29.8,"rajada_kmh":55.4,"vento_dir_graus":17,"et0_mm":4.55},{"data":"2026-07-19","tmax":25.9,"tmin":17.7,"precip_mm":27.7,"prob_chuva":60,"weathercode":96,"tempo":"trovoada","vento_kmh":23.8,"rajada_kmh":50.0,"vento_dir_graus":34,"et0_mm":3.07},{"data":"2026-07-20","tmax":25.3,"tmin":18.5,"precip_mm":26.8,"prob_chuva":57,"weathercode":95,"tempo":"trovoada","vento_kmh":25.9,"rajada_kmh":71.3,"vento_dir_graus":13,"et0_mm":3.74},{"data":"2026-07-21","tmax":20.3,"tmin":18.3,"precip_mm":105.2,"prob_chuva":71,"weathercode":96,"tempo":"trovoada","vento_kmh":12.1,"rajada_kmh":41.8,"vento_dir_graus":61,"et0_mm":1.02}],"fonte":"Open-Meteo","atualizado_em":"2026-07-15T05:07:38Z"},"colheita":{"pct_plantado":100.0,"pct_colhido":100.0,"area_soja_ha":8000,"fonte":"Emater/RS-Ascar - Informativo Conjuntural (fechamento)","data_referencia":"2026-05-14","granularidade":"regional (Frederico Westphalen) aplicado ao municipio","regiao":"Frederico Westphalen","derivado":true,"ha_plantado_estim":8000,"ha_colhido_estim":8000}},{"id":"campina_das_missoes","nome":"CAMPINA DAS MISSÕES","ibge":4303707,"uf":"RS","lat":-27.9888,"lon":-54.8416,"area_soja_ha":6000,"clima":{"ibge":4303707,"nome":"CAMPINA DAS MISSÕES","uf":"RS","lat":-27.9888,"lon":-54.8416,"atual":{"tmax":22.7,"tmin":11.2,"precip_mm":0.0,"prob_chuva":0,"weathercode":0,"tempo":"sol"},"previsao_7d":[{"data":"2026-07-15","tmax":22.7,"tmin":11.2,"precip_mm":0.0,"prob_chuva":0,"weathercode":0,"tempo":"sol","vento_kmh":21.0,"rajada_kmh":38.5,"vento_dir_graus":38,"et0_mm":3.2},{"data":"2026-07-16","tmax":27.2,"tmin":15.4,"precip_mm":0.0,"prob_chuva":4,"weathercode":0,"tempo":"sol","vento_kmh":23.8,"rajada_kmh":45.0,"vento_dir_graus":34,"et0_mm":4.39},{"data":"2026-07-17","tmax":28.6,"tmin":22.3,"precip_mm":0.0,"prob_chuva":2,"weathercode":0,"tempo":"sol","vento_kmh":34.3,"rajada_kmh":69.5,"vento_dir_graus":13,"et0_mm":5.24},{"data":"2026-07-18","tmax":28.4,"tmin":19.6,"precip_mm":43.0,"prob_chuva":76,"weathercode":96,"tempo":"trovoada","vento_kmh":29.0,"rajada_kmh":58.3,"vento_dir_graus":360,"et0_mm":4.18},{"data":"2026-07-19","tmax":28.3,"tmin":19.2,"precip_mm":66.2,"prob_chuva":84,"weathercode":96,"tempo":"trovoada","vento_kmh":24.2,"rajada_kmh":53.6,"vento_dir_graus":25,"et0_mm":2.74},{"data":"2026-07-20","tmax":25.2,"tmin":19.3,"precip_mm":38.3,"prob_chuva":76,"weathercode":96,"tempo":"trovoada","vento_kmh":35.7,"rajada_kmh":74.2,"vento_dir_graus":4,"et0_mm":3.52},{"data":"2026-07-21","tmax":21.4,"tmin":17.2,"precip_mm":25.0,"prob_chuva":81,"weathercode":96,"tempo":"trovoada","vento_kmh":16.6,"rajada_kmh":39.2,"vento_dir_graus":143,"et0_mm":1.3}],"fonte":"Open-Meteo","atualizado_em":"2026-07-15T05:07:38Z"},"colheita":{"pct_plantado":100.0,"pct_colhido":100.0,"area_soja_ha":6000,"fonte":"Emater/RS-Ascar (regional Santa Rosa, Fenasoja 30/04)","data_referencia":"2026-05-14","granularidade":"regional (Santa Rosa) aplicado ao municipio","regiao":"Santa Rosa","derivado":true,"ha_plantado_estim":6000,"ha_colhido_estim":6000}},{"id":"campo_novo","nome":"CAMPO NOVO","ibge":4304002,"uf":"RS","lat":-27.6792,"lon":-53.8052,"area_soja_ha":10900,"clima":{"ibge":4304002,"nome":"CAMPO NOVO","uf":"RS","lat":-27.6792,"lon":-53.8052,"atual":{"tmax":20.6,"tmin":9.4,"precip_mm":0.0,"prob_chuva":0,"weathercode":0,"tempo":"sol"},"previsao_7d":[{"data":"2026-07-15","tmax":20.6,"tmin":9.4,"precip_mm":0.0,"prob_chuva":0,"weathercode":0,"tempo":"sol","vento_kmh":22.2,"rajada_kmh":37.1,"vento_dir_graus":48,"et0_mm":3.0},{"data":"2026-07-16","tmax":24.8,"tmin":13.2,"precip_mm":0.0,"prob_chuva":0,"weathercode":0,"tempo":"sol","vento_kmh":25.7,"rajada_kmh":44.3,"vento_dir_graus":45,"et0_mm":3.97},{"data":"2026-07-17","tmax":25.9,"tmin":19.7,"precip_mm":0.0,"prob_chuva":2,"weathercode":0,"tempo":"sol","vento_kmh":35.1,"rajada_kmh":62.6,"vento_dir_graus":25,"et0_mm":4.64},{"data":"2026-07-18","tmax":26.8,"tmin":19.6,"precip_mm":4.2,"prob_chuva":41,"weathercode":95,"tempo":"trovoada","vento_kmh":31.2,"rajada_kmh":56.9,"vento_dir_graus":14,"et0_mm":4.62},{"data":"2026-07-19","tmax":25.0,"tmin":17.9,"precip_mm":33.3,"prob_chuva":65,"weathercode":96,"tempo":"trovoada","vento_kmh":24.8,"rajada_kmh":47.9,"vento_dir_graus":30,"et0_mm":3.04},{"data":"2026-07-20","tmax":24.9,"tmin":18.6,"precip_mm":22.6,"prob_chuva":60,"weathercode":95,"tempo":"trovoada","vento_kmh":29.5,"rajada_kmh":76.3,"vento_dir_graus":10,"et0_mm":3.88},{"data":"2026-07-21","tmax":20.6,"tmin":18.5,"precip_mm":76.0,"prob_chuva":71,"weathercode":96,"tempo":"trovoada","vento_kmh":14.3,"rajada_kmh":41.8,"vento_dir_graus":53,"et0_mm":1.07}],"fonte":"Open-Meteo","atualizado_em":"2026-07-15T05:07:38Z"},"colheita":{"pct_plantado":100.0,"pct_colhido":100.0,"area_soja_ha":10900,"fonte":"Emater/RS-Ascar (regional Santa Rosa, Fenasoja 30/04)","data_referencia":"2026-05-14","granularidade":"regional (Santa Rosa) aplicado ao municipio","regiao":"Santa Rosa","derivado":true,"ha_plantado_estim":10900,"ha_colhido_estim":10900}},{"id":"candido_godoi","nome":"CÂNDIDO GODÓI","ibge":4304309,"uf":"RS","lat":-27.9515,"lon":-54.7517,"area_soja_ha":9500,"clima":{"ibge":4304309,"nome":"CÂNDIDO GODÓI","uf":"RS","lat":-27.9515,"lon":-54.7517,"atual":{"tmax":22.5,"tmin":10.9,"precip_mm":0.0,"prob_chuva":0,"weathercode":0,"tempo":"sol"},"previsao_7d":[{"data":"2026-07-15","tmax":22.5,"tmin":10.9,"precip_mm":0.0,"prob_chuva":0,"weathercode":0,"tempo":"sol","vento_kmh":21.9,"rajada_kmh":41.0,"vento_dir_graus":43,"et0_mm":3.24},{"data":"2026-07-16","tmax":27.1,"tmin":15.3,"precip_mm":0.0,"prob_chuva":4,"weathercode":0,"tempo":"sol","vento_kmh":24.6,"rajada_kmh":46.8,"vento_dir_graus":40,"et0_mm":4.41},{"data":"2026-07-17","tmax":28.5,"tmin":22.1,"precip_mm":0.0,"prob_chuva":2,"weathercode":1,"tempo":"parcial","vento_kmh":34.7,"rajada_kmh":70.2,"vento_dir_graus":17,"et0_mm":5.17},{"data":"2026-07-18","tmax":28.3,"tmin":19.5,"precip_mm":43.8,"prob_chuva":76,"weathercode":96,"tempo":"trovoada","vento_kmh":27.4,"rajada_kmh":58.7,"vento_dir_graus":2,"et0_mm":4.22},{"data":"2026-07-19","tmax":28.2,"tmin":19.2,"precip_mm":74.3,"prob_chuva":84,"weathercode":96,"tempo":"trovoada","vento_kmh":23.1,"rajada_kmh":54.0,"vento_dir_graus":29,"et0_mm":3.1},{"data":"2026-07-20","tmax":25.3,"tmin":19.4,"precip_mm":29.1,"prob_chuva":76,"weathercode":96,"tempo":"trovoada","vento_kmh":38.9,"rajada_kmh":78.8,"vento_dir_graus":7,"et0_mm":3.83},{"data":"2026-07-21","tmax":21.7,"tmin":17.2,"precip_mm":22.6,"prob_chuva":81,"weathercode":96,"tempo":"trovoada","vento_kmh":16.3,"rajada_kmh":42.1,"vento_dir_graus":142,"et0_mm":1.27}],"fonte":"Open-Meteo","atualizado_em":"2026-07-15T05:07:38Z"},"colheita":{"pct_plantado":100.0,"pct_colhido":100.0,"area_soja_ha":9500,"fonte":"Emater/RS-Ascar (regional Santa Rosa, Fenasoja 30/04)","data_referencia":"2026-05-14","granularidade":"regional (Santa Rosa) aplicado ao municipio","regiao":"Santa Rosa","derivado":true,"ha_plantado_estim":9500,"ha_colhido_estim":9500}},{"id":"coronel_bicaco","nome":"CORONEL BICACO","ibge":4305900,"uf":"RS","lat":-27.7197,"lon":-53.7022,"area_soja_ha":34000,"clima":{"ibge":4305900,"nome":"CORONEL BICACO","uf":"RS","lat":-27.7197,"lon":-53.7022,"atual":{"tmax":20.3,"tmin":9.5,"precip_mm":0.0,"prob_chuva":0,"weathercode":0,"tempo":"sol"},"previsao_7d":[{"data":"2026-07-15","tmax":20.3,"tmin":9.5,"precip_mm":0.0,"prob_chuva":0,"weathercode":0,"tempo":"sol","vento_kmh":21.3,"rajada_kmh":35.6,"vento_dir_graus":41,"et0_mm":2.98},{"data":"2026-07-16","tmax":24.4,"tmin":13.1,"precip_mm":0.0,"prob_chuva":0,"weathercode":0,"tempo":"sol","vento_kmh":24.5,"rajada_kmh":42.5,"vento_dir_graus":39,"et0_mm":3.89},{"data":"2026-07-17","tmax":25.7,"tmin":19.3,"precip_mm":0.0,"prob_chuva":2,"weathercode":0,"tempo":"sol","vento_kmh":34.9,"rajada_kmh":63.7,"vento_dir_graus":20,"et0_mm":4.57},{"data":"2026-07-18","tmax":26.2,"tmin":19.8,"precip_mm":3.6,"prob_chuva":41,"weathercode":95,"tempo":"trovoada","vento_kmh":31.0,"rajada_kmh":60.8,"vento_dir_graus":10,"et0_mm":4.72},{"data":"2026-07-19","tmax":25.1,"tmin":17.6,"precip_mm":35.4,"prob_chuva":65,"weathercode":96,"tempo":"trovoada","vento_kmh":23.9,"rajada_kmh":51.8,"vento_dir_graus":27,"et0_mm":2.95},{"data":"2026-07-20","tmax":24.3,"tmin":18.3,"precip_mm":15.7,"prob_chuva":60,"weathercode":95,"tempo":"trovoada","vento_kmh":28.3,"rajada_kmh":70.6,"vento_dir_graus":8,"et0_mm":3.75},{"data":"2026-07-21","tmax":20.7,"tmin":18.0,"precip_mm":73.8,"prob_chuva":71,"weathercode":96,"tempo":"trovoada","vento_kmh":12.1,"rajada_kmh":47.5,"vento_dir_graus":55,"et0_mm":1.1}],"fonte":"Open-Meteo","atualizado_em":"2026-07-15T05:07:38Z"},"colheita":{"pct_plantado":100.0,"pct_colhido":100.0,"area_soja_ha":34000,"fonte":"Emater/RS-Ascar (regional Santa Rosa, Fenasoja 30/04)","data_referencia":"2026-05-14","granularidade":"regional (Santa Rosa) aplicado ao municipio","regiao":"Santa Rosa","derivado":true,"ha_plantado_estim":34000,"ha_colhido_estim":34000}},{"id":"crissiumal","nome":"CRISSIUMAL","ibge":4306007,"uf":"RS","lat":-27.4999,"lon":-54.0994,"area_soja_ha":13500,"clima":{"ibge":4306007,"nome":"CRISSIUMAL","uf":"RS","lat":-27.4999,"lon":-54.0994,"atual":{"tmax":22.1,"tmin":10.0,"precip_mm":0.0,"prob_chuva":0,"weathercode":0,"tempo":"sol"},"previsao_7d":[{"data":"2026-07-15","tmax":22.1,"tmin":10.0,"precip_mm":0.0,"prob_chuva":0,"weathercode":0,"tempo":"sol","vento_kmh":19.7,"rajada_kmh":36.7,"vento_dir_graus":48,"et0_mm":3.21},{"data":"2026-07-16","tmax":26.4,"tmin":14.5,"precip_mm":0.0,"prob_chuva":0,"weathercode":0,"tempo":"sol","vento_kmh":23.6,"rajada_kmh":45.0,"vento_dir_graus":44,"et0_mm":4.35},{"data":"2026-07-17","tmax":28.0,"tmin":20.8,"precip_mm":0.0,"prob_chuva":2,"weathercode":0,"tempo":"sol","vento_kmh":29.3,"rajada_kmh":58.0,"vento_dir_graus":25,"et0_mm":5.15},{"data":"2026-07-18","tmax":28.0,"tmin":20.0,"precip_mm":4.5,"prob_chuva":41,"weathercode":95,"tempo":"trovoada","vento_kmh":25.4,"rajada_kmh":65.5,"vento_dir_graus":14,"et0_mm":4.72},{"data":"2026-07-19","tmax":27.3,"tmin":18.2,"precip_mm":23.7,"prob_chuva":51,"weathercode":96,"tempo":"trovoada","vento_kmh":25.6,"rajada_kmh":51.5,"vento_dir_graus":35,"et0_mm":3.42},{"data":"2026-07-20","tmax":25.8,"tmin":18.9,"precip_mm":15.6,"prob_chuva":60,"weathercode":95,"tempo":"trovoada","vento_kmh":28.5,"rajada_kmh":76.7,"vento_dir_graus":10,"et0_mm":4.03},{"data":"2026-07-21","tmax":21.1,"tmin":18.7,"precip_mm":51.8,"prob_chuva":67,"weathercode":95,"tempo":"trovoada","vento_kmh":12.2,"rajada_kmh":37.1,"vento_dir_graus":77,"et0_mm":1.1}],"fonte":"Open-Meteo","atualizado_em":"2026-07-15T05:07:38Z"},"colheita":{"pct_plantado":100.0,"pct_colhido":100.0,"area_soja_ha":13500,"fonte":"Emater/RS-Ascar (regional Santa Rosa, Fenasoja 30/04)","data_referencia":"2026-05-14","granularidade":"regional (Santa Rosa) aplicado ao municipio","regiao":"Santa Rosa","derivado":true,"ha_plantado_estim":13500,"ha_colhido_estim":13500}},{"id":"derrubadas","nome":"DERRUBADAS","ibge":4306320,"uf":"RS","lat":-27.2642,"lon":-53.8645,"area_soja_ha":10000,"clima":{"ibge":4306320,"nome":"DERRUBADAS","uf":"RS","lat":-27.2642,"lon":-53.8645,"atual":{"tmax":22.7,"tmin":8.4,"precip_mm":0.0,"prob_chuva":0,"weathercode":0,"tempo":"sol"},"previsao_7d":[{"data":"2026-07-15","tmax":22.7,"tmin":8.4,"precip_mm":0.0,"prob_chuva":0,"weathercode":0,"tempo":"sol","vento_kmh":15.2,"rajada_kmh":31.0,"vento_dir_graus":66,"et0_mm":2.78},{"data":"2026-07-16","tmax":26.5,"tmin":12.0,"precip_mm":0.0,"prob_chuva":0,"weathercode":0,"tempo":"sol","vento_kmh":18.3,"rajada_kmh":38.5,"vento_dir_graus":57,"et0_mm":3.74},{"data":"2026-07-17","tmax":27.5,"tmin":20.1,"precip_mm":0.0,"prob_chuva":2,"weathercode":0,"tempo":"sol","vento_kmh":23.3,"rajada_kmh":51.5,"vento_dir_graus":35,"et0_mm":4.59},{"data":"2026-07-18","tmax":28.1,"tmin":18.3,"precip_mm":3.0,"prob_chuva":24,"weathercode":95,"tempo":"trovoada","vento_kmh":21.6,"rajada_kmh":49.7,"vento_dir_graus":37,"et0_mm":4.26},{"data":"2026-07-19","tmax":27.6,"tmin":17.6,"precip_mm":11.4,"prob_chuva":41,"weathercode":96,"tempo":"trovoada","vento_kmh":18.3,"rajada_kmh":45.4,"vento_dir_graus":46,"et0_mm":3.26},{"data":"2026-07-20","tmax":27.4,"tmin":19.0,"precip_mm":11.2,"prob_chuva":50,"weathercode":95,"tempo":"trovoada","vento_kmh":21.9,"rajada_kmh":53.6,"vento_dir_graus":15,"et0_mm":4.01},{"data":"2026-07-21","tmax":20.3,"tmin":18.2,"precip_mm":55.6,"prob_chuva":69,"weathercode":95,"tempo":"trovoada","vento_kmh":8.6,"rajada_kmh":38.5,"vento_dir_graus":70,"et0_mm":0.89}],"fonte":"Open-Meteo","atualizado_em":"2026-07-15T05:07:38Z"},"colheita":{"pct_plantado":100.0,"pct_colhido":100.0,"area_soja_ha":10000,"fonte":"Emater/RS-Ascar - Informativo Conjuntural (fechamento)","data_referencia":"2026-05-14","granularidade":"regional (Frederico Westphalen) aplicado ao municipio","regiao":"Frederico Westphalen","derivado":true,"ha_plantado_estim":10000,"ha_colhido_estim":10000}},{"id":"doutor_mauricio_cardoso","nome":"DOUTOR MAURÍCIO CARDOSO","ibge":4306734,"uf":"RS","lat":-27.5103,"lon":-54.3577,"area_soja_ha":13780,"clima":{"ibge":4306734,"nome":"DOUTOR MAURÍCIO CARDOSO","uf":"RS","lat":-27.5103,"lon":-54.3577,"atual":{"tmax":24.2,"tmin":9.7,"precip_mm":0.0,"prob_chuva":0,"weathercode":0,"tempo":"sol"},"previsao_7d":[{"data":"2026-07-15","tmax":24.2,"tmin":9.7,"precip_mm":0.0,"prob_chuva":0,"weathercode":0,"tempo":"sol","vento_kmh":16.0,"rajada_kmh":31.7,"vento_dir_graus":52,"et0_mm":2.9},{"data":"2026-07-16","tmax":28.5,"tmin":14.1,"precip_mm":0.0,"prob_chuva":0,"weathercode":0,"tempo":"sol","vento_kmh":20.6,"rajada_kmh":36.0,"vento_dir_graus":47,"et0_mm":4.09},{"data":"2026-07-17","tmax":29.3,"tmin":21.6,"precip_mm":0.0,"prob_chuva":2,"weathercode":1,"tempo":"parcial","vento_kmh":30.1,"rajada_kmh":54.0,"vento_dir_graus":26,"et0_mm":5.1},{"data":"2026-07-18","tmax":29.4,"tmin":20.4,"precip_mm":3.2,"prob_chuva":45,"weathercode":80,"tempo":"chuva","vento_kmh":25.4,"rajada_kmh":49.7,"vento_dir_graus":13,"et0_mm":4.55},{"data":"2026-07-19","tmax":28.7,"tmin":19.2,"precip_mm":24.4,"prob_chuva":65,"weathercode":95,"tempo":"trovoada","vento_kmh":23.8,"rajada_kmh":43.2,"vento_dir_graus":37,"et0_mm":3.43},{"data":"2026-07-20","tmax":26.8,"tmin":20.1,"precip_mm":8.8,"prob_chuva":59,"weathercode":95,"tempo":"trovoada","vento_kmh":28.1,"rajada_kmh":58.3,"vento_dir_graus":12,"et0_mm":4.06},{"data":"2026-07-21","tmax":22.1,"tmin":19.8,"precip_mm":26.2,"prob_chuva":67,"weathercode":95,"tempo":"trovoada","vento_kmh":11.5,"rajada_kmh":32.0,"vento_dir_graus":114,"et0_mm":1.07}],"fonte":"Open-Meteo","atualizado_em":"2026-07-15T05:07:38Z"},"colheita":{"pct_plantado":100.0,"pct_colhido":100.0,"area_soja_ha":13780,"fonte":"Emater/RS-Ascar (regional Santa Rosa, Fenasoja 30/04)","data_referencia":"2026-05-14","granularidade":"regional (Santa Rosa) aplicado ao municipio","regiao":"Santa Rosa","derivado":true,"ha_plantado_estim":13780,"ha_colhido_estim":13780}},{"id":"girua","nome":"GIRUÁ","ibge":4309001,"uf":"RS","lat":-28.0297,"lon":-54.3517,"area_soja_ha":62000,"clima":{"ibge":4309001,"nome":"GIRUÁ","uf":"RS","lat":-28.0297,"lon":-54.3517,"atual":{"tmax":20.9,"tmin":9.9,"precip_mm":0.0,"prob_chuva":0,"weathercode":0,"tempo":"sol"},"previsao_7d":[{"data":"2026-07-15","tmax":20.9,"tmin":9.9,"precip_mm":0.0,"prob_chuva":0,"weathercode":0,"tempo":"sol","vento_kmh":22.4,"rajada_kmh":41.4,"vento_dir_graus":35,"et0_mm":3.06},{"data":"2026-07-16","tmax":25.3,"tmin":13.8,"precip_mm":0.0,"prob_chuva":0,"weathercode":0,"tempo":"sol","vento_kmh":26.0,"rajada_kmh":46.4,"vento_dir_graus":37,"et0_mm":4.0},{"data":"2026-07-17","tmax":27.2,"tmin":20.3,"precip_mm":0.0,"prob_chuva":4,"weathercode":0,"tempo":"sol","vento_kmh":35.4,"rajada_kmh":69.1,"vento_dir_graus":15,"et0_mm":4.82},{"data":"2026-07-18","tmax":27.1,"tmin":19.1,"precip_mm":18.4,"prob_chuva":65,"weathercode":96,"tempo":"trovoada","vento_kmh":32.1,"rajada_kmh":68.0,"vento_dir_graus":3,"et0_mm":4.27},{"data":"2026-07-19","tmax":25.7,"tmin":18.5,"precip_mm":56.7,"prob_chuva":75,"weathercode":95,"tempo":"trovoada","vento_kmh":28.5,"rajada_kmh":51.1,"vento_dir_graus":25,"et0_mm":2.85},{"data":"2026-07-20","tmax":24.1,"tmin":18.6,"precip_mm":21.8,"prob_chuva":67,"weathercode":95,"tempo":"trovoada","vento_kmh":36.6,"rajada_kmh":73.1,"vento_dir_graus":5,"et0_mm":3.89},{"data":"2026-07-21","tmax":19.5,"tmin":17.3,"precip_mm":34.0,"prob_chuva":73,"weathercode":96,"tempo":"trovoada","vento_kmh":17.9,"rajada_kmh":45.7,"vento_dir_graus":139,"et0_mm":1.05}],"fonte":"Open-Meteo","atualizado_em":"2026-07-15T05:07:38Z"},"colheita":{"pct_plantado":100.0,"pct_colhido":100.0,"area_soja_ha":62000,"fonte":"Emater/RS-Ascar (regional Santa Rosa, Fenasoja 30/04)","data_referencia":"2026-05-14","granularidade":"regional (Santa Rosa) aplicado ao municipio","regiao":"Santa Rosa","derivado":true,"ha_plantado_estim":62000,"ha_colhido_estim":62000}},{"id":"horizontina","nome":"HORIZONTINA","ibge":4309605,"uf":"RS","lat":-27.6282,"lon":-54.3053,"area_soja_ha":12000,"clima":{"ibge":4309605,"nome":"HORIZONTINA","uf":"RS","lat":-27.6282,"lon":-54.3053,"atual":{"tmax":23.1,"tmin":9.8,"precip_mm":0.0,"prob_chuva":0,"weathercode":0,"tempo":"sol"},"previsao_7d":[{"data":"2026-07-15","tmax":23.1,"tmin":9.8,"precip_mm":0.0,"prob_chuva":0,"weathercode":0,"tempo":"sol","vento_kmh":15.2,"rajada_kmh":31.3,"vento_dir_graus":49,"et0_mm":2.89},{"data":"2026-07-16","tmax":27.6,"tmin":14.3,"precip_mm":0.0,"prob_chuva":2,"weathercode":0,"tempo":"sol","vento_kmh":21.5,"rajada_kmh":39.2,"vento_dir_graus":42,"et0_mm":4.03},{"data":"2026-07-17","tmax":28.9,"tmin":21.5,"precip_mm":0.0,"prob_chuva":4,"weathercode":1,"tempo":"parcial","vento_kmh":31.0,"rajada_kmh":58.7,"vento_dir_graus":21,"et0_mm":5.1},{"data":"2026-07-18","tmax":28.9,"tmin":19.9,"precip_mm":4.7,"prob_chuva":59,"weathercode":95,"tempo":"trovoada","vento_kmh":27.0,"rajada_kmh":58.3,"vento_dir_graus":9,"et0_mm":4.59},{"data":"2026-07-19","tmax":28.2,"tmin":19.1,"precip_mm":21.1,"prob_chuva":71,"weathercode":95,"tempo":"trovoada","vento_kmh":27.2,"rajada_kmh":49.7,"vento_dir_graus":32,"et0_mm":3.4},{"data":"2026-07-20","tmax":26.5,"tmin":19.8,"precip_mm":16.6,"prob_chuva":64,"weathercode":95,"tempo":"trovoada","vento_kmh":30.9,"rajada_kmh":68.4,"vento_dir_graus":9,"et0_mm":4.12},{"data":"2026-07-21","tmax":21.2,"tmin":19.6,"precip_mm":35.8,"prob_chuva":65,"weathercode":95,"tempo":"trovoada","vento_kmh":10.8,"rajada_kmh":33.8,"vento_dir_graus":122,"et0_mm":1.01}],"fonte":"Open-Meteo","atualizado_em":"2026-07-15T05:07:38Z"},"colheita":{"pct_plantado":100.0,"pct_colhido":100.0,"area_soja_ha":12000,"fonte":"Emater/RS-Ascar (regional Santa Rosa, Fenasoja 30/04)","data_referencia":"2026-05-14","granularidade":"regional (Santa Rosa) aplicado ao municipio","regiao":"Santa Rosa","derivado":true,"ha_plantado_estim":12000,"ha_colhido_estim":12000}},{"id":"humaita","nome":"HUMAITÁ","ibge":4309704,"uf":"RS","lat":-27.5691,"lon":-53.9695,"area_soja_ha":7150,"clima":{"ibge":4309704,"nome":"HUMAITÁ","uf":"RS","lat":-27.5691,"lon":-53.9695,"atual":{"tmax":21.6,"tmin":10.1,"precip_mm":0.0,"prob_chuva":0,"weathercode":0,"tempo":"sol"},"previsao_7d":[{"data":"2026-07-15","tmax":21.6,"tmin":10.1,"precip_mm":0.0,"prob_chuva":0,"weathercode":0,"tempo":"sol","vento_kmh":21.8,"rajada_kmh":38.2,"vento_dir_graus":53,"et0_mm":3.2},{"data":"2026-07-16","tmax":25.8,"tmin":14.1,"precip_mm":0.0,"prob_chuva":0,"weathercode":0,"tempo":"sol","vento_kmh":24.7,"rajada_kmh":44.6,"vento_dir_graus":48,"et0_mm":4.24},{"data":"2026-07-17","tmax":27.2,"tmin":20.7,"precip_mm":0.0,"prob_chuva":2,"weathercode":0,"tempo":"sol","vento_kmh":31.3,"rajada_kmh":58.7,"vento_dir_graus":26,"et0_mm":4.96},{"data":"2026-07-18","tmax":27.9,"tmin":20.6,"precip_mm":5.6,"prob_chuva":41,"weathercode":96,"tempo":"trovoada","vento_kmh":26.7,"rajada_kmh":60.5,"vento_dir_graus":13,"et0_mm":4.72},{"data":"2026-07-19","tmax":27.0,"tmin":18.2,"precip_mm":23.8,"prob_chuva":51,"weathercode":96,"tempo":"trovoada","vento_kmh":26.3,"rajada_kmh":51.1,"vento_dir_graus":35,"et0_mm":3.25},{"data":"2026-07-20","tmax":25.8,"tmin":18.9,"precip_mm":23.5,"prob_chuva":60,"weathercode":95,"tempo":"trovoada","vento_kmh":30.4,"rajada_kmh":74.2,"vento_dir_graus":10,"et0_mm":4.18},{"data":"2026-07-21","tmax":20.9,"tmin":18.9,"precip_mm":71.0,"prob_chuva":67,"weathercode":96,"tempo":"trovoada","vento_kmh":14.0,"rajada_kmh":36.4,"vento_dir_graus":58,"et0_mm":1.09}],"fonte":"Open-Meteo","atualizado_em":"2026-07-15T05:07:38Z"},"colheita":{"pct_plantado":100.0,"pct_colhido":100.0,"area_soja_ha":7150,"fonte":"Emater/RS-Ascar (regional Santa Rosa, Fenasoja 30/04)","data_referencia":"2026-05-14","granularidade":"regional (Santa Rosa) aplicado ao municipio","regiao":"Santa Rosa","derivado":true,"ha_plantado_estim":7150,"ha_colhido_estim":7150}},{"id":"independencia","nome":"INDEPENDÊNCIA","ibge":4310405,"uf":"RS","lat":-27.8354,"lon":-54.1886,"area_soja_ha":22000,"clima":{"ibge":4310405,"nome":"INDEPENDÊNCIA","uf":"RS","lat":-27.8354,"lon":-54.1886,"atual":{"tmax":22.2,"tmin":9.9,"precip_mm":0.0,"prob_chuva":0,"weathercode":0,"tempo":"sol"},"previsao_7d":[{"data":"2026-07-15","tmax":22.2,"tmin":9.9,"precip_mm":0.0,"prob_chuva":0,"weathercode":0,"tempo":"sol","vento_kmh":14.7,"rajada_kmh":31.7,"vento_dir_graus":44,"et0_mm":2.91},{"data":"2026-07-16","tmax":26.5,"tmin":13.9,"precip_mm":0.0,"prob_chuva":2,"weathercode":0,"tempo":"sol","vento_kmh":21.3,"rajada_kmh":40.0,"vento_dir_graus":41,"et0_mm":3.88},{"data":"2026-07-17","tmax":28.3,"tmin":21.4,"precip_mm":0.0,"prob_chuva":4,"weathercode":1,"tempo":"parcial","vento_kmh":30.2,"rajada_kmh":58.3,"vento_dir_graus":18,"et0_mm":4.95},{"data":"2026-07-18","tmax":28.4,"tmin":19.5,"precip_mm":11.9,"prob_chuva":59,"weathercode":95,"tempo":"trovoada","vento_kmh":30.3,"rajada_kmh":58.3,"vento_dir_graus":2,"et0_mm":4.51},{"data":"2026-07-19","tmax":26.9,"tmin":18.7,"precip_mm":50.2,"prob_chuva":71,"weathercode":95,"tempo":"trovoada","vento_kmh":27.1,"rajada_kmh":50.8,"vento_dir_graus":29,"et0_mm":3.08},{"data":"2026-07-20","tmax":26.0,"tmin":19.1,"precip_mm":24.0,"prob_chuva":64,"weathercode":95,"tempo":"trovoada","vento_kmh":31.7,"rajada_kmh":72.0,"vento_dir_graus":7,"et0_mm":4.08},{"data":"2026-07-21","tmax":21.2,"tmin":19.1,"precip_mm":37.4,"prob_chuva":65,"weathercode":96,"tempo":"trovoada","vento_kmh":15.2,"rajada_kmh":39.6,"vento_dir_graus":123,"et0_mm":1.09}],"fonte":"Open-Meteo","atualizado_em":"2026-07-15T05:07:38Z"},"colheita":{"pct_plantado":100.0,"pct_colhido":100.0,"area_soja_ha":22000,"fonte":"Emater/RS-Ascar (regional Santa Rosa, Fenasoja 30/04)","data_referencia":"2026-05-14","granularidade":"regional (Santa Rosa) aplicado ao municipio","regiao":"Santa Rosa","derivado":true,"ha_plantado_estim":22000,"ha_colhido_estim":22000}},{"id":"inhacora","nome":"INHACORÁ","ibge":4310413,"uf":"RS","lat":-27.8752,"lon":-54.015,"area_soja_ha":7200,"clima":{"ibge":4310413,"nome":"INHACORÁ","uf":"RS","lat":-27.8752,"lon":-54.015,"atual":{"tmax":21.4,"tmin":10.4,"precip_mm":0.0,"prob_chuva":0,"weathercode":0,"tempo":"sol"},"previsao_7d":[{"data":"2026-07-15","tmax":21.4,"tmin":10.4,"precip_mm":0.0,"prob_chuva":0,"weathercode":0,"tempo":"sol","vento_kmh":17.4,"rajada_kmh":31.7,"vento_dir_graus":44,"et0_mm":3.04},{"data":"2026-07-16","tmax":25.6,"tmin":14.3,"precip_mm":0.0,"prob_chuva":0,"weathercode":0,"tempo":"sol","vento_kmh":24.0,"rajada_kmh":42.1,"vento_dir_graus":39,"et0_mm":4.05},{"data":"2026-07-17","tmax":26.9,"tmin":20.8,"precip_mm":0.0,"prob_chuva":2,"weathercode":1,"tempo":"parcial","vento_kmh":31.4,"rajada_kmh":56.5,"vento_dir_graus":16,"et0_mm":4.86},{"data":"2026-07-18","tmax":27.6,"tmin":19.3,"precip_mm":9.3,"prob_chuva":57,"weathercode":96,"tempo":"trovoada","vento_kmh":31.9,"rajada_kmh":54.0,"vento_dir_graus":2,"et0_mm":4.47},{"data":"2026-07-19","tmax":26.4,"tmin":18.5,"precip_mm":47.4,"prob_chuva":73,"weathercode":96,"tempo":"trovoada","vento_kmh":28.5,"rajada_kmh":49.3,"vento_dir_graus":27,"et0_mm":3.0},{"data":"2026-07-20","tmax":25.6,"tmin":18.9,"precip_mm":19.8,"prob_chuva":65,"weathercode":95,"tempo":"trovoada","vento_kmh":33.9,"rajada_kmh":73.4,"vento_dir_graus":5,"et0_mm":4.13},{"data":"2026-07-21","tmax":20.4,"tmin":18.9,"precip_mm":33.4,"prob_chuva":68,"weathercode":96,"tempo":"trovoada","vento_kmh":16.2,"rajada_kmh":41.8,"vento_dir_graus":118,"et0_mm":1.04}],"fonte":"Open-Meteo","atualizado_em":"2026-07-15T05:07:38Z"},"colheita":{"pct_plantado":100.0,"pct_colhido":100.0,"area_soja_ha":7200,"fonte":"Emater/RS-Ascar (regional Santa Rosa, Fenasoja 30/04)","data_referencia":"2026-05-14","granularidade":"regional (Santa Rosa) aplicado ao municipio","regiao":"Santa Rosa","derivado":true,"ha_plantado_estim":7200,"ha_colhido_estim":7200}},{"id":"miraguai","nome":"MIRAGUAÍ","ibge":4312302,"uf":"RS","lat":-27.497,"lon":-53.6891,"area_soja_ha":5400,"clima":{"ibge":4312302,"nome":"MIRAGUAÍ","uf":"RS","lat":-27.497,"lon":-53.6891,"atual":{"tmax":21.6,"tmin":9.0,"precip_mm":0.0,"prob_chuva":0,"weathercode":0,"tempo":"sol"},"previsao_7d":[{"data":"2026-07-15","tmax":21.6,"tmin":9.0,"precip_mm":0.0,"prob_chuva":0,"weathercode":0,"tempo":"sol","vento_kmh":14.0,"rajada_kmh":29.9,"vento_dir_graus":54,"et0_mm":2.8},{"data":"2026-07-16","tmax":26.0,"tmin":12.2,"precip_mm":0.0,"prob_chuva":0,"weathercode":0,"tempo":"sol","vento_kmh":19.3,"rajada_kmh":36.7,"vento_dir_graus":49,"et0_mm":3.65},{"data":"2026-07-17","tmax":26.9,"tmin":19.8,"precip_mm":0.0,"prob_chuva":2,"weathercode":0,"tempo":"sol","vento_kmh":29.8,"rajada_kmh":57.2,"vento_dir_graus":25,"et0_mm":4.54},{"data":"2026-07-18","tmax":27.5,"tmin":19.5,"precip_mm":3.6,"prob_chuva":37,"weathercode":95,"tempo":"trovoada","vento_kmh":28.2,"rajada_kmh":55.4,"vento_dir_graus":18,"et0_mm":4.48},{"data":"2026-07-19","tmax":26.8,"tmin":17.9,"precip_mm":27.6,"prob_chuva":60,"weathercode":96,"tempo":"trovoada","vento_kmh":21.8,"rajada_kmh":46.4,"vento_dir_graus":36,"et0_mm":3.07},{"data":"2026-07-20","tmax":26.4,"tmin":18.6,"precip_mm":22.4,"prob_chuva":57,"weathercode":95,"tempo":"trovoada","vento_kmh":24.3,"rajada_kmh":55.8,"vento_dir_graus":13,"et0_mm":3.78},{"data":"2026-07-21","tmax":20.6,"tmin":18.4,"precip_mm":92.2,"prob_chuva":71,"weathercode":96,"tempo":"trovoada","vento_kmh":8.5,"rajada_kmh":40.3,"vento_dir_graus":85,"et0_mm":0.99}],"fonte":"Open-Meteo","atualizado_em":"2026-07-15T05:07:38Z"},"colheita":{"pct_plantado":100.0,"pct_colhido":100.0,"area_soja_ha":5400,"fonte":"Emater/RS-Ascar (regional Santa Rosa, Fenasoja 30/04)","data_referencia":"2026-05-14","granularidade":"regional (Santa Rosa) aplicado ao municipio","regiao":"Santa Rosa","derivado":true,"ha_plantado_estim":5400,"ha_colhido_estim":5400}},{"id":"nova_candelaria","nome":"NOVA CANDELÁRIA","ibge":4313011,"uf":"RS","lat":-27.6137,"lon":-54.1074,"area_soja_ha":2800,"clima":{"ibge":4313011,"nome":"NOVA CANDELÁRIA","uf":"RS","lat":-27.6137,"lon":-54.1074,"atual":{"tmax":22.3,"tmin":10.7,"precip_mm":0.0,"prob_chuva":0,"weathercode":0,"tempo":"sol"},"previsao_7d":[{"data":"2026-07-15","tmax":22.3,"tmin":10.7,"precip_mm":0.0,"prob_chuva":0,"weathercode":0,"tempo":"sol","vento_kmh":20.1,"rajada_kmh":36.4,"vento_dir_graus":50,"et0_mm":3.28},{"data":"2026-07-16","tmax":26.7,"tmin":15.1,"precip_mm":0.0,"prob_chuva":0,"weathercode":0,"tempo":"sol","vento_kmh":24.2,"rajada_kmh":45.4,"vento_dir_graus":44,"et0_mm":4.45},{"data":"2026-07-17","tmax":28.4,"tmin":21.6,"precip_mm":0.0,"prob_chuva":2,"weathercode":0,"tempo":"sol","vento_kmh":29.0,"rajada_kmh":57.6,"vento_dir_graus":24,"et0_mm":5.29},{"data":"2026-07-18","tmax":28.7,"tmin":20.3,"precip_mm":6.4,"prob_chuva":41,"weathercode":95,"tempo":"trovoada","vento_kmh":26.3,"rajada_kmh":65.5,"vento_dir_graus":10,"et0_mm":4.71},{"data":"2026-07-19","tmax":27.9,"tmin":18.8,"precip_mm":17.3,"prob_chuva":51,"weathercode":95,"tempo":"trovoada","vento_kmh":25.6,"rajada_kmh":50.0,"vento_dir_graus":35,"et0_mm":3.4},{"data":"2026-07-20","tmax":26.4,"tmin":19.4,"precip_mm":20.2,"prob_chuva":60,"weathercode":95,"tempo":"trovoada","vento_kmh":29.6,"rajada_kmh":68.0,"vento_dir_graus":9,"et0_mm":4.28},{"data":"2026-07-21","tmax":21.6,"tmin":19.3,"precip_mm":51.6,"prob_chuva":67,"weathercode":95,"tempo":"trovoada","vento_kmh":12.6,"rajada_kmh":36.4,"vento_dir_graus":81,"et0_mm":1.11}],"fonte":"Open-Meteo","atualizado_em":"2026-07-15T05:07:38Z"},"colheita":{"pct_plantado":100.0,"pct_colhido":100.0,"area_soja_ha":2800,"fonte":"Emater/RS-Ascar (regional Santa Rosa, Fenasoja 30/04)","data_referencia":"2026-05-14","granularidade":"regional (Santa Rosa) aplicado ao municipio","regiao":"Santa Rosa","derivado":true,"ha_plantado_estim":2800,"ha_colhido_estim":2800}},{"id":"novo_machado","nome":"NOVO MACHADO","ibge":4313425,"uf":"RS","lat":-27.5765,"lon":-54.5036,"area_soja_ha":11680,"clima":{"ibge":4313425,"nome":"NOVO MACHADO","uf":"RS","lat":-27.5765,"lon":-54.5036,"atual":{"tmax":24.0,"tmin":9.6,"precip_mm":0.0,"prob_chuva":0,"weathercode":0,"tempo":"sol"},"previsao_7d":[{"data":"2026-07-15","tmax":24.0,"tmin":9.6,"precip_mm":0.0,"prob_chuva":0,"weathercode":0,"tempo":"sol","vento_kmh":17.0,"rajada_kmh":33.1,"vento_dir_graus":59,"et0_mm":2.9},{"data":"2026-07-16","tmax":28.3,"tmin":13.9,"precip_mm":0.0,"prob_chuva":0,"weathercode":0,"tempo":"sol","vento_kmh":20.9,"rajada_kmh":37.1,"vento_dir_graus":52,"et0_mm":4.07},{"data":"2026-07-17","tmax":28.9,"tmin":21.5,"precip_mm":0.0,"prob_chuva":4,"weathercode":1,"tempo":"parcial","vento_kmh":31.0,"rajada_kmh":55.4,"vento_dir_graus":28,"et0_mm":4.91},{"data":"2026-07-18","tmax":29.1,"tmin":20.4,"precip_mm":9.3,"prob_chuva":52,"weathercode":95,"tempo":"trovoada","vento_kmh":24.9,"rajada_kmh":48.2,"vento_dir_graus":15,"et0_mm":4.16},{"data":"2026-07-19","tmax":28.7,"tmin":19.1,"precip_mm":37.2,"prob_chuva":65,"weathercode":95,"tempo":"trovoada","vento_kmh":28.9,"rajada_kmh":50.4,"vento_dir_graus":34,"et0_mm":3.31},{"data":"2026-07-20","tmax":26.2,"tmin":19.8,"precip_mm":12.9,"prob_chuva":63,"weathercode":96,"tempo":"trovoada","vento_kmh":33.2,"rajada_kmh":62.3,"vento_dir_graus":12,"et0_mm":4.03},{"data":"2026-07-21","tmax":22.2,"tmin":19.2,"precip_mm":31.0,"prob_chuva":65,"weathercode":95,"tempo":"trovoada","vento_kmh":14.7,"rajada_kmh":32.8,"vento_dir_graus":125,"et0_mm":1.22}],"fonte":"Open-Meteo","atualizado_em":"2026-07-15T05:07:38Z"},"colheita":{"pct_plantado":100.0,"pct_colhido":100.0,"area_soja_ha":11680,"fonte":"Emater/RS-Ascar (regional Santa Rosa, Fenasoja 30/04)","data_referencia":"2026-05-14","granularidade":"regional (Santa Rosa) aplicado ao municipio","regiao":"Santa Rosa","derivado":true,"ha_plantado_estim":11680,"ha_colhido_estim":11680}},{"id":"palmeira_das_missoes","nome":"PALMEIRA DAS MISSÕES","ibge":4313706,"uf":"RS","lat":-27.9007,"lon":-53.3134,"area_soja_ha":110000,"clima":{"ibge":4313706,"nome":"PALMEIRA DAS MISSÕES","uf":"RS","lat":-27.9007,"lon":-53.3134,"atual":{"tmax":19.5,"tmin":8.4,"precip_mm":0.0,"prob_chuva":0,"weathercode":0,"tempo":"sol"},"previsao_7d":[{"data":"2026-07-15","tmax":19.5,"tmin":8.4,"precip_mm":0.0,"prob_chuva":0,"weathercode":0,"tempo":"sol","vento_kmh":18.6,"rajada_kmh":36.4,"vento_dir_graus":35,"et0_mm":2.71},{"data":"2026-07-16","tmax":23.9,"tmin":12.3,"precip_mm":0.0,"prob_chuva":0,"weathercode":0,"tempo":"sol","vento_kmh":22.5,"rajada_kmh":39.6,"vento_dir_graus":31,"et0_mm":3.71},{"data":"2026-07-17","tmax":25.0,"tmin":18.3,"precip_mm":0.0,"prob_chuva":2,"weathercode":1,"tempo":"parcial","vento_kmh":37.6,"rajada_kmh":67.3,"vento_dir_graus":16,"et0_mm":4.28},{"data":"2026-07-18","tmax":25.1,"tmin":18.3,"precip_mm":1.8,"prob_chuva":33,"weathercode":53,"tempo":"garoa","vento_kmh":29.5,"rajada_kmh":57.2,"vento_dir_graus":8,"et0_mm":4.41},{"data":"2026-07-19","tmax":24.5,"tmin":16.4,"precip_mm":35.7,"prob_chuva":59,"weathercode":95,"tempo":"trovoada","vento_kmh":22.0,"rajada_kmh":56.5,"vento_dir_graus":25,"et0_mm":2.57},{"data":"2026-07-20","tmax":24.5,"tmin":18.1,"precip_mm":12.2,"prob_chuva":50,"weathercode":95,"tempo":"trovoada","vento_kmh":29.8,"rajada_kmh":61.6,"vento_dir_graus":358,"et0_mm":3.92},{"data":"2026-07-21","tmax":19.8,"tmin":17.6,"precip_mm":72.2,"prob_chuva":63,"weathercode":95,"tempo":"trovoada","vento_kmh":13.3,"rajada_kmh":47.9,"vento_dir_graus":57,"et0_mm":0.96}],"fonte":"Open-Meteo","atualizado_em":"2026-07-15T05:07:38Z"},"colheita":{"pct_plantado":100.0,"pct_colhido":100.0,"area_soja_ha":110000,"fonte":"Emater/RS-Ascar (regional Santa Rosa, Fenasoja 30/04)","data_referencia":"2026-05-14","granularidade":"regional (Santa Rosa) aplicado ao municipio","regiao":"Santa Rosa","derivado":true,"ha_plantado_estim":110000,"ha_colhido_estim":110000}},{"id":"porto_lucena","nome":"PORTO LUCENA","ibge":4315008,"uf":"RS","lat":-27.8569,"lon":-55.01,"area_soja_ha":4500,"clima":{"ibge":4315008,"nome":"PORTO LUCENA","uf":"RS","lat":-27.8569,"lon":-55.01,"atual":{"tmax":24.2,"tmin":10.0,"precip_mm":0.0,"prob_chuva":0,"weathercode":0,"tempo":"sol"},"previsao_7d":[{"data":"2026-07-15","tmax":24.2,"tmin":10.0,"precip_mm":0.0,"prob_chuva":0,"weathercode":0,"tempo":"sol","vento_kmh":15.7,"rajada_kmh":31.3,"vento_dir_graus":49,"et0_mm":3.1},{"data":"2026-07-16","tmax":28.1,"tmin":13.6,"precip_mm":0.0,"prob_chuva":0,"weathercode":0,"tempo":"sol","vento_kmh":23.3,"rajada_kmh":48.6,"vento_dir_graus":41,"et0_mm":4.23},{"data":"2026-07-17","tmax":29.2,"tmin":22.5,"precip_mm":0.0,"prob_chuva":2,"weathercode":0,"tempo":"sol","vento_kmh":28.3,"rajada_kmh":58.7,"vento_dir_graus":25,"et0_mm":5.06},{"data":"2026-07-18","tmax":29.2,"tmin":19.4,"precip_mm":34.0,"prob_chuva":68,"weathercode":96,"tempo":"trovoada","vento_kmh":22.5,"rajada_kmh":50.8,"vento_dir_graus":11,"et0_mm":3.83},{"data":"2026-07-19","tmax":29.4,"tmin":18.9,"precip_mm":62.3,"prob_chuva":74,"weathercode":96,"tempo":"trovoada","vento_kmh":24.1,"rajada_kmh":53.3,"vento_dir_graus":31,"et0_mm":2.89},{"data":"2026-07-20","tmax":26.1,"tmin":19.5,"precip_mm":28.5,"prob_chuva":68,"weathercode":96,"tempo":"trovoada","vento_kmh":28.9,"rajada_kmh":73.1,"vento_dir_graus":9,"et0_mm":3.23},{"data":"2026-07-21","tmax":21.9,"tmin":17.5,"precip_mm":21.6,"prob_chuva":72,"weathercode":96,"tempo":"trovoada","vento_kmh":13.1,"rajada_kmh":36.0,"vento_dir_graus":147,"et0_mm":1.26}],"fonte":"Open-Meteo","atualizado_em":"2026-07-15T05:07:38Z"},"colheita":{"pct_plantado":100.0,"pct_colhido":100.0,"area_soja_ha":4500,"fonte":"Emater/RS-Ascar (regional Santa Rosa, Fenasoja 30/04)","data_referencia":"2026-05-14","granularidade":"regional (Santa Rosa) aplicado ao municipio","regiao":"Santa Rosa","derivado":true,"ha_plantado_estim":4500,"ha_colhido_estim":4500}},{"id":"porto_maua","nome":"PORTO MAUÁ","ibge":4315057,"uf":"RS","lat":-27.5796,"lon":-54.6657,"area_soja_ha":3300,"clima":{"ibge":4315057,"nome":"PORTO MAUÁ","uf":"RS","lat":-27.5796,"lon":-54.6657,"atual":{"tmax":24.3,"tmin":9.5,"precip_mm":0.0,"prob_chuva":0,"weathercode":0,"tempo":"sol"},"previsao_7d":[{"data":"2026-07-15","tmax":24.3,"tmin":9.5,"precip_mm":0.0,"prob_chuva":0,"weathercode":0,"tempo":"sol","vento_kmh":12.8,"rajada_kmh":28.1,"vento_dir_graus":64,"et0_mm":2.8},{"data":"2026-07-16","tmax":28.3,"tmin":12.8,"precip_mm":0.0,"prob_chuva":0,"weathercode":0,"tempo":"sol","vento_kmh":19.3,"rajada_kmh":39.2,"vento_dir_graus":53,"et0_mm":3.82},{"data":"2026-07-17","tmax":29.0,"tmin":22.0,"precip_mm":0.0,"prob_chuva":2,"weathercode":1,"tempo":"parcial","vento_kmh":29.1,"rajada_kmh":56.9,"vento_dir_graus":22,"et0_mm":4.78},{"data":"2026-07-18","tmax":29.1,"tmin":20.3,"precip_mm":4.2,"prob_chuva":55,"weathercode":95,"tempo":"trovoada","vento_kmh":21.5,"rajada_kmh":51.5,"vento_dir_graus":0,"et0_mm":4.09},{"data":"2026-07-19","tmax":29.1,"tmin":18.8,"precip_mm":41.4,"prob_chuva":69,"weathercode":96,"tempo":"trovoada","vento_kmh":23.4,"rajada_kmh":45.4,"vento_dir_graus":27,"et0_mm":3.28},{"data":"2026-07-20","tmax":25.7,"tmin":19.5,"precip_mm":10.5,"prob_chuva":65,"weathercode":95,"tempo":"trovoada","vento_kmh":28.4,"rajada_kmh":59.8,"vento_dir_graus":9,"et0_mm":3.95},{"data":"2026-07-21","tmax":22.3,"tmin":18.4,"precip_mm":31.6,"prob_chuva":66,"weathercode":95,"tempo":"trovoada","vento_kmh":12.8,"rajada_kmh":34.6,"vento_dir_graus":137,"et0_mm":1.24}],"fonte":"Open-Meteo","atualizado_em":"2026-07-15T05:07:38Z"},"colheita":{"pct_plantado":100.0,"pct_colhido":100.0,"area_soja_ha":3300,"fonte":"Emater/RS-Ascar (regional Santa Rosa, Fenasoja 30/04)","data_referencia":"2026-05-14","granularidade":"regional (Santa Rosa) aplicado ao municipio","regiao":"Santa Rosa","derivado":true,"ha_plantado_estim":3300,"ha_colhido_estim":3300}},{"id":"redentora","nome":"REDENTORA","ibge":4315404,"uf":"RS","lat":-27.664,"lon":-53.6407,"area_soja_ha":13000,"clima":{"ibge":4315404,"nome":"REDENTORA","uf":"RS","lat":-27.664,"lon":-53.6407,"atual":{"tmax":20.5,"tmin":9.4,"precip_mm":0.0,"prob_chuva":0,"weathercode":0,"tempo":"sol"},"previsao_7d":[{"data":"2026-07-15","tmax":20.5,"tmin":9.4,"precip_mm":0.0,"prob_chuva":0,"weathercode":0,"tempo":"sol","vento_kmh":18.1,"rajada_kmh":33.5,"vento_dir_graus":45,"et0_mm":2.88},{"data":"2026-07-16","tmax":24.6,"tmin":12.8,"precip_mm":0.0,"prob_chuva":0,"weathercode":0,"tempo":"sol","vento_kmh":21.7,"rajada_kmh":39.6,"vento_dir_graus":43,"et0_mm":3.69},{"data":"2026-07-17","tmax":25.8,"tmin":19.1,"precip_mm":0.0,"prob_chuva":2,"weathercode":1,"tempo":"parcial","vento_kmh":33.2,"rajada_kmh":60.5,"vento_dir_graus":20,"et0_mm":4.44},{"data":"2026-07-18","tmax":26.1,"tmin":19.6,"precip_mm":3.0,"prob_chuva":41,"weathercode":95,"tempo":"trovoada","vento_kmh":29.9,"rajada_kmh":57.2,"vento_dir_graus":13,"et0_mm":4.62},{"data":"2026-07-19","tmax":25.4,"tmin":17.4,"precip_mm":27.6,"prob_chuva":65,"weathercode":96,"tempo":"trovoada","vento_kmh":23.0,"rajada_kmh":53.3,"vento_dir_graus":33,"et0_mm":2.86},{"data":"2026-07-20","tmax":24.7,"tmin":18.0,"precip_mm":19.6,"prob_chuva":60,"weathercode":95,"tempo":"trovoada","vento_kmh":27.3,"rajada_kmh":62.6,"vento_dir_graus":6,"et0_mm":3.77},{"data":"2026-07-21","tmax":20.2,"tmin":17.9,"precip_mm":90.8,"prob_chuva":71,"weathercode":96,"tempo":"trovoada","vento_kmh":10.7,"rajada_kmh":42.8,"vento_dir_graus":47,"et0_mm":1.02}],"fonte":"Open-Meteo","atualizado_em":"2026-07-15T05:07:38Z"},"colheita":{"pct_plantado":100.0,"pct_colhido":100.0,"area_soja_ha":13000,"fonte":"Emater/RS-Ascar (regional Santa Rosa, Fenasoja 30/04)","data_referencia":"2026-05-14","granularidade":"regional (Santa Rosa) aplicado ao municipio","regiao":"Santa Rosa","derivado":true,"ha_plantado_estim":13000,"ha_colhido_estim":13000}},{"id":"santa_rosa","nome":"SANTA ROSA","ibge":4317202,"uf":"RS","lat":-27.8702,"lon":-54.4796,"area_soja_ha":20064,"clima":{"ibge":4317202,"nome":"SANTA ROSA","uf":"RS","lat":-27.8702,"lon":-54.4796,"atual":{"tmax":21.9,"tmin":10.1,"precip_mm":0.0,"prob_chuva":0,"weathercode":0,"tempo":"sol"},"previsao_7d":[{"data":"2026-07-15","tmax":21.9,"tmin":10.1,"precip_mm":0.0,"prob_chuva":0,"weathercode":0,"tempo":"sol","vento_kmh":17.2,"rajada_kmh":34.2,"vento_dir_graus":47,"et0_mm":2.93},{"data":"2026-07-16","tmax":26.4,"tmin":14.2,"precip_mm":0.0,"prob_chuva":2,"weathercode":0,"tempo":"sol","vento_kmh":22.1,"rajada_kmh":40.0,"vento_dir_graus":42,"et0_mm":3.97},{"data":"2026-07-17","tmax":28.2,"tmin":21.1,"precip_mm":0.0,"prob_chuva":4,"weathercode":0,"tempo":"sol","vento_kmh":33.2,"rajada_kmh":64.8,"vento_dir_graus":17,"et0_mm":4.94},{"data":"2026-07-18","tmax":28.2,"tmin":19.1,"precip_mm":20.9,"prob_chuva":67,"weathercode":95,"tempo":"trovoada","vento_kmh":26.1,"rajada_kmh":59.8,"vento_dir_graus":5,"et0_mm":4.22},{"data":"2026-07-19","tmax":27.9,"tmin":18.8,"precip_mm":76.1,"prob_chuva":77,"weathercode":95,"tempo":"trovoada","vento_kmh":24.6,"rajada_kmh":50.0,"vento_dir_graus":33,"et0_mm":2.99},{"data":"2026-07-20","tmax":24.5,"tmin":19.1,"precip_mm":29.1,"prob_chuva":64,"weathercode":95,"tempo":"trovoada","vento_kmh":31.8,"rajada_kmh":64.4,"vento_dir_graus":9,"et0_mm":3.81},{"data":"2026-07-21","tmax":21.2,"tmin":17.9,"precip_mm":28.2,"prob_chuva":67,"weathercode":96,"tempo":"trovoada","vento_kmh":17.0,"rajada_kmh":37.4,"vento_dir_graus":144,"et0_mm":1.23}],"fonte":"Open-Meteo","atualizado_em":"2026-07-15T05:07:38Z"},"colheita":{"pct_plantado":100.0,"pct_colhido":100.0,"area_soja_ha":20064,"fonte":"Emater/RS-Ascar (regional Santa Rosa, Fenasoja 30/04)","data_referencia":"2026-05-14","granularidade":"regional (Santa Rosa) aplicado ao municipio","regiao":"Santa Rosa","derivado":true,"ha_plantado_estim":20064,"ha_colhido_estim":20064}},{"id":"santo_augusto","nome":"SANTO AUGUSTO","ibge":4317806,"uf":"RS","lat":-27.8526,"lon":-53.7776,"area_soja_ha":33300,"clima":{"ibge":4317806,"nome":"SANTO AUGUSTO","uf":"RS","lat":-27.8526,"lon":-53.7776,"atual":{"tmax":20.5,"tmin":9.9,"precip_mm":0.0,"prob_chuva":0,"weathercode":0,"tempo":"sol"},"previsao_7d":[{"data":"2026-07-15","tmax":20.5,"tmin":9.9,"precip_mm":0.0,"prob_chuva":0,"weathercode":0,"tempo":"sol","vento_kmh":21.2,"rajada_kmh":35.3,"vento_dir_graus":41,"et0_mm":3.01},{"data":"2026-07-16","tmax":24.7,"tmin":13.6,"precip_mm":0.0,"prob_chuva":0,"weathercode":0,"tempo":"sol","vento_kmh":26.5,"rajada_kmh":45.7,"vento_dir_graus":38,"et0_mm":4.08},{"data":"2026-07-17","tmax":25.9,"tmin":19.8,"precip_mm":0.0,"prob_chuva":2,"weathercode":1,"tempo":"parcial","vento_kmh":34.7,"rajada_kmh":62.6,"vento_dir_graus":18,"et0_mm":4.73},{"data":"2026-07-18","tmax":26.7,"tmin":19.1,"precip_mm":8.6,"prob_chuva":41,"weathercode":96,"tempo":"trovoada","vento_kmh":31.0,"rajada_kmh":65.9,"vento_dir_graus":5,"et0_mm":4.38},{"data":"2026-07-19","tmax":25.3,"tmin":17.7,"precip_mm":37.6,"prob_chuva":65,"weathercode":95,"tempo":"trovoada","vento_kmh":28.8,"rajada_kmh":47.9,"vento_dir_graus":27,"et0_mm":2.88},{"data":"2026-07-20","tmax":24.5,"tmin":18.4,"precip_mm":15.6,"prob_chuva":60,"weathercode":95,"tempo":"trovoada","vento_kmh":31.4,"rajada_kmh":76.7,"vento_dir_graus":7,"et0_mm":3.79},{"data":"2026-07-21","tmax":19.7,"tmin":18.3,"precip_mm":45.2,"prob_chuva":71,"weathercode":96,"tempo":"trovoada","vento_kmh":15.2,"rajada_kmh":47.2,"vento_dir_graus":103,"et0_mm":0.95}],"fonte":"Open-Meteo","atualizado_em":"2026-07-15T05:07:38Z"},"colheita":{"pct_plantado":100.0,"pct_colhido":100.0,"area_soja_ha":33300,"fonte":"Emater/RS-Ascar (regional Santa Rosa, Fenasoja 30/04)","data_referencia":"2026-05-14","granularidade":"regional (Santa Rosa) aplicado ao municipio","regiao":"Santa Rosa","derivado":true,"ha_plantado_estim":33300,"ha_colhido_estim":33300}},{"id":"santo_cristo","nome":"SANTO CRISTO","ibge":4317905,"uf":"RS","lat":-27.8263,"lon":-54.662,"area_soja_ha":7028,"clima":{"ibge":4317905,"nome":"SANTO CRISTO","uf":"RS","lat":-27.8263,"lon":-54.662,"atual":{"tmax":22.2,"tmin":9.6,"precip_mm":0.0,"prob_chuva":0,"weathercode":0,"tempo":"sol"},"previsao_7d":[{"data":"2026-07-15","tmax":22.2,"tmin":9.6,"precip_mm":0.0,"prob_chuva":0,"weathercode":0,"tempo":"sol","vento_kmh":18.6,"rajada_kmh":36.0,"vento_dir_graus":46,"et0_mm":2.93},{"data":"2026-07-16","tmax":26.8,"tmin":14.2,"precip_mm":0.0,"prob_chuva":0,"weathercode":0,"tempo":"sol","vento_kmh":21.8,"rajada_kmh":42.5,"vento_dir_graus":44,"et0_mm":4.05},{"data":"2026-07-17","tmax":28.2,"tmin":21.3,"precip_mm":0.0,"prob_chuva":2,"weathercode":1,"tempo":"parcial","vento_kmh":32.6,"rajada_kmh":66.6,"vento_dir_graus":20,"et0_mm":4.83},{"data":"2026-07-18","tmax":28.1,"tmin":19.1,"precip_mm":20.6,"prob_chuva":67,"weathercode":96,"tempo":"trovoada","vento_kmh":25.1,"rajada_kmh":58.7,"vento_dir_graus":6,"et0_mm":4.04},{"data":"2026-07-19","tmax":28.0,"tmin":18.8,"precip_mm":77.3,"prob_chuva":78,"weathercode":96,"tempo":"trovoada","vento_kmh":23.8,"rajada_kmh":50.8,"vento_dir_graus":30,"et0_mm":3.07},{"data":"2026-07-20","tmax":24.7,"tmin":19.1,"precip_mm":21.0,"prob_chuva":68,"weathercode":95,"tempo":"trovoada","vento_kmh":30.6,"rajada_kmh":67.3,"vento_dir_graus":9,"et0_mm":3.67},{"data":"2026-07-21","tmax":21.5,"tmin":17.7,"precip_mm":33.0,"prob_chuva":72,"weathercode":96,"tempo":"trovoada","vento_kmh":15.4,"rajada_kmh":39.2,"vento_dir_graus":146,"et0_mm":1.24}],"fonte":"Open-Meteo","atualizado_em":"2026-07-15T05:07:38Z"},"colheita":{"pct_plantado":100.0,"pct_colhido":100.0,"area_soja_ha":7028,"fonte":"Emater/RS-Ascar (regional Santa Rosa, Fenasoja 30/04)","data_referencia":"2026-05-14","granularidade":"regional (Santa Rosa) aplicado ao municipio","regiao":"Santa Rosa","derivado":true,"ha_plantado_estim":7028,"ha_colhido_estim":7028}},{"id":"sao_jose_do_inhacora","nome":"SÃO JOSÉ DO INHACORÁ","ibge":4318499,"uf":"RS","lat":-27.7251,"lon":-54.1275,"area_soja_ha":2200,"clima":{"ibge":4318499,"nome":"SÃO JOSÉ DO INHACORÁ","uf":"RS","lat":-27.7251,"lon":-54.1275,"atual":{"tmax":22.4,"tmin":10.5,"precip_mm":0.0,"prob_chuva":0,"weathercode":0,"tempo":"sol"},"previsao_7d":[{"data":"2026-07-15","tmax":22.4,"tmin":10.5,"precip_mm":0.0,"prob_chuva":0,"weathercode":0,"tempo":"sol","vento_kmh":15.6,"rajada_kmh":30.6,"vento_dir_graus":50,"et0_mm":3.04},{"data":"2026-07-16","tmax":26.6,"tmin":14.3,"precip_mm":0.0,"prob_chuva":2,"weathercode":0,"tempo":"sol","vento_kmh":22.4,"rajada_kmh":42.5,"vento_dir_graus":45,"et0_mm":4.08},{"data":"2026-07-17","tmax":28.4,"tmin":21.8,"precip_mm":0.0,"prob_chuva":4,"weathercode":1,"tempo":"parcial","vento_kmh":28.5,"rajada_kmh":58.0,"vento_dir_graus":20,"et0_mm":5.09},{"data":"2026-07-18","tmax":28.7,"tmin":19.8,"precip_mm":8.6,"prob_chuva":59,"weathercode":95,"tempo":"trovoada","vento_kmh":29.0,"rajada_kmh":64.4,"vento_dir_graus":3,"et0_mm":4.59},{"data":"2026-07-19","tmax":27.6,"tmin":18.9,"precip_mm":28.3,"prob_chuva":71,"weathercode":95,"tempo":"trovoada","vento_kmh":27.6,"rajada_kmh":52.2,"vento_dir_graus":32,"et0_mm":3.18},{"data":"2026-07-20","tmax":26.4,"tmin":19.2,"precip_mm":19.4,"prob_chuva":64,"weathercode":95,"tempo":"trovoada","vento_kmh":30.6,"rajada_kmh":71.6,"vento_dir_graus":9,"et0_mm":4.24},{"data":"2026-07-21","tmax":21.2,"tmin":19.2,"precip_mm":37.4,"prob_chuva":65,"weathercode":95,"tempo":"trovoada","vento_kmh":10.4,"rajada_kmh":36.7,"vento_dir_graus":108,"et0_mm":0.99}],"fonte":"Open-Meteo","atualizado_em":"2026-07-15T05:07:38Z"},"colheita":{"pct_plantado":100.0,"pct_colhido":100.0,"area_soja_ha":2200,"fonte":"Emater/RS-Ascar (regional Santa Rosa, Fenasoja 30/04)","data_referencia":"2026-05-14","granularidade":"regional (Santa Rosa) aplicado ao municipio","regiao":"Santa Rosa","derivado":true,"ha_plantado_estim":2200,"ha_colhido_estim":2200}},{"id":"sao_martinho","nome":"SÃO MARTINHO","ibge":4319109,"uf":"RS","lat":-27.7112,"lon":-53.9699,"area_soja_ha":12100,"clima":{"ibge":4319109,"nome":"SÃO MARTINHO","uf":"RS","lat":-27.7112,"lon":-53.9699,"atual":{"tmax":21.7,"tmin":10.6,"precip_mm":0.0,"prob_chuva":0,"weathercode":0,"tempo":"sol"},"previsao_7d":[{"data":"2026-07-15","tmax":21.7,"tmin":10.6,"precip_mm":0.0,"prob_chuva":0,"weathercode":0,"tempo":"sol","vento_kmh":21.3,"rajada_kmh":37.8,"vento_dir_graus":50,"et0_mm":3.21},{"data":"2026-07-16","tmax":25.7,"tmin":14.6,"precip_mm":0.0,"prob_chuva":0,"weathercode":0,"tempo":"sol","vento_kmh":25.9,"rajada_kmh":47.2,"vento_dir_graus":45,"et0_mm":4.3},{"data":"2026-07-17","tmax":27.3,"tmin":20.9,"precip_mm":0.0,"prob_chuva":2,"weathercode":1,"tempo":"parcial","vento_kmh":32.1,"rajada_kmh":60.8,"vento_dir_graus":23,"et0_mm":4.99},{"data":"2026-07-18","tmax":27.9,"tmin":19.7,"precip_mm":9.9,"prob_chuva":46,"weathercode":95,"tempo":"trovoada","vento_kmh":29.2,"rajada_kmh":64.8,"vento_dir_graus":7,"et0_mm":4.58},{"data":"2026-07-19","tmax":26.6,"tmin":18.6,"precip_mm":17.4,"prob_chuva":71,"weathercode":96,"tempo":"trovoada","vento_kmh":28.7,"rajada_kmh":51.5,"vento_dir_graus":32,"et0_mm":3.12},{"data":"2026-07-20","tmax":26.0,"tmin":19.0,"precip_mm":19.6,"prob_chuva":63,"weathercode":95,"tempo":"trovoada","vento_kmh":32.4,"rajada_kmh":70.9,"vento_dir_graus":7,"et0_mm":4.3},{"data":"2026-07-21","tmax":21.1,"tmin":18.9,"precip_mm":35.0,"prob_chuva":67,"weathercode":95,"tempo":"trovoada","vento_kmh":13.1,"rajada_kmh":41.0,"vento_dir_graus":88,"et0_mm":1.04}],"fonte":"Open-Meteo","atualizado_em":"2026-07-15T05:07:38Z"},"colheita":{"pct_plantado":100.0,"pct_colhido":100.0,"area_soja_ha":12100,"fonte":"Emater/RS-Ascar (regional Santa Rosa, Fenasoja 30/04)","data_referencia":"2026-05-14","granularidade":"regional (Santa Rosa) aplicado ao municipio","regiao":"Santa Rosa","derivado":true,"ha_plantado_estim":12100,"ha_colhido_estim":12100}},{"id":"sao_valerio_do_sul","nome":"SÃO VALÉRIO DO SUL","ibge":4319737,"uf":"RS","lat":-27.7906,"lon":-53.9368,"area_soja_ha":5832,"clima":{"ibge":4319737,"nome":"SÃO VALÉRIO DO SUL","uf":"RS","lat":-27.7906,"lon":-53.9368,"atual":{"tmax":21.2,"tmin":10.4,"precip_mm":0.0,"prob_chuva":0,"weathercode":0,"tempo":"sol"},"previsao_7d":[{"data":"2026-07-15","tmax":21.2,"tmin":10.4,"precip_mm":0.0,"prob_chuva":0,"weathercode":0,"tempo":"sol","vento_kmh":20.6,"rajada_kmh":35.3,"vento_dir_graus":46,"et0_mm":3.12},{"data":"2026-07-16","tmax":25.3,"tmin":14.3,"precip_mm":0.0,"prob_chuva":0,"weathercode":0,"tempo":"sol","vento_kmh":26.0,"rajada_kmh":45.7,"vento_dir_graus":42,"et0_mm":4.19},{"data":"2026-07-17","tmax":26.6,"tmin":20.5,"precip_mm":0.0,"prob_chuva":2,"weathercode":1,"tempo":"parcial","vento_kmh":32.8,"rajada_kmh":59.8,"vento_dir_graus":20,"et0_mm":4.86},{"data":"2026-07-18","tmax":27.5,"tmin":19.4,"precip_mm":8.8,"prob_chuva":46,"weathercode":96,"tempo":"trovoada","vento_kmh":30.6,"rajada_kmh":60.5,"vento_dir_graus":5,"et0_mm":4.48},{"data":"2026-07-19","tmax":26.2,"tmin":18.4,"precip_mm":25.7,"prob_chuva":71,"weathercode":96,"tempo":"trovoada","vento_kmh":28.9,"rajada_kmh":50.0,"vento_dir_graus":30,"et0_mm":3.02},{"data":"2026-07-20","tmax":25.6,"tmin":18.9,"precip_mm":18.6,"prob_chuva":63,"weathercode":95,"tempo":"trovoada","vento_kmh":32.6,"rajada_kmh":72.7,"vento_dir_graus":6,"et0_mm":4.11},{"data":"2026-07-21","tmax":20.5,"tmin":18.9,"precip_mm":37.8,"prob_chuva":67,"weathercode":96,"tempo":"trovoada","vento_kmh":14.7,"rajada_kmh":40.3,"vento_dir_graus":103,"et0_mm":0.99}],"fonte":"Open-Meteo","atualizado_em":"2026-07-15T05:07:38Z"},"colheita":{"pct_plantado":100.0,"pct_colhido":100.0,"area_soja_ha":5832,"fonte":"Emater/RS-Ascar (regional Santa Rosa, Fenasoja 30/04)","data_referencia":"2026-05-14","granularidade":"regional (Santa Rosa) aplicado ao municipio","regiao":"Santa Rosa","derivado":true,"ha_plantado_estim":5832,"ha_colhido_estim":5832}},{"id":"sede_nova","nome":"SEDE NOVA","ibge":4320230,"uf":"RS","lat":-27.6367,"lon":-53.9493,"area_soja_ha":6500,"clima":{"ibge":4320230,"nome":"SEDE NOVA","uf":"RS","lat":-27.6367,"lon":-53.9493,"atual":{"tmax":21.1,"tmin":9.9,"precip_mm":0.0,"prob_chuva":0,"weathercode":0,"tempo":"sol"},"previsao_7d":[{"data":"2026-07-15","tmax":21.1,"tmin":9.9,"precip_mm":0.0,"prob_chuva":0,"weathercode":0,"tempo":"sol","vento_kmh":23.1,"rajada_kmh":39.2,"vento_dir_graus":51,"et0_mm":3.13},{"data":"2026-07-16","tmax":25.3,"tmin":13.9,"precip_mm":0.0,"prob_chuva":0,"weathercode":0,"tempo":"sol","vento_kmh":26.5,"rajada_kmh":45.7,"vento_dir_graus":46,"et0_mm":4.18},{"data":"2026-07-17","tmax":26.5,"tmin":20.3,"precip_mm":0.0,"prob_chuva":2,"weathercode":0,"tempo":"sol","vento_kmh":33.4,"rajada_kmh":59.4,"vento_dir_graus":26,"et0_mm":4.82},{"data":"2026-07-18","tmax":27.4,"tmin":19.9,"precip_mm":6.0,"prob_chuva":46,"weathercode":96,"tempo":"trovoada","vento_kmh":29.2,"rajada_kmh":60.1,"vento_dir_graus":11,"et0_mm":4.55},{"data":"2026-07-19","tmax":26.1,"tmin":18.2,"precip_mm":25.2,"prob_chuva":71,"weathercode":96,"tempo":"trovoada","vento_kmh":26.6,"rajada_kmh":47.9,"vento_dir_graus":33,"et0_mm":3.12},{"data":"2026-07-20","tmax":25.5,"tmin":18.8,"precip_mm":20.4,"prob_chuva":63,"weathercode":95,"tempo":"trovoada","vento_kmh":32.2,"rajada_kmh":73.1,"vento_dir_graus":8,"et0_mm":4.17},{"data":"2026-07-21","tmax":20.9,"tmin":18.7,"precip_mm":56.2,"prob_chuva":67,"weathercode":96,"tempo":"trovoada","vento_kmh":14.2,"rajada_kmh":36.7,"vento_dir_graus":57,"et0_mm":1.09}],"fonte":"Open-Meteo","atualizado_em":"2026-07-15T05:07:38Z"},"colheita":{"pct_plantado":100.0,"pct_colhido":100.0,"area_soja_ha":6500,"fonte":"Emater/RS-Ascar (regional Santa Rosa, Fenasoja 30/04)","data_referencia":"2026-05-14","granularidade":"regional (Santa Rosa) aplicado ao municipio","regiao":"Santa Rosa","derivado":true,"ha_plantado_estim":6500,"ha_colhido_estim":6500}},{"id":"senador_salgado_filho","nome":"SENADOR SALGADO FILHO","ibge":4320321,"uf":"RS","lat":-28.025,"lon":-54.5507,"area_soja_ha":8740,"clima":{"ibge":4320321,"nome":"SENADOR SALGADO FILHO","uf":"RS","lat":-28.025,"lon":-54.5507,"atual":{"tmax":21.4,"tmin":10.4,"precip_mm":0.0,"prob_chuva":0,"weathercode":0,"tempo":"sol"},"previsao_7d":[{"data":"2026-07-15","tmax":21.4,"tmin":10.4,"precip_mm":0.0,"prob_chuva":0,"weathercode":0,"tempo":"sol","vento_kmh":24.1,"rajada_kmh":42.8,"vento_dir_graus":35,"et0_mm":3.16},{"data":"2026-07-16","tmax":25.7,"tmin":14.6,"precip_mm":0.0,"prob_chuva":0,"weathercode":0,"tempo":"sol","vento_kmh":26.2,"rajada_kmh":46.4,"vento_dir_graus":38,"et0_mm":4.26},{"data":"2026-07-17","tmax":27.6,"tmin":20.6,"precip_mm":0.0,"prob_chuva":2,"weathercode":0,"tempo":"sol","vento_kmh":37.4,"rajada_kmh":69.1,"vento_dir_graus":17,"et0_mm":4.97},{"data":"2026-07-18","tmax":27.5,"tmin":19.3,"precip_mm":32.8,"prob_chuva":74,"weathercode":96,"tempo":"trovoada","vento_kmh":29.7,"rajada_kmh":62.6,"vento_dir_graus":5,"et0_mm":4.18},{"data":"2026-07-19","tmax":26.8,"tmin":18.7,"precip_mm":53.2,"prob_chuva":81,"weathercode":95,"tempo":"trovoada","vento_kmh":29.9,"rajada_kmh":54.4,"vento_dir_graus":29,"et0_mm":2.95},{"data":"2026-07-20","tmax":24.0,"tmin":19.1,"precip_mm":18.8,"prob_chuva":72,"weathercode":95,"tempo":"trovoada","vento_kmh":35.0,"rajada_kmh":72.4,"vento_dir_graus":9,"et0_mm":3.94},{"data":"2026-07-21","tmax":20.6,"tmin":17.0,"precip_mm":48.4,"prob_chuva":76,"weathercode":96,"tempo":"trovoada","vento_kmh":17.9,"rajada_kmh":44.3,"vento_dir_graus":141,"et0_mm":1.12}],"fonte":"Open-Meteo","atualizado_em":"2026-07-15T05:07:38Z"},"colheita":{"pct_plantado":100.0,"pct_colhido":100.0,"area_soja_ha":8740,"fonte":"Emater/RS-Ascar (regional Santa Rosa, Fenasoja 30/04)","data_referencia":"2026-05-14","granularidade":"regional (Santa Rosa) aplicado ao municipio","regiao":"Santa Rosa","derivado":true,"ha_plantado_estim":8740,"ha_colhido_estim":8740}},{"id":"tenente_portela","nome":"TENENTE PORTELA","ibge":4321402,"uf":"RS","lat":-27.3711,"lon":-53.7585,"area_soja_ha":15000,"clima":{"ibge":4321402,"nome":"TENENTE PORTELA","uf":"RS","lat":-27.3711,"lon":-53.7585,"atual":{"tmax":21.0,"tmin":8.3,"precip_mm":0.0,"prob_chuva":0,"weathercode":0,"tempo":"sol"},"previsao_7d":[{"data":"2026-07-15","tmax":21.0,"tmin":8.3,"precip_mm":0.0,"prob_chuva":0,"weathercode":0,"tempo":"sol","vento_kmh":15.7,"rajada_kmh":30.6,"vento_dir_graus":54,"et0_mm":2.72},{"data":"2026-07-16","tmax":25.1,"tmin":12.6,"precip_mm":0.0,"prob_chuva":0,"weathercode":0,"tempo":"sol","vento_kmh":19.4,"rajada_kmh":37.4,"vento_dir_graus":47,"et0_mm":3.65},{"data":"2026-07-17","tmax":26.0,"tmin":19.7,"precip_mm":0.0,"prob_chuva":2,"weathercode":0,"tempo":"sol","vento_kmh":28.9,"rajada_kmh":56.5,"vento_dir_graus":25,"et0_mm":4.5},{"data":"2026-07-18","tmax":26.9,"tmin":19.0,"precip_mm":3.8,"prob_chuva":24,"weathercode":95,"tempo":"trovoada","vento_kmh":26.1,"rajada_kmh":54.0,"vento_dir_graus":21,"et0_mm":4.34},{"data":"2026-07-19","tmax":26.2,"tmin":17.5,"precip_mm":14.5,"prob_chuva":41,"weathercode":95,"tempo":"trovoada","vento_kmh":21.3,"rajada_kmh":46.8,"vento_dir_graus":31,"et0_mm":3.08},{"data":"2026-07-20","tmax":25.8,"tmin":18.5,"precip_mm":21.4,"prob_chuva":50,"weathercode":95,"tempo":"trovoada","vento_kmh":24.7,"rajada_kmh":64.1,"vento_dir_graus":14,"et0_mm":3.78},{"data":"2026-07-21","tmax":20.0,"tmin":17.9,"precip_mm":73.8,"prob_chuva":69,"weathercode":96,"tempo":"trovoada","vento_kmh":8.0,"rajada_kmh":45.7,"vento_dir_graus":73,"et0_mm":0.87}],"fonte":"Open-Meteo","atualizado_em":"2026-07-15T05:07:38Z"},"colheita":{"pct_plantado":100.0,"pct_colhido":100.0,"area_soja_ha":15000,"fonte":"Emater/RS-Ascar (regional Santa Rosa, Fenasoja 30/04)","data_referencia":"2026-05-14","granularidade":"regional (Santa Rosa) aplicado ao municipio","regiao":"Santa Rosa","derivado":true,"ha_plantado_estim":15000,"ha_colhido_estim":15000}},{"id":"tiradentes_do_sul","nome":"TIRADENTES DO SUL","ibge":4321477,"uf":"RS","lat":-27.4022,"lon":-54.0814,"area_soja_ha":6000,"clima":{"ibge":4321477,"nome":"TIRADENTES DO SUL","uf":"RS","lat":-27.4022,"lon":-54.0814,"atual":{"tmax":23.0,"tmin":9.1,"precip_mm":0.0,"prob_chuva":0,"weathercode":0,"tempo":"sol"},"previsao_7d":[{"data":"2026-07-15","tmax":23.0,"tmin":9.1,"precip_mm":0.0,"prob_chuva":0,"weathercode":0,"tempo":"sol","vento_kmh":16.6,"rajada_kmh":34.2,"vento_dir_graus":56,"et0_mm":2.99},{"data":"2026-07-16","tmax":27.1,"tmin":13.4,"precip_mm":0.0,"prob_chuva":0,"weathercode":0,"tempo":"sol","vento_kmh":20.9,"rajada_kmh":39.2,"vento_dir_graus":51,"et0_mm":4.08},{"data":"2026-07-17","tmax":28.2,"tmin":20.2,"precip_mm":0.0,"prob_chuva":2,"weathercode":1,"tempo":"parcial","vento_kmh":27.6,"rajada_kmh":53.6,"vento_dir_graus":33,"et0_mm":4.86},{"data":"2026-07-18","tmax":28.2,"tmin":19.3,"precip_mm":4.0,"prob_chuva":41,"weathercode":95,"tempo":"trovoada","vento_kmh":23.5,"rajada_kmh":51.5,"vento_dir_graus":25,"et0_mm":4.61},{"data":"2026-07-19","tmax":27.8,"tmin":18.0,"precip_mm":10.4,"prob_chuva":51,"weathercode":95,"tempo":"trovoada","vento_kmh":23.6,"rajada_kmh":53.3,"vento_dir_graus":38,"et0_mm":3.4},{"data":"2026-07-20","tmax":26.2,"tmin":18.9,"precip_mm":15.1,"prob_chuva":60,"weathercode":95,"tempo":"trovoada","vento_kmh":26.6,"rajada_kmh":67.3,"vento_dir_graus":10,"et0_mm":3.95},{"data":"2026-07-21","tmax":20.9,"tmin":18.4,"precip_mm":56.0,"prob_chuva":67,"weathercode":95,"tempo":"trovoada","vento_kmh":12.3,"rajada_kmh":37.8,"vento_dir_graus":36,"et0_mm":1.06}],"fonte":"Open-Meteo","atualizado_em":"2026-07-15T05:07:38Z"},"colheita":{"pct_plantado":100.0,"pct_colhido":100.0,"area_soja_ha":6000,"fonte":"Emater/RS-Ascar (regional Santa Rosa, Fenasoja 30/04)","data_referencia":"2026-05-14","granularidade":"regional (Santa Rosa) aplicado ao municipio","regiao":"Santa Rosa","derivado":true,"ha_plantado_estim":6000,"ha_colhido_estim":6000}},{"id":"tres_de_maio","nome":"TRÊS DE MAIO","ibge":4321808,"uf":"RS","lat":-27.78,"lon":-54.2357,"area_soja_ha":21030,"clima":{"ibge":4321808,"nome":"TRÊS DE MAIO","uf":"RS","lat":-27.78,"lon":-54.2357,"atual":{"tmax":21.7,"tmin":9.5,"precip_mm":0.0,"prob_chuva":0,"weathercode":0,"tempo":"sol"},"previsao_7d":[{"data":"2026-07-15","tmax":21.7,"tmin":9.5,"precip_mm":0.0,"prob_chuva":0,"weathercode":0,"tempo":"sol","vento_kmh":15.2,"rajada_kmh":29.9,"vento_dir_graus":46,"et0_mm":2.79},{"data":"2026-07-16","tmax":26.0,"tmin":13.5,"precip_mm":0.0,"prob_chuva":2,"weathercode":0,"tempo":"sol","vento_kmh":21.4,"rajada_kmh":37.4,"vento_dir_graus":44,"et0_mm":3.74},{"data":"2026-07-17","tmax":27.9,"tmin":20.9,"precip_mm":0.0,"prob_chuva":4,"weathercode":1,"tempo":"parcial","vento_kmh":32.1,"rajada_kmh":58.3,"vento_dir_graus":19,"et0_mm":4.8},{"data":"2026-07-18","tmax":27.9,"tmin":19.4,"precip_mm":13.0,"prob_chuva":59,"weathercode":95,"tempo":"trovoada","vento_kmh":29.6,"rajada_kmh":59.4,"vento_dir_graus":5,"et0_mm":4.3},{"data":"2026-07-19","tmax":26.5,"tmin":18.6,"precip_mm":69.5,"prob_chuva":71,"weathercode":96,"tempo":"trovoada","vento_kmh":27.9,"rajada_kmh":47.9,"vento_dir_graus":32,"et0_mm":2.95},{"data":"2026-07-20","tmax":25.4,"tmin":19.1,"precip_mm":32.8,"prob_chuva":64,"weathercode":96,"tempo":"trovoada","vento_kmh":31.9,"rajada_kmh":74.5,"vento_dir_graus":7,"et0_mm":3.87},{"data":"2026-07-21","tmax":21.2,"tmin":18.8,"precip_mm":47.2,"prob_chuva":65,"weathercode":96,"tempo":"trovoada","vento_kmh":15.4,"rajada_kmh":38.9,"vento_dir_graus":131,"et0_mm":1.16}],"fonte":"Open-Meteo","atualizado_em":"2026-07-15T05:07:38Z"},"colheita":{"pct_plantado":100.0,"pct_colhido":100.0,"area_soja_ha":21030,"fonte":"Emater/RS-Ascar (regional Santa Rosa, Fenasoja 30/04)","data_referencia":"2026-05-14","granularidade":"regional (Santa Rosa) aplicado ao municipio","regiao":"Santa Rosa","derivado":true,"ha_plantado_estim":21030,"ha_colhido_estim":21030}},{"id":"tres_passos","nome":"TRÊS PASSOS","ibge":4321907,"uf":"RS","lat":-27.4555,"lon":-53.9296,"area_soja_ha":9000,"clima":{"ibge":4321907,"nome":"TRÊS PASSOS","uf":"RS","lat":-27.4555,"lon":-53.9296,"atual":{"tmax":22.3,"tmin":10.0,"precip_mm":0.0,"prob_chuva":0,"weathercode":0,"tempo":"sol"},"previsao_7d":[{"data":"2026-07-15","tmax":22.3,"tmin":10.0,"precip_mm":0.0,"prob_chuva":0,"weathercode":0,"tempo":"sol","vento_kmh":16.8,"rajada_kmh":34.6,"vento_dir_graus":58,"et0_mm":3.12},{"data":"2026-07-16","tmax":26.3,"tmin":14.2,"precip_mm":0.0,"prob_chuva":0,"weathercode":0,"tempo":"sol","vento_kmh":21.7,"rajada_kmh":42.5,"vento_dir_graus":51,"et0_mm":4.07},{"data":"2026-07-17","tmax":27.8,"tmin":20.8,"precip_mm":0.0,"prob_chuva":2,"weathercode":0,"tempo":"sol","vento_kmh":28.1,"rajada_kmh":58.3,"vento_dir_graus":27,"et0_mm":4.87},{"data":"2026-07-18","tmax":28.5,"tmin":21.0,"precip_mm":4.2,"prob_chuva":41,"weathercode":95,"tempo":"trovoada","vento_kmh":24.7,"rajada_kmh":56.2,"vento_dir_graus":19,"et0_mm":4.77},{"data":"2026-07-19","tmax":27.8,"tmin":18.4,"precip_mm":14.1,"prob_chuva":51,"weathercode":96,"tempo":"trovoada","vento_kmh":25.3,"rajada_kmh":53.3,"vento_dir_graus":37,"et0_mm":3.34},{"data":"2026-07-20","tmax":26.3,"tmin":19.3,"precip_mm":22.1,"prob_chuva":60,"weathercode":95,"tempo":"trovoada","vento_kmh":25.8,"rajada_kmh":58.3,"vento_dir_graus":12,"et0_mm":4.0},{"data":"2026-07-21","tmax":20.8,"tmin":18.9,"precip_mm":65.6,"prob_chuva":67,"weathercode":95,"tempo":"trovoada","vento_kmh":10.9,"rajada_kmh":42.5,"vento_dir_graus":63,"et0_mm":1.04}],"fonte":"Open-Meteo","atualizado_em":"2026-07-15T05:07:38Z"},"colheita":{"pct_plantado":100.0,"pct_colhido":100.0,"area_soja_ha":9000,"fonte":"Emater/RS-Ascar (regional Santa Rosa, Fenasoja 30/04)","data_referencia":"2026-05-14","granularidade":"regional (Santa Rosa) aplicado ao municipio","regiao":"Santa Rosa","derivado":true,"ha_plantado_estim":9000,"ha_colhido_estim":9000}},{"id":"tucunduva","nome":"TUCUNDUVA","ibge":4322103,"uf":"RS","lat":-27.6573,"lon":-54.4439,"area_soja_ha":10540,"clima":{"ibge":4322103,"nome":"TUCUNDUVA","uf":"RS","lat":-27.6573,"lon":-54.4439,"atual":{"tmax":23.2,"tmin":10.1,"precip_mm":0.0,"prob_chuva":0,"weathercode":0,"tempo":"sol"},"previsao_7d":[{"data":"2026-07-15","tmax":23.2,"tmin":10.1,"precip_mm":0.0,"prob_chuva":0,"weathercode":0,"tempo":"sol","vento_kmh":18.3,"rajada_kmh":35.6,"vento_dir_graus":54,"et0_mm":3.04},{"data":"2026-07-16","tmax":27.7,"tmin":14.7,"precip_mm":0.0,"prob_chuva":2,"weathercode":0,"tempo":"sol","vento_kmh":22.7,"rajada_kmh":41.8,"vento_dir_graus":49,"et0_mm":4.22},{"data":"2026-07-17","tmax":28.7,"tmin":21.5,"precip_mm":0.0,"prob_chuva":4,"weathercode":1,"tempo":"parcial","vento_kmh":32.8,"rajada_kmh":63.0,"vento_dir_graus":23,"et0_mm":5.15},{"data":"2026-07-18","tmax":28.9,"tmin":20.0,"precip_mm":9.7,"prob_chuva":67,"weathercode":95,"tempo":"trovoada","vento_kmh":27.3,"rajada_kmh":56.2,"vento_dir_graus":11,"et0_mm":4.44},{"data":"2026-07-19","tmax":28.3,"tmin":19.1,"precip_mm":50.0,"prob_chuva":77,"weathercode":96,"tempo":"trovoada","vento_kmh":30.7,"rajada_kmh":55.8,"vento_dir_graus":29,"et0_mm":3.32},{"data":"2026-07-20","tmax":26.0,"tmin":19.4,"precip_mm":16.0,"prob_chuva":64,"weathercode":96,"tempo":"trovoada","vento_kmh":35.0,"rajada_kmh":67.7,"vento_dir_graus":9,"et0_mm":4.17},{"data":"2026-07-21","tmax":22.0,"tmin":18.9,"precip_mm":34.8,"prob_chuva":67,"weathercode":96,"tempo":"trovoada","vento_kmh":16.6,"rajada_kmh":38.2,"vento_dir_graus":125,"et0_mm":1.24}],"fonte":"Open-Meteo","atualizado_em":"2026-07-15T05:07:38Z"},"colheita":{"pct_plantado":100.0,"pct_colhido":100.0,"area_soja_ha":10540,"fonte":"Emater/RS-Ascar (regional Santa Rosa, Fenasoja 30/04)","data_referencia":"2026-05-14","granularidade":"regional (Santa Rosa) aplicado ao municipio","regiao":"Santa Rosa","derivado":true,"ha_plantado_estim":10540,"ha_colhido_estim":10540}},{"id":"tuparendi","nome":"TUPARENDI","ibge":4322301,"uf":"RS","lat":-27.7598,"lon":-54.4814,"area_soja_ha":13544,"clima":{"ibge":4322301,"nome":"TUPARENDI","uf":"RS","lat":-27.7598,"lon":-54.4814,"atual":{"tmax":22.9,"tmin":10.0,"precip_mm":0.0,"prob_chuva":0,"weathercode":0,"tempo":"sol"},"previsao_7d":[{"data":"2026-07-15","tmax":22.9,"tmin":10.0,"precip_mm":0.0,"prob_chuva":0,"weathercode":0,"tempo":"sol","vento_kmh":15.8,"rajada_kmh":32.0,"vento_dir_graus":48,"et0_mm":2.88},{"data":"2026-07-16","tmax":27.4,"tmin":14.4,"precip_mm":0.0,"prob_chuva":2,"weathercode":0,"tempo":"sol","vento_kmh":20.5,"rajada_kmh":37.1,"vento_dir_graus":47,"et0_mm":3.96},{"data":"2026-07-17","tmax":28.6,"tmin":21.6,"precip_mm":0.0,"prob_chuva":4,"weathercode":1,"tempo":"parcial","vento_kmh":31.2,"rajada_kmh":60.1,"vento_dir_graus":20,"et0_mm":4.95},{"data":"2026-07-18","tmax":28.7,"tmin":19.8,"precip_mm":15.1,"prob_chuva":67,"weathercode":95,"tempo":"trovoada","vento_kmh":25.8,"rajada_kmh":51.1,"vento_dir_graus":8,"et0_mm":4.13},{"data":"2026-07-19","tmax":28.2,"tmin":19.2,"precip_mm":62.9,"prob_chuva":77,"weathercode":96,"tempo":"trovoada","vento_kmh":26.3,"rajada_kmh":49.3,"vento_dir_graus":26,"et0_mm":3.12},{"data":"2026-07-20","tmax":25.5,"tmin":19.3,"precip_mm":21.2,"prob_chuva":64,"weathercode":96,"tempo":"trovoada","vento_kmh":29.9,"rajada_kmh":60.5,"vento_dir_graus":6,"et0_mm":3.8},{"data":"2026-07-21","tmax":22.3,"tmin":18.6,"precip_mm":33.6,"prob_chuva":67,"weathercode":96,"tempo":"trovoada","vento_kmh":16.0,"rajada_kmh":38.2,"vento_dir_graus":140,"et0_mm":1.35}],"fonte":"Open-Meteo","atualizado_em":"2026-07-15T05:07:38Z"},"colheita":{"pct_plantado":100.0,"pct_colhido":100.0,"area_soja_ha":13544,"fonte":"Emater/RS-Ascar (regional Santa Rosa, Fenasoja 30/04)","data_referencia":"2026-05-14","granularidade":"regional (Santa Rosa) aplicado ao municipio","regiao":"Santa Rosa","derivado":true,"ha_plantado_estim":13544,"ha_colhido_estim":13544}},{"id":"ubiretama","nome":"UBIRETAMA","ibge":4322343,"uf":"RS","lat":-28.0404,"lon":-54.686,"area_soja_ha":5100,"clima":{"ibge":4322343,"nome":"UBIRETAMA","uf":"RS","lat":-28.0404,"lon":-54.686,"atual":{"tmax":21.6,"tmin":10.7,"precip_mm":0.0,"prob_chuva":0,"weathercode":0,"tempo":"sol"},"previsao_7d":[{"data":"2026-07-15","tmax":21.6,"tmin":10.7,"precip_mm":0.0,"prob_chuva":0,"weathercode":0,"tempo":"sol","vento_kmh":24.5,"rajada_kmh":43.6,"vento_dir_graus":37,"et0_mm":3.23},{"data":"2026-07-16","tmax":25.9,"tmin":15.0,"precip_mm":0.0,"prob_chuva":4,"weathercode":0,"tempo":"sol","vento_kmh":26.9,"rajada_kmh":50.0,"vento_dir_graus":38,"et0_mm":4.42},{"data":"2026-07-17","tmax":27.9,"tmin":21.1,"precip_mm":0.0,"prob_chuva":2,"weathercode":0,"tempo":"sol","vento_kmh":37.0,"rajada_kmh":71.3,"vento_dir_graus":18,"et0_mm":5.09},{"data":"2026-07-18","tmax":27.8,"tmin":19.6,"precip_mm":46.4,"prob_chuva":76,"weathercode":96,"tempo":"trovoada","vento_kmh":29.5,"rajada_kmh":64.1,"vento_dir_graus":5,"et0_mm":4.21},{"data":"2026-07-19","tmax":27.3,"tmin":18.9,"precip_mm":52.5,"prob_chuva":84,"weathercode":96,"tempo":"trovoada","vento_kmh":29.7,"rajada_kmh":57.6,"vento_dir_graus":30,"et0_mm":3.08},{"data":"2026-07-20","tmax":24.5,"tmin":19.4,"precip_mm":24.1,"prob_chuva":76,"weathercode":96,"tempo":"trovoada","vento_kmh":34.9,"rajada_kmh":78.5,"vento_dir_graus":8,"et0_mm":4.01},{"data":"2026-07-21","tmax":21.3,"tmin":17.0,"precip_mm":42.2,"prob_chuva":81,"weathercode":96,"tempo":"trovoada","vento_kmh":17.2,"rajada_kmh":43.6,"vento_dir_graus":141,"et0_mm":1.2}],"fonte":"Open-Meteo","atualizado_em":"2026-07-15T05:07:38Z"},"colheita":{"pct_plantado":100.0,"pct_colhido":100.0,"area_soja_ha":5100,"fonte":"Emater/RS-Ascar (regional Santa Rosa, Fenasoja 30/04)","data_referencia":"2026-05-14","granularidade":"regional (Santa Rosa) aplicado ao municipio","regiao":"Santa Rosa","derivado":true,"ha_plantado_estim":5100,"ha_colhido_estim":5100}},{"id":"vista_gaucha","nome":"VISTA GAÚCHA","ibge":4323705,"uf":"RS","lat":-27.2902,"lon":-53.6974,"area_soja_ha":3800,"clima":{"ibge":4323705,"nome":"VISTA GAÚCHA","uf":"RS","lat":-27.2902,"lon":-53.6974,"atual":{"tmax":22.0,"tmin":8.7,"precip_mm":0.0,"prob_chuva":0,"weathercode":0,"tempo":"sol"},"previsao_7d":[{"data":"2026-07-15","tmax":22.0,"tmin":8.7,"precip_mm":0.0,"prob_chuva":0,"weathercode":0,"tempo":"sol","vento_kmh":14.1,"rajada_kmh":28.4,"vento_dir_graus":58,"et0_mm":2.58},{"data":"2026-07-16","tmax":25.9,"tmin":12.1,"precip_mm":0.0,"prob_chuva":0,"weathercode":0,"tempo":"sol","vento_kmh":17.9,"rajada_kmh":34.9,"vento_dir_graus":50,"et0_mm":3.34},{"data":"2026-07-17","tmax":26.7,"tmin":19.9,"precip_mm":0.0,"prob_chuva":2,"weathercode":0,"tempo":"sol","vento_kmh":27.6,"rajada_kmh":52.6,"vento_dir_graus":26,"et0_mm":4.36},{"data":"2026-07-18","tmax":27.5,"tmin":18.9,"precip_mm":5.0,"prob_chuva":24,"weathercode":95,"tempo":"trovoada","vento_kmh":25.9,"rajada_kmh":51.8,"vento_dir_graus":26,"et0_mm":4.12},{"data":"2026-07-19","tmax":26.8,"tmin":18.2,"precip_mm":16.0,"prob_chuva":41,"weathercode":96,"tempo":"trovoada","vento_kmh":20.4,"rajada_kmh":45.4,"vento_dir_graus":32,"et0_mm":3.07},{"data":"2026-07-20","tmax":26.8,"tmin":19.6,"precip_mm":15.8,"prob_chuva":50,"weathercode":95,"tempo":"trovoada","vento_kmh":23.0,"rajada_kmh":51.8,"vento_dir_graus":11,"et0_mm":3.55},{"data":"2026-07-21","tmax":20.8,"tmin":18.7,"precip_mm":60.6,"prob_chuva":69,"weathercode":96,"tempo":"trovoada","vento_kmh":8.1,"rajada_kmh":41.0,"vento_dir_graus":68,"et0_mm":0.78}],"fonte":"Open-Meteo","atualizado_em":"2026-07-15T05:07:38Z"},"colheita":{"pct_plantado":100.0,"pct_colhido":100.0,"area_soja_ha":3800,"fonte":"Emater/RS-Ascar (regional Santa Rosa, Fenasoja 30/04)","data_referencia":"2026-05-14","granularidade":"regional (Santa Rosa) aplicado ao municipio","regiao":"Santa Rosa","derivado":true,"ha_plantado_estim":3800,"ha_colhido_estim":3800}}],"alertas":{"ativos":[],"ufs":["RS"]},"colheita":{"status":"validado","fonte":"Emater/RS-Ascar - Informativo Conjuntural (via SEAPI-RS / Canal Rural)","granularidade":"estadual","data_referencia":"2026-06-11","cultura":"soja","itens":[{"regiao":"Rio Grande do Sul","uf":"RS","granularidade":"estadual","pct_plantado":100,"pct_colhido":100,"vs_media5anos":null,"vs_safra_anterior":null,"condicao_lavoura":"Safra encerrada; forte variabilidade regional (1.200-4.200 kg/ha); produtividade -14,8% vs projeção inicial","fonte":"Emater/RS-Ascar - Informativo Conjuntural (via SEAPI-RS / Canal Rural)","data_referencia":"2026-06-11","safra":"2025/2026","produtividade_kg_ha":2707,"area_ha":6690000,"producao_t":18132401,"var_producao_pct":32.9,"preco_rs_sc":129,"preco_data":"2026-07-03","preco_fonte":"Grao Direto (Centro Ocidental RS)"}]},"preco":{"valor":129,"uf":"RS","data":"2026-07-03","fonte":"Grao Direto (Centro Ocidental RS)","unidade":"R$/sc 60kg"}}